Workbook
Name _xlcn.WorksheetConnection_BGMatl1: BGMatl[]
Name _xlcn.WorksheetConnection_Cells1: Cells[]
Name _xlcn.WorksheetConnection_Distributors1: Distributors[]
Name _xlcn.WorksheetConnection_EOL_Tbl1: EOL_Tbl[]
Name _xlcn.WorksheetConnection_Equip1: Equip[]
Name _xlcn.WorksheetConnection_Modeling1: Modeling[]
Name _xlcn.WorksheetConnection_Other1: Other[]
Name _xlcn.WorksheetConnection_PackMod1: PackMod[]
Name _xlcn.WorksheetConnection_RandD1: RandD[]
Name _xlcn.WorksheetConnection_RawMatl1: RawMatl[]
Name _xlcn.WorksheetConnection_Service1: Service[]
Name AEO: [2]Safety!$L$2
Name Co_2306: '[3]Co_CoSO4 forecast'!$V$182
Name Co_p25: '[3]Co_CoSO4 forecast'!$AA$25
Name Co_p50: '[3]Co_CoSO4 forecast'!$AA$24
Name Co_p75: '[3]Co_CoSO4 forecast'!$AA$23
Name compa: [4]PROVP!#REF!
Name Comparaison: [4]PROVP!$A:$A
Name cut_allowed_LT: [2]Safety!$L$6
Name cut_allowed_PC: [2]Safety!$L$5
Name cut_safety_LT: [2]Safety!$AK$8
Name cut_safety_PC: [2]Safety!$AK$7
Name ExternalData_1: Professional!#REF!
Name gC_kWh: [5]INPUTS!$B$32
Name gCO2_gC: [5]INPUTS!$B$34
Name Impres_titres_MI: [4]PROVP!$A:$A
Name Li_2306: [3]LCE!$V$170
Name Li_histprice: [3]LCE!$V$97:$V$170
Name Li_p25: [3]LCE!$AA$13
Name Li_p50: [3]LCE!$AA$12
Name Li_p75: [3]LCE!$AA$11
Name mode: [6]Config!$AD$7:$AD$19
Name Ni_2306: '[3]Ni_NiSO4 forecast'!$V$188
Name Ni_p25: '[3]Ni_NiSO4 forecast'!$AA$31
Name Ni_p50: '[3]Ni_NiSO4 forecast'!$AA$30
Name Ni_p75: '[3]Ni_NiSO4 forecast'!$AA$29
Name P91_: [4]PROVP!#REF!
Name P92_: [4]PROVP!#REF!
Name Renewable_and_Non_Renewable_Generation: [7]Contents!#REF!
Name Scenario: [8]Targets_byFleet!$A$1
Name T2MT: [9]Fuel_Specs!$F$135
Name TableName: "Dummy"
Name Transmission_loss: [5]kWhpMi!$G$1
Name UF_REEV20: [5]kWhpMi!$M$5
Name UF_REEV40: [5]kWhpMi!$M$4
Name WRcap_2021: [2]Safety!$L$3
Name WRcap_2025: [2]Safety!$L$4
Name Zone_impres_MI: [4]PROVP!$B$5:$B$90
Name _2014_eGRID_Subregion_File: #REF!
Name tblVspecsData: #REF!
Name tblVspecsHeader: #REF!
Name SearchType: 'Search List'!$A$2:$A$4
Name EOLSearch: 'Search List'!$C$2:$C$4
Name SearchType: #REF!
Name ExternalData_3: Append2!$A$1:$AN$1188
Name cost11: #REF!

Sheet literature review
C2: Yu et al., 2024 https://www.sciencedirect.com/science/article/abs/pii/S0378775323013319#:~:text=Manufacturing%20scraps%20refer%20to%20the,manufacturing%20scraps%20and%20spent%20batteries.&text=Not%20yet%20undergone%20cycling%20and,end%20of%20its%20operational%20lifespan.&text=Primarily%20from%20the%20used%20EVs%2C%20electronic%20devices%2C%20etc.
C4: "It’s reported that the scrap rate should be maintained below 10% to ensure profitability in battery manufacturing plants"
C6: "Circular Energy Storage (CES) estimates a global average scrap rate of 7.67% for 2023 and anticipates a decline to 4.34% by 2030 due to continuous improvements in the production process. However, at the current stage, given that many gigafactories are still taking steps to build plants and improve the manufacturing process, the rapid growth of the new production line results in high initial scrap rates."
C12: The ICCT data includes IRA-funded projecgts that are mostly planned facilities
C13: The NAATBatt data includes mostly those that are already commercial
C16: Operating capacity: https://www.broadn.io/blogs/on-us-manufacturing-capacity-utilization

Sheet Narrowed Manu facilities
A1: Source | B1: Status | C1: Supply Chain Segment | D1: Company | E1: Product/Facility Type | F1: Product | G1: Chemistry | H1: Facility State or Province | I1: Production Capacity | J1: Production Units | K1: Year online | L1: Notes on production capacity
A2: NaatBatt 2025 | C2: Midstream | D2: Blue Solutions Canada Inc. | G2: - | H2: QC | I2: 0.2 | J2: GWh/yr | K2: 2025 | L2: Solid state
A3: NaatBatt 2025 | C3: Midstream | D3: LI-CAP Technologies | G3: - | H3: CA | I3: 0.3 | J3: GWh/yr | K3: 2025 | L3: Cathode component https://www.nacleanenergy.com/energy-storage/licap-technologies-and-california-energy-commission-celebrate-major-milestone-in-u-s-battery-manufacturing-with-launch-of-300-mwh-dry-electrode-production-line?utm_source=chatgpt.com
A4: NaatBatt 2025 | C4: Midstream | D4: Enovix | G4: LCO | H4: CA | I4: 0.2 | J4: GWh/yr | K4: 2025
A5: NaatBatt 2025 | C5: Midstream | D5: Xerion Advanced Battery Corp | G5: LCO | H5: OH | I5: 1 | J5: GWh/yr | K5: 2025 | L5: https://www.iarpa.gov/images/PropsersDayPDFs/RESILIENCE/Xerion_Capabilities_Statement.pdf?utm_source=chatgpt.com
A6: NaatBatt 2025 | C6: Midstream | D6: Xerion Advanced Battery Corp | G6: LCO | H6: OH | K6: 2029 | L6: Refining
A7: NaatBatt 2025 | C7: Midstream | D7: Xerion Advanced Battery Corp | G7: LCO | H7: OH | K7: 2029 | L7: Refining
A8: NaatBatt 2025 | B8: Commercial | C8: Downstream | D8: Ford Motor Company | E8: Cell Assemblies/ Groupings | F8: Packs | G8: LFP | H8: MI | I8: 2 | J8: GWh/Yr | K8: 2025
A9: NaatBatt 2025 | B9: Commercial | C9: Downstream | D9: HiTHIUM Energy Storage Technology USA Inc. | E9: Assembly and Integration | F9: Battery Energy Storage | G9: LFP | H9: CA | I9: 10 | J9: GWh/yr | K9: 2025
A10: NaatBatt 2025 | B10: Commercial | C10: Downstream | D10: Lithion Battery | E10: Cell Assemblies/ Groupings | F10: Modules/ Arrays | G10: LFP | H10: NV | I10: 5 | J10: GWh/Yr | K10: 2025
A11: NaatBatt 2025 | B11: Commercial | C11: Downstream | D11: NP Power | E11: Manufacturing | F11: Cells and Cell Assemblies LPF and other chemistries | G11: LFP | H11: CA | I11: 2 | J11: GWh/yr | K11: 2025
A12: NaatBatt 2025 | B12: Commercial | C12: Downstream | D12: Sparkz Inc. | E12: Cell Assemblies/ Groupings | F12: Packs | G12: LFP | H12: CA | I12: 1 | J12: GWh/Yr | K12: 2025
A13: EDF | B13: Under construction | C13: Downstream | D13: Our Next Energy, Inc. | E13: Cell Assemblies/ Groupings | F13: Packs | G13: LFP | H13: MI | I13: 20 | J13: GWh/yr | K13: 2027 | L13: https://insideevs.com/news/615476/one-20gwh-battery-lfp-gigafactory-michigan/1000/
A14: EDF | C14: Downstream | D14: Canadian Solar | F14: Battery | G14: LFP | H14: TN | I14: 6 | J14: GWh/yr | K14: 2026 | L14: the note here makes it seem promising but there were a lot of large numbers online
A15: ICCT | C15: Downstream | D15: General Motors & Samsung SDI | F15: Battery | G15: LFP | H15: IN | I15: =36-27 -> 9 | J15: GWh/yr | K15: 2027 | L15: https://techcrunch.com/2023/06/13/gm-and-partner-samsung-sdi-pick-indiana-for-3b-battery-factory/#:~:text=Indiana%20Gov.,for%20most%20of%20its%20vehicles.
A16: NaatBatt 2025 | C16: Downstream | D16: Xos Trucks | F16: Packs | G16: LFP | H16: TN | I16: =2000*100/1000000 -> 0.2 | J16: GWh/yr | K16: 2025 | L16: https://www.aviseanalytics.com/xos-driving-a-path-to-profitability-in-the-ev-industry/#:~:text=for%20Xos%20products.-,Image%20Source:%20Company,changes%20and%20a%20second%20shift.
A17: NaatBatt 2025 | C17: Midstream | D17: A123 Systems | G17: LFP | H17: MI | I17: 0.969 | J17: GWh/yr | K17: 2025
A18: NaatBatt 2025 | C18: Midstream | D18: American Battery Factory | G18: LFP | H18: AZ | I18: 4 | J18: GWh/yr | K18: 2027
A19: NaatBatt 2025 | C19: Midstream | D19: Amplify Cell Technologies | G19: LFP | H19: MS | I19: 21 | J19: GWh/yr | K19: 2027 | L19: duplicate— https://www.businesswire.com/news/home/20240701093920/en/Amplify-Cell-Technologies-Begins-Construction-of-Mississippi-Battery-Cell-Factory?utm_source=chatgpt.com
A20: NaatBatt 2025 | C20: Midstream | D20: Dragonfly Energy Holdings Corp | G20: LFP | H20: NV | I20: 0.15 | J20: GWh/yr | K20: 2025
A21: NaatBatt 2025 | C21: Midstream | D21: Enpower Greentech | G21: LFP | H21: MI | I21: 0.2 | J21: GWh/yr | K21: 2025 | L21: https://www.enpower-energy.com/en/news/usa-battery-development-manufacturing-updates?utm_source=chatgpt.com
A22: NaatBatt 2025 | C22: Midstream | D22: e-Storage | G22: LFP | H22: KY | I22: 6 | J22: GWh/yr | K22: 2029
A23: NaatBatt 2025 | C23: Midstream | D23: Five Stone Energy | G23: LFP | H23: VA | K23: 2029 | L23: Not cell manufacturing
A24: NaatBatt 2025 | C24: Midstream | D24: Ford Motor Company | G24: LFP | H24: MI | I24: 20 | J24: GWh/yr | K24: 2029
A25: NaatBatt 2025 | C25: Midstream | D25: Gotion | G25: LFP | H25: MI | I25: 68 | J25: GWh/yr | K25: 2029 | L25: https://publications.anl.gov/anlpubs/2024/03/187735.pdf?utm_source=chatgpt.com
A26: EDF | C26: Midstream | D26: Guoxuan High Tech Co. | E26: LFP | F26: Cells | G26: LFP | H26: IL | I26: 50 | J26: GWh/yr | K26: 2024 | L26: https://www.evlithium.com/Blog/gotion-lifepo4-battery.html#:~:text=The%20factory%2C%20with%20a%20planned%20investment%20of,expected%20to%20go%20into%20production%20next%20year. https://www.batterytechonline.com/battery-manufacturing/gotion-in-motion-guoxuan-high-tech-keeps-going-growing
A27: NaatBatt 2025 | C27: Midstream | D27: LG Energy Solution Ltd | G27: LFP | H27: AZ | I27: 17 | J27: GWh/yr | K27: 2029
A28: NaatBatt 2025 | C28: Midstream | D28: Lithion Battery, Inc. | G28: LFP | H28: NV | I28: 0.2 | J28: GWh/yr | K28: 2025
A29: NaatBatt 2025 | C29: Midstream | D29: Lithion Battery, Inc. | G29: LFP | H29: AB | K29: 2025 | L29: Small facility
A30: NaatBatt 2025 | C30: Midstream | D30: Our Next Energy, Inc. | G30: LFP | H30: MI | I30: 0.01 | J30: GWh/yr | K30: 2025
A31: NaatBatt 2025 | C31: Midstream | D31: Pomega Energy Storage Technologies | G31: LFP | H31: SC | I31: 3 | J31: GWh/yr | K31: 2027
A32: NaatBatt 2025 | C32: Midstream | D32: Rolled-Ribbon Battery Company | G32: LFP | H32: TX | K32: 2025 | L32: Small facility https://www.crunchbase.com/organization/rolled-ribbon-battery-company?utm_source=chatgpt.com
A33: ICCT | C33: Midstream | D33: Sparkz | E33: LFP | F33: Cells | G33: LFP | H33: WV | I33: 15 | J33: GWh/yr | K33: 2028 | L33: https://autotechinsight.spglobal.com/feed?fs_site_area[0]=news&fs_tags[8][0]=41199
A34: NaatBatt 2025 | C34: Midstream | D34: Stryten Energy | G34: LFP | H34: KS | K34: 2025 | L34: Seem to focus on military
A35: NaatBatt 2025 | C35: Midstream | D35: Stryten Energy | G35: LFP | H35: ON | K35: 2025 | L35: Military
A36: NaatBatt 2025 | C36: Midstream | D36: Ultralife Corp | G36: LFP | H36: NY | I36: 0.05 | J36: GWh/yr | K36: 2025 | L36: https://www.ultralifecorp.com/ECommerce/product/ubi-2590/bb-2590-rechargeable-batteries/ubbl02-01-cb/ubi-2590-li-ion-cb
A37: NaatBatt 2025 | B37: Commercial | C37: Downstream | D37: Altairnano | E37: Cell Assemblies/ Groupings | F37: Modules/ Arrays | G37: LTO | H37: IN | I37: 0.26 | J37: GWh/yr | K37: 2025
A38: NaatBatt 2025 | C38: Midstream | D38: Altairnano | G38: LTO | H38: IN | I38: 0.26 | J38: GWh/yr | K38: 2025 | L38: https://pdf.secdatabase.com/219/0001437749-17-009565.pdf?utm_source=chatgpt.com
A39: NaatBatt 2025 | C39: Midstream | D39: ABSL Power Solutions, Inc. | G39: NA | H39: CO | K39: 2025 | L39: Military
A40: NaatBatt 2025 | B40: Commercial | C40: Downstream | D40: Clarios | E40: Cell Assemblies/ Groupings | F40: Packs | G40: NCA | H40: MI | I40: 2 | J40: GWh/yr | K40: 2025
A41: NaatBatt 2025 | B41: Commercial | C41: Downstream | D41: Electrovaya | E41: Battery Development | F41: Lithium-ion batteries | G41: NCA | H41: NY | I41: 0.5 | J41: GWh/yr | K41: 2025
A42: NaatBatt 2025 | B42: Commercial | C42: Downstream | D42: Tesla | E42: Cell Assemblies/ Groupings | F42: Packs | G42: NCA | H42: TX | I42: 100 | J42: GWh/Yr | K42: 2025
A43: NaatBatt 2025 | B43: Commercial | C43: Downstream | D43: Tesla Inc. | E43: Cell Assemblies/ Groupings | F43: Packs | G43: NCA | H43: NV | I43: 20 | J43: GWh | K43: 2025
A44: NaatBatt 2025 | B44: Commercial | C44: Downstream | D44: Tesla Inc. | E44: Assembly and Integration | F44: Packs Modules | G44: NCA | H44: CA | I44: 40 | J44: GWh/yr | K44: 2025
A45: EDF | C45: Downstream | D45: Tesla Motors, Inc. | F45: Packs | G45: NCA | H45: NV | I45: 139 | J45: GWh/yr | K45: 2027 | L45: https://techcrunch.com/2025/02/06/tracking-the-ev-battery-factory-construction-boom-across-north-america/#:~:text=Tesla%20in%20January%202023%20announced,in%202025%20before%20scaling%20production.
A46: NaatBatt 2025 | C46: Downstream | D46: VinFast | F46: Battery | G46: NCA | H46: NC | I46: =150000*100/1000000 -> 15 | J46: GWh/yr | K46: 2028 | L46: https://en.baochinhphu.vn/vinfast-to-build-electric-vehicle-and-battery-manufacturing-factory-in-us-111220330140457811.htm
A47: NaatBatt 2025 | C47: Midstream | D47: Clarios | G47: NCA | H47: MI | I47: 0.001 | J47: GWh/yr | K47: 2025
A48: NaatBatt 2025 | C48: Midstream | D48: EaglePicher Technologies, LLC | G48: NCA | H48: MO | I48: 0.2 | J48: GWh/yr | K48: 2025 | L48: Military application
A49: NaatBatt 2025 | C49: Midstream | D49: Electrovaya | G49: NCA | H49: NY | I49: 0.5 | J49: GWh/yr | K49: 2025
A50: NaatBatt 2025 | C50: Midstream | D50: Tesla Inc | G50: NCA | H50: CA | I50: 4 | J50: GWh/yr | K50: 2025
A51: NaatBatt 2025 | C51: Midstream | D51: Tesla Inc, Panasonic Corp | G51: NCA | H51: NV | I51: 10 | J51: GWh/yr | K51: 2029
A52: NaatBatt 2025 | C52: Midstream | D52: Tesla Inc. | G52: NCA | H52: TX | I52: 10 | J52: GWh/yr | K52: 2025
A53: NaatBatt 2025 | B53: Commercial | C53: Downstream | D53: AESC | E53: Cell Assemblies/ Groupings | F53: Packs | G53: NMC | H53: TN | I53: 40 | J53: GWj/Yr | K53: 2025 | L53: Pivoting to stationary storage - https://www.just-auto.com/news/aesc-halts-construction-of-us-ev-battery-plant/ https://aesc-group.com/news/aesc-and-bmw-group-announce-new-partnership-in-battery-cell-production-and-supply
A54: NaatBatt 2025 | B54: Commercial | C54: Downstream | D54: BlueOvalSK (JV - Ford and SK ON) | E54: Cell Assemblies/ Groupings | F54: Packs | G54: NMC | H54: KY | I54: 20 | J54: GWh/Yr | K54: 2025
A55: NaatBatt 2025 | B55: Commercial | C55: Downstream | D55: BMZ USA Inc. | E55: Assembly and Integration | F55: Packs | G55: NMC | H55: VA | I55: 2 | J55: GWh/yr | K55: 2025
A56: NaatBatt 2025 | B56: Commercial | C56: Downstream | D56: EnerSys | E56: Cell Assemblies/ Groupings | F56: Packs | G56: NMC | H56: GA | I56: 4 | J56: GWh/yr | K56: 2027
A57: NaatBatt 2025 | B57: Commercial | C57: Downstream | D57: Ionblox | E57: Cell Assemblies/ Groupings | F57: Modules/ Arrays | G57: NMC | H57: CA | I57: 0.005 | J57: GWh/yr | K57: 2025
A58: NaatBatt 2025 | B58: Commercial | C58: Downstream | D58: LG Energy Solution Michigan Inc. | E58: Cell Assemblies/ Groupings | F58: Packs | G58: NMC | H58: MI | I58: 5 | J58: GWh | K58: 2025
A59: NaatBatt 2025 | B59: Commercial | C59: Downstream | D59: Mercedes-Benz | E59: Manufacturing | F59: Packs | G59: NMC | H59: AL | I59: 15 | J59: GWh/yr | K59: 2025
A60: NaatBatt 2025 | B60: Commercial | C60: Downstream | D60: Saft America, Inc. | E60: Cell Assemblies/ Groupings | F60: Modules/ Arrays | G60: NMC | H60: GA | I60: 2 | J60: GWh/Yr | K60: 2025
A61: NaatBatt 2025 | B61: Commercial | C61: Downstream | D61: Saft America, Inc. | E61: Cell Assemblies/ Groupings | F61: Packs | G61: NMC | H61: NC | I61: 5 | J61: GWh/Yr | K61: 2025
A62: NaatBatt 2025 | B62: Commercial | C62: Downstream | D62: Samsung SDI America Inc. | E62: Cell Assemblies/ Groupings | F62: Modules/ Arrays | G62: NMC | H62: MI | I62: 27 | J62: GWh/Yr | K62: 2025
A63: NaatBatt 2025 | B63: Commercial | C63: Downstream | D63: Samsung SDI America Inc. | E63: Cell Assemblies/ Groupings | F63: Packs | G63: NMC | H63: MI | I63: 36 | J63: GWh/Yr | K63: 2025
A64: NaatBatt 2025 | B64: Commercial | C64: Downstream | D64: Toyota | E64: Manufacturing | F64: Packs | G64: NMC | H64: KY | I64: 7 | J64: GWh/yr | K64: 2025
A65: NaatBatt 2025 | B65: Planned | C65: Downstream | D65: AESC | E65: Cell Assemblies/ Groupings | F65: Packs | G65: NMC | H65: KY | I65: 30 | J65: GWh/Yr | K65: 2026 | L65: Reports state 2025- but yet to be open https://us.aesc-group.com/aesc-celebrates-structural-completion-milestone-at-state-of-the-art-gigafactory-in-bowling-green/
A66: NaatBatt 2025 | B66: Planned | C66: Downstream | D66: BlueOvalSK (JV - Ford and SK ON) | E66: Cell Assemblies/ Groupings | F66: Packs | G66: NMC | H66: TN | I66: 43 | J66: GWh/Yr | K66: 2027 | L66: https://www.commercialappeal.com/story/money/business/2025/08/19/blueoval-sk-battery-production-delay-west-tennessee/85725474007/
A67: NaatBatt 2025 | B67: Planned | C67: Downstream | D67: Gotion | E67: Cell Assemblies/ Groupings | F67: Other/ Unknown | G67: NMC | H67: IL | I67: 10 | J67: GWh/yr | K67: 2026 | L67: https://autotechinsight.spglobal.com/news/5283484/gotion-to-start-ev-battery-production-in-manteno-in-september-with-five-production-lines
A68: NaatBatt 2025 | B68: Planned | C68: Downstream | D68: Rivian | E68: Cell Assemblies/ Groupings | F68: Packs | G68: NMC | H68: GA | I68: 50 | J68: GWh/Yr | K68: 2028 | L68: https://www.esgdive.com/news/rivian-kickoff-georgia-plant-gov-brian-kemp/758268/
A69: NaatBatt 2025 | B69: Planned | C69: Downstream | D69: Statevolt | E69: Cell Assemblies/ Groupings | F69: Packs | G69: NMC | H69: CA | I69: 54 | J69: GWh/yr | K69: 2026 | L69: https://statevolt.com/manufacturing/imperial-valley-gigafactory/
A70: NaatBatt 2025 | B70: Pre-commercial/ startup | C70: Downstream | D70: American Lithium Energy | E70: Cell Assemblies/ Groupings | F70: Packs | G70: NMC | H70: CA | I70: 0.2 | J70: GWh/Yr | K70: 2025
A71: NaatBatt 2025 | B71: Under construction | C71: Downstream | D71: BMW Group Inc | E71: Assembly and Integration | F71: Packs | G71: NMC | H71: SLP | I71: 8.75 | J71: GWh/yr | K71: 2026 | L71: https://www.bmwblog.com/2024/10/30/bmw-lithium-battery-production-mexico-san-luis-potosi/
A72: NaatBatt 2025 | B72: Under Construction | C72: Downstream | D72: BMW Manufacturing | E72: Cell Assemblies/ Groupings | F72: Packs | G72: NMC | H72: SC | I72: =22500*80/1000000 -> 1.8 | J72: GWh/yr | K72: 2025 | L72: 22500 units per year, assuming each unit is 80 kwh
A73: EDF | B73: Under construction | C73: Downstream | D73: LG Energy Solution Michigan Inc. | E73: Cell Assemblies/ Groupings | F73: Packs | G73: NMC | H73: MI | I73: 21.5 | J73: GWh/yr | K73: 2026 | L73: https://lgenergymi.com/growth/lg-energy-solution-michigan-inc-tops-out-new-production-facility/
A74: EDF | C74: Downstream | D74: BorgWarner | F74: Battery | G74: NMC | H74: TN | I74: 3 | J74: GWh/yr | K74: 2024 | L74: https://finance.yahoo.com/news/borgwarner-bwa-makes-62m-electrification-113411082.html
A75: ICCT | C75: Downstream | D75: Freudenberg | F75: Modules, Packs | G75: NMC | H75: MI | I75: 19 | J75: GWh/yr | K75: 2025 | L75: https://www.freudenberg.com/en/company/press-media/news-detail/2023-02-02-freudenberg-e-power-systems-and-lg-energy-solution-sign-long-term-supply-partnership-for-battery-cell-modules
A76: ICCT | C76: Downstream | D76: Hyundai Motor Group SK and LG | F76: Modules | G76: NMC | H76: GA | I76: 35 | J76: GWh/yr | K76: 2026 | L76: https://businessalabama.com/hyundai-motor-group-and-sk-on-to-build-battery-cell-plant-in-georgia/
A77: ICCT | C77: Downstream | D77: Toyota | F77: Battery | G77: NMC | H77: NC | I77: 30 | J77: GWh/yr | K77: 2025 | L77: https://pressroom.toyota.com/toyota-charges-into-u-s-battery-manufacturing/
A78: NaatBatt 2025 | C78: Midstream | D78: AESC | G78: NMC | H78: TN | I78: 3 | J78: GWh/yr | K78: 2025
A79: NaatBatt 2025 | C79: Midstream | D79: American Lithium Energy | G79: NMC | H79: CA | K79: 2025 | L79: Military application
A80: NaatBatt 2025 | C80: Midstream | D80: BlueOvalSK (JV of Ford and SK On) | G80: NMC | H80: KY | I80: 20 | J80: GWh/yr | K80: 2027 | L80: https://www.energy.gov/sites/default/files/2022-12/DOE-LPO_BlueOval_SK_EA_and_DRAFT_FONSI.pdf?utm_source=chatgpt.com
A81: NaatBatt 2025 | C81: Midstream | D81: BlueOvalSK (JV of Ford and SK On) | G81: NMC | H81: TN | I81: 43 | J81: GWh/yr | K81: 2027
A82: NaatBatt 2025 | C82: Midstream | D82: EaglePicher Technologies, LLC | G82: NMC | H82: MO | K82: 2025 | L82: Military application
A83: NaatBatt 2025 | C83: Midstream | D83: Electrovaya | G83: NMC | H83: ON | I83: 0.5 | J83: GWh/yr | K83: 2025
A84: NaatBatt 2025 | C84: Midstream | D84: Electrovaya | G84: NMC | H84: ON | I84: 0.5 | J84: GWh/yr | K84: 2025
A85: NaatBatt 2025 | C85: Midstream | D85: EnerSys | G85: NMC | H85: CA | I85: 0 | K85: 2025 | L85: Closed
A86: NaatBatt 2025 | C86: Midstream | D86: EnerSys | G86: NMC | H86: PA | I86: 0.07 | J86: GWh/yr | K86: 2025
A87: NaatBatt 2025 | C87: Midstream | D87: EnerSys | G87: NMC | H87: SC | I87: 4 | J87: GWh/yr | K87: 2029 | L87: https://investor.enersys.com/node/22481/pdf/
A88: NaatBatt 2025 | C88: Midstream | D88: Enovix | G88: NMC | H88: CA | I88: 0.2 | J88: GWh/yr | K88: 2025
A89: NaatBatt 2025 | C89: Midstream | D89: Enpower Greentech | G89: NMC | H89: IN | I89: 0.8 | J89: GWh/yr | K89: 2025
A90: NaatBatt 2025 | C90: Midstream | D90: Five Stone Energy | G90: NMC | H90: VA | K90: 2029 | L90: Not cell manufacturing
A91: NaatBatt 2025 | C91: Midstream | D91: Forge Nano | G91: NMC | H91: CO | K91: 2025 | L91: Supplemental
A92: NaatBatt 2025 | C92: Midstream | D92: Forge Nano - Forge Battery | G92: NMC | H92: NC | I92: 1 | J92: GWh/yr | K92: 2027
A93: NaatBatt 2025 | C93: Midstream | D93: General Motors (GM) - Samsung SDI JV | G93: NMC | H93: IN | I93: 36 | J93: GWh/yr | K93: 2029 | L93: https://insideevs.com/news/731721/gm-samsung-sdi-indiana-ev-battery-factory-official-delay/
A94: NaatBatt 2025 | C94: Midstream | D94: Gotion | G94: NMC | H94: IL | I94: 40 | J94: GWh/yr | K94: 2029
A95: NaatBatt 2025 | C95: Midstream | D95: Ionblox | G95: NMC | H95: CA | I95: 0.005 | J95: GWh/yr | K95: 2025 | L95: https://milpwr.org/wp-content/uploads/2024/06/Ionblox_High-Energy-and-High-Power-Silicon-Anode-LIBs_DPEC_6-4-24-Herman-Lopez.pdf?utm_source=chatgpt.com
A96: NaatBatt 2025 | C96: Midstream | D96: LG Energy Solution | G96: NMC | H96: MI | I96: 50 | J96: GWh/yr | K96: 2027
A97: NaatBatt 2025 | C97: Midstream | D97: LG Energy Solution Ltd | G97: NMC | H97: MI | I97: 5 | J97: GWh/yr | K97: 2027
A98: NaatBatt 2025 | C98: Midstream | D98: LG Energy Solution Ltd | G98: NMC | H98: MI | I98: 16.5 | J98: GWh/yr | K98: 2025
A99: NaatBatt 2025 | C99: Midstream | D99: LG Energy Solution Ltd | G99: NMC | H99: AZ | I99: 36 | J99: GWh/yr | K99: 2027
A100: NaatBatt 2025 | C100: Midstream | D100: Nanotech Energy | G100: NMC | H100: CA | I100: 0.15 | J100: GWh/yr | K100: 2025 | L100: https://battery-tech.net/company/nanotech-energy/?utm_source=chatgpt.com
...

Sheet Manu facilities incl removed
A1: Source | B1: Status | C1: Supply Chain Segment | D1: Included in old sheet? | E1: Company | F1: Facility Name | G1: Product/Facility Type | H1: Product | I1: Company Website | J1: Facility Address | K1: Facility City | L1: Facility State or Province | M1: Facility Country | N1: Facility Zip | O1: Facility Phone | P1: Latitude | Q1: Longitude | R1: Facility Workforce | S1: Production Capacity | T1: Production Units | U1: Year online | V1: Notes on production capacity | W1: HQ Company | X1: HQ Company Website | Y1: HQ City | Z1: HQ State or Province | AA1: HQ Country | AB1: QC | AC1: QC Date | AD1: Sources | AE1: Notes | AF1: Brief Company Profile | AG1: Sources2 | AH1: Summary Word Count | AI1: Contact | AJ1: Contact Email | AK1: Contact Phone | AL1: Column1
A2: NaatBatt 2025 | B2: Commercial | C2: Downstream | D2: N | E2: Altairnano | F2: Altairnano | G2: Cell Assemblies/ Groupings | H2: Modules/ Arrays | I2: https://altairnano.com/ | J2: 7307 Quality Circle | K2: Anderson | L2: IN | M2: US | N2: 46013 | O2: 317-333-7617 | P2: 40.040045 | Q2: -85.728025 | S2: 0.26 | T2: GWh/yr | U2: 2025 | W2: Altairnano | X2: https://altairnano.com/ | Y2: Reno | Z2: NV | AA2: US | AB2: EW MK | AC2: 8/9/2021 8/14/2025 | AD2: altairnano.com | AE2: LTO Battery Module; Closed its Reno manuf. Facility and moved it to China. Initial facility in Anderson is listed as permanently closed; BNEF does not list it; Unsure if it makes cells in US. Called and emailed | AF2: Altairnano leverages nanoscale technologies for powerful lithium titanate solutions. Its unique nano cells bring advantages to electric grid, transportation, and industrial applications. | AG2: https://altairnano.com/ | AH2: 22
A3: NaatBatt 2025 | E3: A123 Systems | L3: MI | S3: 0.969 | T3: GWh/yr | U3: 2025
A4: NaatBatt 2025 | B4: Commercial | C4: Downstream | D4: N | E4: AA Portable Power Corp. | F4: AA Portable Power Corp. | G4: Cell Assemblies/ Groupings | H4: Packs | I4: https://www.batteryspace.com/?gad=1&gclid=Cj0KCQjwk96lBhDHARIsAEKO4xY2o39jDdsYILun_GXH8PAloFNva54KUidx4aN6RDw6Uc46SGLc530aAjq2EALw_wcB | J4: 825 South 19th Street | K4: Richmond | L4: CA | M4: US | N4: 94804 | O4: 510-525-2328 | P4: 37.920848 | Q4: -122.35225 | R4: 30 | U4: 2025 | W4: AA Portable Power Corp. | X4: https://www.batteryspace.com/?gad=1&gclid=Cj0KCQjwk96lBhDHARIsAEKO4xY2o39jDdsYILun_GXH8PAloFNva54KUidx4aN6RDw6Uc46SGLc530aAjq2EALw_wcB | Y4: Richmond | Z4: CA | AA4: US | AB4: EW | AC4: 44417 | AD4: Thomasnet: Battery Packs / manufacturers; batteryspace.com | AE4: Mostly a battery distributor, but has production lines for custom order battery packs and battery testing. Workforce Range: 10-49 | AF4: AA Portable Power Corp. (dba: Batteryspace.com) was founded in 2000 and became a reputable battery manufacturer over the years. | AG4: https://www.batteryspace.com/?gad=1&gclid=Cj0KCQjwk96lBhDHARIsAEKO4xY2o39jDdsYILun_GXH8PAloFNva54KUidx4aN6RDw6Uc46SGLc530aAjq2EALw_wcB, https://www.batteryspace.com/contactus.aspx | AH4: 19
A5: NaatBatt 2025 | E5: ABSL Power Solutions, Inc. | L5: CO | S5: - | T5: GWh/yr | U5: 2025 | X5: Military
A6: NaatBatt 2025 | B6: Commercial | C6: Downstream | D6: y- updated capacity | E6: Accelera by Cummins | F6: Accelera | G6: Assembly and Integration | H6: Integrated Battery Packs for Trucks and Energy Storage | I6: https://www.accelerazero.com | J6: 500 Jackson St | K6: Columbus | L6: IN | M6: US | N6: 47201 | P6: 40.604878 | Q6: -85.858078 | S6: 2 | T6: GWh/yr | U6: 2025 | W6: Cummins | X6: https://www.cummins.com | Y6: Columbus | Z6: IN | AA6: US | AB6: AP | AC6: 45529 | AD6: https://www.cummins.com/news/releases/2023/03/08/cummins-launches-accelera-cummins-advance-transition-zero-emissions-future | AE6: CUMMINS LAUNCHES ACCELERA BY CUMMINS TO ADVANCE THE TRANSITION TO A ZERO-EMISSIONS FUTURE | AF6: Accelera by Cummins provides a diverse portfolio of zero-emission solutions including lithium batteries for the world’s most economically vital industries, empowering them to accelerate the transition to a sustainable future. | AH6: 30
A7: NaatBatt 2025 | B7: Pre-commercial/ startup | C7: Downstream | D7: N | E7: Acculon Energy | F7: Rev1 | G7: Cell Assemblies/ Groupings | H7: Packs | I7: https://acculonenergy.com/ | J7: 1305 Kinnear Rd | K7: Columbus | L7: OH | M7: US | N7: 43212 | O7: 614-259-7792 | P7: 39.997633 | Q7: -83.04217 | R7: 15 | S7: 2 | T7: GWh/yr | U7: 2025 | V7: https://acculonenergy.com/acculon-energy-announces-strategic-initiative-for-a-manufacturing-facility/ | W7: Acculon Energy | X7: https://acculonenergy.com/ | Y7: Columbus | Z7: OH | AA7: US | AB7: SD | AC7: 45432 | AD7: Questionnaire | AF7: Acculon Energy is a battery system developer and manufacturer. It provides an innovative end-to-end approach for accelerating market entry while minimizing risk during commercialization. | AG7: Questionnaire | AH7: 24 | AI7: Betsy Barry | AJ7: betsy.barry@acculonenergy.com | AK7: 706-206-7271
A8: NaatBatt 2025 | B8: Planned | C8: Downstream | D8: N | E8: AESC | F8: Bowling Green Plant | G8: Cell Assemblies/ Groupings | H8: Packs | I8: https://www.aesc-group.com/en/ | J8: Kentucky Transpark | K8: Bowling Green | L8: KY | M8: US | N8: 42101 | O8: 502-377-5675 | P8: 37.04 | Q8: -86.32 | R8: 2000 (Planned) | S8: 30 | T8: GWh/Yr | U8: 2026 | V8: Reports state 2025- but yet to be open https://us.aesc-group.com/aesc-celebrates-structural-completion-milestone-at-state-of-the-art-gigafactory-in-bowling-green/ | W8: AESC | X8: https://www.aesc-group.com/en/ | Y8: Zama | Z8: Kanagawa | AA8: Japan | AB8: KK MK | AC8: 8/4/2022 9/18/2025 | AD8: https://spectrumnews1.com/ky/bowling-green/news/2022/04/26/envision-aesc-plans-to-establish--2-billion-gigafactory-in-kentucky | AE8: Construction halted; plans uncertain | AF8: AESC Group leads a revolution with artificial intelligence converging with the internet of things-driven battery solutions, globally pioneering high-performance EV and energy storage, accelerating the shift to an endurable future. | AH8: 30
A9: NaatBatt 2025 | B9: Commercial | C9: Downstream | D9: N | E9: AESC | F9: Smyrna Battery Plant | G9: Cell Assemblies/ Groupings | H9: Packs | I9: https://www.aesc-group.com/en/ | J9: 500 Battery Plant Rd | K9: Smyrna | L9: TN | M9: US | N9: 37167 | O9: 615-768-3505 | P9: 36.217687 | Q9: -86.46103 | R9: 400 | S9: 40 | T9: GWj/Yr | U9: 2025 | V9: https://aesc-group.com/news/aesc-and-bmw-group-announce-new-partnership-in-battery-cell-production-and-supply | W9: AESC | X9: https://www.aesc-group.com/en/ | Y9: Zama | Z9: Kanagawa | AA9: Japan | AB9: VP MK | AC9: 8/1/2022 9/18/2025 | AD9: https://www.commercialappeal.com/story/money/2018/08/03/nissan-envision-group-take-control-smyrna-battery-plant/897768002/; https://www.dnb.com/business-directory/company-profiles.envision_aesc_(us)_llc.8a4477d46136013057715865676bc4c9.html | AE9: 2022 - Assembles battery packs for the Nissan Leaf; 2025 - Retooled for Energy Storage Systems (ESS) rather than EV | AF9: AESC Group leads a revolution with artificial intelligence converging with the internet of things-driven battery solutions, globally pioneering high-performance EV and energy storage, accelerating the shift to an endurable future. | AH9: 30
A10: NaatBatt 2025 | B10: Under construction | C10: Downstream | D10: N | E10: Akku Energy Devices LLC | F10: Akku Energy Devices LLC | G10: Manufacturing | H10: Packs | I10: https://akkuenergydevices.com/ | J10: 2650 E. 40th Ave. | K10: Denver | L10: CO | M10: US | N10: 80205 | O10: 303-808-4551 | P10: 39.771966 | Q10: -104.95529 | W10: Akku Energy Devices LLC | X10: https://akkuenergydevices.com/ | Y10: Denver | Z10: CO | AA10: US | AB10: MK | AC10: 45671 | AD10: Questionnaire | AF10: Akku Energy Devices LLC is a battery module and pack manufacturer specializing in micro-mobility, last-mile delivery vehicles, transportable energy storage, and stationary storage systems. | AH10: 24 | AI10: Bo Lee | AJ10: BoLee@evtico.com | AK10: 303-808-4551
A11: EDF | E11: AllCell Technology | H11: Modules/ Arrays | K11: Midland | L11: MI | S11: 0.0005064763 | T11: GWh/yr | U11: 2025
A12: NaatBatt 2025 | B12: Commercial | C12: Downstream | D12: N | E12: Alpha Technologies | F12: Alpha Technologies | G12: Cell Assemblies/ Groupings | H12: Modules/ Arrays | I12: https://www.alpha.com/ | J12: 1075 Satellite Blvd NW #100 | K12: Suwanee | L12: GA | M12: US | N12: 30024 | O12: 800-322-5742 | P12: 34.019067 | Q12: -84.069399 | U12: 2025 | W12: EnerSys | X12: https://www.enersys.com/en/ | Y12: Reading | Z12: PA | AA12: US | AB12: VP | AC12: 44429 | AD12: Questionnaire; enersys.com; alpha.com | AF12: Alpha Technologies, and EnerSys company, delivers integrated energy storage systems designed to meet the demands of a fast-evolving energy future, particularly in broadband and renewable energy applications. | AG12: https://www.alpha.com/, https://www.alpha.com/company/overview/about-alpha-technologies | AH12: 27
A13: NaatBatt 2025 | E13: Altairnano | L13: IN | S13: 0.26 | T13: GWh/yr | U13: 2025 | X13: https://pdf.secdatabase.com/219/0001437749-17-009565.pdf?utm_source=chatgpt.com
A14: NaatBatt 2025 | B14: Commercial | C14: Downstream | D14: N | E14: Ameresco | F14: Ameresco | G14: Assembly and Integration | H14: Battery Energy Storage | I14: https://www.ameresco.com/ | J14: 12211 W Alameda Pkwy, Suite 205 | K14: Lakewood | L14: CO | M14: US | N14: 80228 | O14: 720-627-8772 | P14: 39.705527 | Q14: -105.13842 | U14: 2025 | W14: Ameresco | X14: https://www.ameresco.com/ | Y14: Farmington | Z14: MA | AA14: US | AB14: AP | AC14: 45527 | AF14: Ameresco – an independent provider of innovative energy efficiency renewable energy solutions throughout North America - offers unique expertise across an array of green energy services including battery energy storage. | AH14: 30
A15: EDF | E15: American Autoparts, Inc (Mobis North America, LLC) | H15: Battery | K15: Midland | L15: MI | S15: 0.3311 | T15: GWh/yr | U15: 2027
A16: NaatBatt 2025 | E16: American Battery Factory | L16: AZ | S16: 4 | T16: GWh/yr | U16: 2027
A17: ICCT | E17: American Battery Factory | H17: Battery | K17: Coweta County | L17: Georgia | S17: 15 | T17: GWh/yr | U17: 2025 | V17: https://americanbatteryfactory.com/production
A18: NaatBatt 2025 | B18: Commercial | C18: Downstream | D18: Y | E18: American Battery Solutions | F18: Headquarters & Innovation Center | G18: Battery Development | H18: Packs Modules | I18: https://www.americanbatterysolutions.com/ | J18: 3768 S. Lapeer Road | K18: Lake Orion | L18: MI | M18: US | N18: 48539 | O18: 248-462-6364 | P18: 42.727073 | Q18: -83.243593 | R18: 156 | S18: =2/1000 -> 0.002 | T18: GWh/Yr | U18: 2025 | W18: Komatsu America | X18: https://www.americanbatterysolutions.com/ | Y18: Lake Orion | Z18: MI | AA18: US | AB18: VP AP | AC18: 8/6/2022 9/13/2024 | AD18: americanbatterysolutions.com/high-voltage; dnb.com/business-directory/company-profiles.american_battery_solutions_inc; Questionnaire; https://www.americanbatterysolutions.com/news-articles/american-battery-solutions-announces-re-launch-of-springboro-ohio-manufacturing-facility-with-added-capacity-to-meet-growing-lithium-ion-battery-demand; https://www.oemoffhighway.com/electronics/power-systems/batteries-capacitors/company/22005710/american-battery-solutions#:~:text=Our%20manufacturing%20team%20has%20produced,motive%20industrial%2C%20and%20commercial%20sectors. | AE18: Assembles battery packs for Fiat; 8 MWh/y expected production 2025 for 150,000 vehicles; Production capacity was estimated from current production of 60k packs to 150k packs corresponding to 8 MWh | AF18: American Battery Solutions delivered high-quality lithium-ion integrated battery solutions to meet energy needs | AG18: https://www.americanbatterysolutions.com/ | AH18: 13 | AI18: John Warner | AJ18: jwarner@americanbatterysolutions.com | AK18: 8109194751
A19: NaatBatt 2025 | B19: Commercial | C19: Downstream | D19: N | E19: American Battery Solutions | F19: ABS Innovation Center | G19: Battery Development | H19: Packs | I19: https://www.americanbatterysolutions.com/ | J19: 8110 Drouet Dr | K19: Springboro | L19: OH | M19: US | N19: 45066 | O19: 937-743-5296 | P19: 39.5532 | Q19: 84.2625 | S19: 2 | T19: GWh/Yr | U19: 2025 | W19: Komatsu America | X19: https://www.americanbatterysolutions.com/ | Y19: Lake Orion | Z19: MI | AA19: US | AB19: MK | AC19: 45918 | AD19: https://www.americanbatterysolutions.com/facilities; https://www.prnewswire.com/news-releases/american-battery-solutions-announces-re-launch-of-springboro-ohio-manufacturing-facility-with-added-capacity-to-meet-growing-lithium-ion-battery-demand-301516527.html | AF19: American Battery Solutions delivers high-quality lithium-ion integrated battery solutions to meet energy needs | AH19: 13 | AI19: John Warner | AJ19: jwarner@americanbatterysolutions.com | AK19: 8109194751
A20: NaatBatt 2025 | B20: Pre-commercial/ startup | C20: Downstream | D20: Y | E20: American Lithium Energy | F20: American Lithium Energy | G20: Cell Assemblies/ Groupings | H20: Packs | I20: https://www.americanlithiumenergy.com/ | J20: 2261 Rutherford Rd | K20: Carlsbad | L20: CA | M20: US | N20: 92008 | O20: 760-444-5244 | P20: 33.131818 | Q20: -117.27596 | R20: 13 | S20: 0.2 | T20: GWh/Yr | U20: 2025 | W20: American Lithium Energy | X20: https://www.americanlithiumenergy.com/ | Y20: Carlsbad | Z20: CA | AA20: US | AB20: VP MK | AC20: 8/1/2022 9/18/2025 | AD20: americanlithiumenergy.com; https://www.datanyze.com/companies/american-lithium-energy/347887839 | AE20: Focuses on batteries and packs for military applications | AF20: American Lithium Energy ships the world's highest energy density silicon anode lithium-ion batteries. | AG20: https://www.americanlithiumenergy.com/, https://www.americanlithiumenergy.com/about | AH20: 13
A21: NaatBatt 2025 | E21: Amplify Cell Technologies | L21: MS | S21: 21 | T21: GWh/yr | U21: 2027 | X21: duplicateâ€” https://www.businesswire.com/news/home/20240701093920/en/Amplify-Cell-Technologies-Begins-Construction-of-Mississippi-Battery-Cell-Factory?utm_source=chatgpt.com
A22: EDF | E22: Amplify Cell Technologies (Accelera, EVE and PACCAR and Daimler) | H22: Battery Component | K22: Liberty | L22: North Carolina | S22: 21 | T22: GWh/yr | U22: 2027 | V22: Amplify Cell Technologies (Accelera, EVE and PACCAR and Daimler)
A23: NaatBatt 2025 | B23: Under construction | C23: Downstream | D23: N | E23: Archer Aviation Inc | F23: Archer Aviation | G23: Assembly and Integration | H23: Packs | I23: https://archer.com/ | J23: 12000 GA-142 | K23: Covington | L23: GA | M23: US | N23: 30014 | P23: 33.6335 | Q23: -83.8475 | R23: 1000 | S23: 5.538 | T23: GWh/Yr | U23: 2027 | V23: Estimating a year after their UAE launch: https://finance.yahoo.com/news/where-archer-aviation-3-years-102300455.html 142 kwh * 6 = 852 kwh per aircraft * 650 aircraft = | W23: Archer Aviation Inc | X23: https://archer.com/ | Y23: San Jose | Z23: CA | AA23: US | AB23: MK | AC23: 45876 | AD23: https://www.airport-technology.com/news/archer-aircraft-facility-georgia/#:~:text=Archer%20Aviation%20has%20completed%20the%20construction%20of%20its,the%20facility%20covers%20an%20area%20of%20about%20400%2C000ft%C2%B2 | AE23: Construction on Phase 1 of this 350,000 sq ft high-volume manufacturing plant began in 2023. It will produce Archer's proprietary battery packs and assemble the "Midnight" aircraft | AF23: Archer is a leader in the electric, vertical take-off and landing space, developing electric air taxis to revolutionize urban transportation with safe and low-noise aircraft. | AH23: 25
A24: NaatBatt 2025 | B24: Pre-commercial/ startup | C24: Downstream | D24: N | E24: Archer Aviation Inc | F24: Archer Aviation | G24: Assembly and Integration | H24: Packs | I24: https://archer.com/ | J24: 190 W Tasman Dr | K24: San Jose | L24: CA | M24: US | N24: 95134 | P24: 37.4102 | Q24: -121.9456 | W24: Archer Aviation Inc | X24: https://archer.com/ | Y24: San Jose | Z24: CA | AA24: US | AB24: MK | AC24: 45876 | AD24: https://www.molicel.com/newsroom/archer-selects-molicel-to-supply-battery-cells-for-midnighttm/ | AE24: They have a strategic partnership with Molicel for the supply of high-performance lithium-ion cells for their "Midnight" aircraft | AF24: Archer is a leader in the electric, vertical take-off and landing space, developing electric air taxis to revolutionize urban transportation with safe and low-noise aircraft. | AH24: 25
A25: NaatBatt 2025 | B25: Commercial | C25: Downstream | D25: N | E25: Arkema | F25: Arkema - Bostik Adhesives | G25: Non-cell Components | H25: Other/ Unknown | I25: https://www.arkema.com/global/en/ | J25: 1301 N. 113th St | K25: Wauwatosa | L25: WI | M25: US | N25: 53226 | O25: 270-395-7121 | P25: 43.047414 | Q25: -88.053951 | U25: 2025 | W25: Arkema | X25: https://www.arkema.com/global/en/ | Y25: King of Prussia | Z25: PA | AA25: US | AB25: VP | AC25: 44421 | AD25: Questionnaire; Arkema.com | AE25: Adhesives | AF25: Arkema, a leader in specialty materials, leverages its expertise in materials science to create innovative, sustainable materials, and particularly providing necessary materials for lithium-ion cell manufacturing | AG25: https://www.arkema.com/global/en/, https://www.arkema.com/global/en/arkema-group/profile/ | AH25: 26
A26: ICCT | E26: BASF | H26: Cathode | K26: Lansing | L26: Michigan | S26: 1.6666667 | T26: GWh/yr | U26: 2024
A27: NaatBatt 2025 | B27: Commercial | C27: Downstream | D27: N | E27: Battery Specialties | F27: Battery Specialties | G27: Cell Assemblies/ Groupings | H27: Packs | I27: https://batteryspecialties.com/ | J27: 3530 Cadillac Ave. | K27: Costa Mesa | L27: CA | M27: US | N27: 92626 | O27: 800-854-5759 | P27: 33.697464 | Q27: -117.93002 | R27: 35 | U27: 2025 | W27: Battery Specialties | X27: https://batteryspecialties.com/ | Y27: Costa Mesa | Z27: CA | AA27: US | AB27: VP | AC27: 44774 | AD27: Thomasnet: Battery Packs / manufacturers; https://www.zoominfo.com/c/battery-specialties/8523659 | AE27: Custom battery packs, usually for military use; | AF27: Battery Specialties is involved in industrial and commercial battery distribution. | AG27: https://batteryspecialties.com/, https://batteryspecialties.com/about | AH27: 10
A28: NaatBatt 2025 | B28: Commercial | C28: Downstream | D28: N | E28: Beam | F28: Broadview | G28: Cell Assemblies/ Groupings | H28: Modules/ Arrays | I28: https://beamforall.com/ | J28: 2600 S 25th Ave, Suite Z | K28: Broadview | L28: IL | M28: US | N28: 60155 | O28: 872-281-7606 | P28: 41.854977 | Q28: -87.864275 | R28: 44 | U28: 2025 | W28: Beam Global | X28: https://beamforall.com/ | Y28: San Diego | Z28: CA | AA28: US | AB28: VP MK | AC28: 8/1/2022 9/18/2025 | AD28: allcelltech.com; Questionnaire; https://www.buzzfile.com/business/Allcell-Technologies-872-281-7606; https://beamforall.com/beam-global-announces-strategic-acquisition-of-allcell-technologies-a-leader-in-energy-storage-solutions/ | AE28: Battery packs using thermal interphase materials; All Cell tech was acquired by Beam | AF28: AllCell Technology produces safe lithium-ion batteries. | AG28: https://www.allcelltech.com/index.php/, https://www.allcelltech.com/index.php/about-us/allcell-overview/ | AH28: 6
A29: NaatBatt 2025 | B29: Commercial | C29: Downstream | D29: N | E29: BETA Technologies | F29: South Burlington Production Facility | G29: Assembly and Integration | H29: Packs | I29: https://beta.team/ | J29: 1550 Williston Rd | K29: South Burlington | L29: VT | M29: US | N29: 05403 | O29: 802-281-3623 | P29: 44.4682 | Q29: -73.1555 | U29: 2025 | W29: BETA Technologies | X29: https://beta.team/ | Y29: South Burlington | Z29: VT | AA29: US | AB29: MK | AC29: 45876 | AD29: https://beta.team/ | AE29: This is BETA's primary 188,000 sq ft manufacturing and assembly facility where they build their aircraft and assemble the battery packs. It is located at the Patrick Leahy Burlington International Airport | AF29: BETA Technologies is an aerospace company developing and manufacturing electric flight and charging systems for the logistics, medical, defense, and passenger sectors. | AH29: 22
A30: NaatBatt 2025 | B30: Commercial | C30: Downstream | D30: N | E30: Black Teal Energy | F30: Black Teal Energy | G30: Cell Assemblies/ Groupings | H30: Enclosures, aftermarket EV batteries, Energy Storage Systems | I30: https://www.blacktealenergy.com/ | J30: 3951 Research Drive, Suite D | K30: Sacramento | L30: CA | M30: US | N30: 95838 | O30: 310-525-5296 | P30: 38.639532 | Q30: -121.45952 | R30: 22 | U30: 2025 | W30: Black Teal Energy | X30: https://www.blacktealenergy.com/ | Y30: Sacramento | Z30: CA | AA30: US | AB30: AP | AC30: 45336 | AD30: https://www.blacktealenergy.com/ | AF30: Black Teal Energy focuses on sustainable energy solutions, offering aftermarket batteries for electric vehicles and energy storage systems, aiming for 100% recyclability and extending the lifespan of battery materials. | AH30: 29
A31: NaatBatt 2025 | B31: Commercial | C31: Downstream | D31: N | E31: Blue Line Battery, Inc. | F31: Blue Line Battery, Inc. | G31: Cell Assemblies/ Groupings | H31: Packs | I31: https://bluelinebattery.com/ | J31: 601 3rd St | K31: Beloit | L31: WI | M31: US | N31: 53511 | O31: 262-501-3376 | P31: 42.503144 | Q31: -89.03522 | R31: 12 | U31: 2025 | W31: Blue Line Battery, Inc. | X31: https://bluelinebattery.com/ | Y31: Whitewater | Z31: WI | AA31: US | AB31: KK | AC31: 44774 | AD31: https://bluelinebattery.com/products/ | AE31: Manufacturer of lithium-ion batteries designed for multiple and varied industrial applications. The company develops water and impact-resistant batteries for applications such as electric bikes, power storage, remote controls, and industrial purposes, enabling companies across various industries to meet and fulfill motive power and stationary energy storage needs. | AF31: Blue Line Battery focuses on the next stage in lithium-ion technology. | AG31: https://bluelinebattery.com/, https://bluelinebattery.com/about/ | AH31: 11
A32: NaatBatt 2025 | B32: Commercial | C32: Downstream | D32: N | E32: Blue Solutions Canada Inc. | F32: Blue Solutions Canada Inc. | G32: Cell Assemblies/ Groupings | H32: Packs | I32: https://www.blue-solutions.ca/ | J32: 1601 Rue de Coulomb | K32: Boucherville | L32: QC | M32: Canada | N32: J4B 8J7 | O32: 450-655-6622 | P32: 45.556091 | Q32: -73.425186 | R32: 228 | U32: 2025 | W32: Blue Solutions Canada Inc. | X32: https://www.blue-solutions.ca/ | Y32: Boucherville | Z32: QC | AA32: Canada | AB32: VP | AC32: 44414 | AD32: Questionnaire; https://www.zoominfo.com/pic/blue-solutions/372118582 | AF32: Blue Solutions Canada has the only solid-state 100% on the market. | AG32: https://www.blue-solutions.ca/ | AH32: 11
A33: NaatBatt 2025 | B33: Commercial | C33: Downstream | D33: N | E33: BlueOvalSK (JV - Ford and SK ON) | F33: 1 Blue Oval | G33: Cell Assemblies/ Groupings | H33: Packs | I33: https://blueovalsk.com/kentucky | J33: 1 BlueOval | K33: Glendale | L33: KY | M33: US | N33: 42740 | P33: 37.6 | Q33: -85.9 | R33: 5000 (Planned) | S33: 20 | T33: GWh/Yr | U33: 2025 | W33: S K Innovation | X33: https://blueovalsk.com/ | Y33: Jongno-gu | Z33: Seoul | AA33: S Korea | AB33: VP MK | AC33: 6/19/2023 9/18/2025 | AD33: https://www.kentucky.com/news/state/kentucky/article254556442.html; BNEF Interactive Dataset\Cell Manufacturing; https://blueovalsk.com/kentucky/; https://www.charged-the-book.com/na-ev-supply-chain-map; https://www.lanereport.com/183196/2025/08/multibillion-dollar-blueoval-sk-ev-battery-plants-launch-production/ | AF33: BlueOvalSK's mega campus is envisioned to be an endurable automotive manufacturing ecosystem. | AG33: https://blueovalsk.com/kentucky, https://www.blueovalsk.com/ | AH33: 12
A34: NaatBatt 2025 | B34: Planned | C34: Downstream | D34: N | E34: BlueOvalSK (JV - Ford and SK ON) | F34: Blue Oval City | G34: Cell Assemblies/ Groupings | H34: Packs | I34: https://blueovalsk.com/tennessee | J34: Blue Oval City | K34: Stanton | L34: TN | M34: US | N34: 38069 | P34: 35.402916 | Q34: -89.417312 | R34: 5800 (Planned) | S34: 43 | T34: GWh/Yr | U34: 2027 | V34: https://www.commercialappeal.com/story/money/business/2025/08/19/blueoval-sk-battery-production-delay-west-tennessee/85725474007/ | W34: S K Innovation | X34: https://blueovalsk.com/ | Y34: Jongno-gu | Z34: Seoul | AA34: S Korea | AB34: VP MK | AC34: 8/4/2022 9/18/2025 | AD34: https://www.kentucky.com/news/state/kentucky/article254556442.html; https://www.commercialappeal.com/story/money/business/2022/07/14/ford-sk-on-ev-battery-plant-west-tennessee-blue-oval-city/10038277002/; BNEF Interactive Dataset\Cell Manufacturing; https://www.lanereport.com/183196/2025/08/multibillion-dollar-blueoval-sk-ev-battery-plants-launch-production/ | AE34: Commissioning expected in by EOY 2027 | AF34: BlueOvalSK's mega campus is envisioned to be an endurable automotive manufacturing ecosystem. | AG34: https://blueovalsk.com/tennessee, https://www.blueovalsk.com/ | AH34: 12
A35: ICCT | E35: BMW AG | H35: Modules, Packs | K35: Warren | L35: Ohio | S35: 1.68 | T35: GWh/yr | U35: 2024
A36: NaatBatt 2025 | B36: Under construction | C36: Downstream | D36: N | E36: BMW Group Inc | F36: BMW San Luis Potosi Battery Manufacturing Plant | G36: Assembly and Integration | H36: Packs | I36: https://www.bmwgroup-werke.com/san-luis-potosi/es.html | J36: Boulevard BMW No. 655 Parque Industrial Desarrollo Logistik II | K36: San Luis Potosi | L36: San Luis Potosi | M36: Mexico | N36: 79526 | O36: 52-444-347-9137 | P36: 22.462813 | Q36: -100.8707 | R36: 500 (Planned) | S36: 8.75 | T36: GWh/yr | U36: 2026 | V36: https://www.bmwblog.com/2024/10/30/bmw-lithium-battery-production-mexico-san-luis-potosi/ | W36: BMW Group | X36: https://www.bmwgroup-werke.com | Y36: Munich | Z36: Bavaria | AA36: Germany | AB36: VP MK | AC36: 6/7/2023 8/14/2025 | AD36: https://www.bmwgroup-werke.com/san-luis-potosi/es/noticias/pressreleases/2023/neue-klasse.html#1022952825; BNEF Cell DB; https://mexico-now.com/bmw-group-to-produce-electric-vehicles-and-high-voltage-batteries-in-slp/ | AE36: 2027 SOP | AF36: BMW, a major car maker, develops and integrates advanced lithium-ion batteries for electric vehicles, focusing on enhancing energy density, efficiency, lifespan, and safety, while collaborating with technology partners for innovation. | AG36: https://www.bmwgroup-werke.com/san-luis-potosi/en.html, https://www.bmwgroup.com/en/investor-relations/company-reports.html | AH36: 30
A37: NaatBatt 2025 | B37: Commercial | C37: Under Construction | D37: N | E37: BMW Manufacturing | F37: Spartanburg Manufacturing Plant | G37: Cell Assemblies/ Groupings | H37: Packs | I37: https://www.bmwgroup-werke.com/en.html | K37: Woodruff | L37: SC | M37: US | N37: 29651 | O37: 864-802-6000 | P37: 34.894648 | Q37: -82.180366 | R37: 120 | S37: =22500*80/1000000 -> 1.8 | T37: GWh/yr | U37: 2025 | V37: 22500 units per year, assuming each unit is 80 kwh | W37: BMW Group | X37: https://www.bmwusa.com/ | Y37: Munich | Z37: Bavaria | AA37: Germany | AB37: EW MK | AC37: 8/9/2021 9/18/2025 | AD37: EV Battery Supply Chain Analysis https://www.automotivelogistics.media/battery-supply-chain/oem-and-lithium-ion-battery-cell-supplier-database/41933.article; bmwusa.com; https://www.bmwgroup-werke.com/spartanburg/en/our-plant/site-infos.html#ace-2129196916; https://www.bmwgroup.com/en/news/general/2024/batteryproduction.html | AE37: Assembles battery packs for BMW; 120 are employed in battery production; 11,000 are employed at the entire plant. Estimated prod. Based on 45,000 batteries in 4 years and doubling capacity in 2019- https://www.bmwgroup-werke.com/spartanburg/en/our-plant/site-infos.html#ace-2129196916 | AF37: BMW Manufacturing, a subsidiary of BMW Group, assembles several vehicle models and battery packs in this 8 million square-foot campus in Greer, South Carolina. | AG37: https://www.bmwgroup-werke.com/en.html | AH37: 24
A38: NaatBatt 2025 | B38: Commercial | C38: Downstream | D38: Y | E38: BMZ USA Inc. | F38: BMZ Virginia Beach Battery Manufacturing Plant | G38: Assembly and Integration | H38: Packs | I38: https://www.bmz-group.com/index.php/en/ | J38: 1429 Miller Store Rd. | K38: Virginia Beach | L38: VA | M38: US | N38: 23455 | O38: 757-821-8494 | P38: 36.895567 | Q38: -76.191425 | R38: 100 | S38: 2 | T38: GWh/yr | U38: 2025 | W38: BMZ Co GmBH | X38: bmz-group.com | Y38: Karlstein am Main | Z38: Bavaria | AA38: Germany | AB38: VP MK | AC38: 6/7/2023 8/14/2025 | AD38: bmz-group.com; BNEF Cell Database; https://www.bestmag.co.uk/bmz-selects-new-us-headquarters-virginia-beach/ | AF38: BMZ innovates high-tech batteries for global brands, integrating cutting-edge tech. Its one-stop-shop ensures excellence across the value chain, from production to after-sales. | AG38: https://www.bmz-group.com/index.php/en/ | AH38: 22
A39: EDF | E39: BorgWarner | H39: Battery | K39: Spring Hill | L39: Tennessee | S39: 3 | T39: GWh/yr | U39: 2024 | V39: https://finance.yahoo.com/news/borgwarner-bwa-makes-62m-electrification-113411082.html
A40: NaatBatt 2025 | B40: Commercial | C40: Downstream | D40: N | E40: Braille Battery, Inc | F40: Braille Battery, Inc | G40: Cell Assemblies/ Groupings | H40: Packs | I40: https://braillebattery.com/ | J40: 6935 15th St E | K40: Sarasota | L40: FL | M40: US | N40: 34243 | O40: 941-312-5047 | P40: 27.417407 | Q40: -82.545679 | R40: 15 | U40: 2025 | W40: Braille Battery Inc. | X40: https://braillebattery.com/ | Y40: Sarasota | Z40: FL | AA40: US | AB40: VP | AC40: 44781 | AD40: braillebattery.com; https://www.zoominfo.com/c/braille-battery-inc/353980518; https://www.linkedin.com/company/braille-battery | AE40: Manufacture specialty Li-ion batteries for racing cars and other high performance applications; Workforce < 25 or 11-50; Estimated 15 | AF40: Braille Battery is a world leader in light-weight AGM batteries. | AG40: https://braillebattery.com/, https://braillebattery.com/our-story/ | AH40: 10
A41: EDF | E41: Canadian Solar | H41: Battery | K41: Spring Hill | L41: Tennessee | S41: 6 | T41: GWh/yr | U41: 2026 | V41: the note here makes it seem promising but there were a lot of large numbers online
A42: EDF | E42: Canoo | H42: Battery | K42: New Carlisle | L42: Indiana | S42: 3.2 | T42: GWh/yr | U42: 2025 | V42: https://www.reuters.com/business/autos-transportation/canoo-build-battery-manufacturing-facility-oklahoma-2022-11-02/
A43: NaatBatt 2025 | B43: Commercial | C43: Downstream | D43: y- updated capacity | E43: Caterpillar | F43: Caterpillar | G43: Assembly and Integration | H43: Battery Energy Storage | I43: https://www.caterpillar.com/en.html | J43: 5205 N O'Connor Blvd #1100 | K43: Irwine | L43: TX | M43: US | N43: 75309 | P43: 32.870365 | Q43: -96.939507 | S43: 5 | T43: GWh/yr | U43: 2025 | W43: Caterpillar | X43: https://www.caterpillar.com/ | Y43: Irwine | Z43: TX | AA43: US | AB43: AP | AC43: 45527 | AD43: https://www.caterpillar.com/en/news/corporate-press-releases/h/lithos-energy-investment.html | AE43: Caterpillar Announces Investment in Lithos Energy Inc. to Further Battery Pack Development and Manufacturing | AF43: Caterpillar is a manufacturer of construction and mining equipment, off-highway diesel and natural gas engines, industrial gas turbines. recently engaged in battery storage for many of its applications | AH43: 28
A44: NaatBatt 2025 | B44: Commercial | C44: Downstream | D44: N | E44: Cell-Con, Inc. | F44: Cell-Con, Inc. | G44: Cell Assemblies/ Groupings | H44: Packs with Lithium and LPF | I44: https://cell-con.com/ | J44: 8468 US Rte. 220 | K44: Bedford | L44: PA | M44: US | N44: 15522 | O44: 800-771-7139 | P44: 39.937092 | Q44: -78.581478 | R44: 30 | U44: 2025 | W44: Cell-Con, Inc. | X44: https://cell-con.com/ | Y44: Exton | Z44: PA | AA44: US | AB44: SD, AP | AC44: 7/1/2024: 8/11/2024 | AD44: Thomasnet: Battery Packs / manufacturers; | AE44: Low voltage packs with embedded sensors; Workforce range: 10-49 | AF44: Cell-Con is a leading U.S. manufacturer of custom and stocked battery packs from cells, specializing in Li-ion, NiMH, LiFePO4, NiCd, and lead-acid power systems; and for portable devices. | AG44: https://cell-con.com/ | AH44: 28
A45: NaatBatt 2025 | B45: Commercial | C45: Downstream | D45: y- updated capacity | E45: Clarios | F45: Clarios | G45: Cell Assemblies/ Groupings | H45: Packs | I45: https://www.clairos.com/ | J45: 70 W 48th St | K45: Holland | L45: MI | M45: US | N45: 49423 | O45: 616-494-4420 | P45: 42.752922 | Q45: -86.108513 | S45: 2 | T45: GWh/yr | U45: 2025 | W45: Clairos | X45: https://www.Clarios.com/ | Y45: Milwaukee | Z45: WI | AA45: US | AB45: EW | AC45: 44417 | AD45: https://betterbuildingssolutioncenter.energy.gov/iso-50001/showcase-projects/clarios-meadowbrook-lithium-ion%E2%80%9450001-ready-facility | AE45: Proprietary LTO pack; Used to be Johnson Controls Inc. | AF45: Clarios develops and manufactures advanced automotive batteries, focusing on lead-acid and lithium-ion technologies for vehicles, including start-stop, conventional, and electric vehicles. | AG45: https://www.clarios.com/, https://www.clarios.com/company/company-overview, https://www.clarios.com/company/mission-values | AH45: 21
A46: NaatBatt 2025 | B46: Commercial | C46: Downstream | D46: N | E46: Conamix Inc. | F46: Conamix Inc. | G46: Cell Assemblies/ Groupings | H46: Packs | J46: 61 Brown Rd | K46: Ithaca | L46: NY | M46: US | N46: 14850 | O46: 607-216-6229 | P46: 42.44 | Q46: -76.46 | R46: 14 | U46: 2025 | W46: Conamix Inc. | Y46: Ithaca | Z46: NY | AA46: US | AB46: VP | AC46: 45243 | AE46: Developer of nano-structured silicon advanced battery materials intended to be used in lithium-ion batteries. The company's battery is developed with high-energy cobalt-free battery materials for rechargeable batteries that can yield more energy than current batteries, providing companies with materials to improve the performance of lithium-ion batteries. | AF46: Conamix develops lithium sulfur battery technology by working on cathode and electrolyte to reduces cost of electric and other markets without using expensive and exotic materials or constrained supply chains. | AG46: https://www.conamix.com/, https://www.conamix.com/about | AH46: 30
A47: NaatBatt 2025 | B47: Commercial | C47: Downstream | D47: N | E47: Coreshell Technologies Inc | F47: Coreshell Technologies Inc | G47: Cell Assemblies/ Groupings | H47: Packs | I47: https://www.coreshell.com/ | J47: 1933 Davis St., Suite 228 | K47: San Leandro | L47: CA | M47: US | N47: 94577 | O47: 415-314-9926 | P47: 37.71 | Q47: -122.1 | R47: 5 | U47: 2025 | W47: Coreshell Technologies Inc | X47: https://www.coreshell.com/ | Y47: Oakland | Z47: CA | AA47: US | AB47: KK | AC47: 44774 | AD47: https://www.buzzfile.com/business/Coreshell-Technologies-Inc-415-314-9926 | AE47: Coreshell is unlocking lower cost, higher capacity, and safer batteries with its low-cost thin-film electrode coating technology. | AF47: Coreshell is an advanced battery solutions company that increases the range of electric vehicles while bringing down costs, so the world can transition to clean energy in time. | AG47: https://www.coreshell.com/, https://www.coreshell.com/about | AH47: 28
A48: NaatBatt 2025 | B48: Commercial | C48: Downstream | D48: N | E48: Coulomb Solutions Inc. (CSI) | F48: Coulomb Solutions Inc. (CSI) | G48: System Integrations | H48: Packs | I48: https://coulombsolutions.com/ | J48: 705 Columbia Avenue | K48: Riverside | L48: CA | M48: US | N48: 92507 | P48: 34.002191 | Q48: -117.32625 | R48: 50 | U48: 2025 | W48: Coulomb Solutions Inc. (CSI) | X48: https://coulombsolutions.com/ | Y48: Livermore | Z48: CA | AA48: US | AB48: SD | AC48: 45699 | AD48: Ahmad's email on 2.11.25 | AF48: Coulomb Solutions Inc. addresses commercial EV challenges and to enable North American original equipment manufacturers to be highly successful in launching electric variants of their commercial truck and bus platforms. | AH48: 30
A49: NaatBatt 2025 | B49: Planned | C49: Downstream | D49: N | E49: Coulomb Solutions Inc. (CSI) | F49: Coulomb Solutions Inc. (CSI) | G49: System Integrations | H49: Packs | I49: https://coulombsolutions.com/csi-battery-systems/ | J49: TBD | K49: TBD | L49: TBD | M49: US | W49: Coulomb Solutions Inc. (CSI) | X49: https://coulombsolutions.com/csi-battery-systems/ | Y49: Livermore | Z49: CA | AA49: US | AB49: BM | AC49: 45922 | AD49: https://coulombsolutions.com/about-us/; https://coulombsolutions.com/csi-battery-systems/ | AE49: Planning to build a new plant in AZ, TX or NV | AF49: Coulomb Solutions Inc. is a Livermore‑based leader in commercial EV battery systems and electrification components, also expanding into residential and industrial energy storage solutions powered by LFP battery technology. | AH49: 29
A50: NaatBatt 2025 | B50: Pre-commercial/ startup | C50: Downstream | D50: N | E50: Cuberg | F50: Advanced Technology Center | G50: Cell Assemblies/ Groupings | H50: Packs | I50: https://cuberg.net/ | J50: 1198 65th Street, Suite 170 | K50: Emeryville | L50: CA | M50: US | N50: 947608 | P50: 37.847688 | Q50: -122.28823 | R50: 40 | W50: Northvolt | X50: https://cuberg.net/ | Y50: Stockholm | Z50: Uppland | AA50: Sweden | AB50: VP | AC50: 44888 | AD50: cuberg.net; BNEF: 2020 Battery Startups; https://www.owler.com/company/cuberg | AE50: Developing the first aviation-certified lithium metal battery pack | AF50: Cuberg combines next-generation battery technology, world-class R&D expertise, and a global manufacturing capacity to enable entirely new modes of all-electric transportation. | AG50: https://cuberg.net/, https://cuberg.net/company | AH50: 21
A51: ICCT | E51: Cummins | H51: Battery | K51: Manteno | L51: IL | S51: 0.825 | T51: GWh/yr | U51: 2027
A52: ICCT | E52: Cummins, Daimler Truck AG | H52: Cells | K52: Manteno | L52: IL | S52: 6.3 | T52: GWh/yr | U52: 2027
A53: NaatBatt 2025 | B53: Commercial | C53: Downstream | D53: N | E53: Custom Power | F53: Custom Power | G53: Cell Assemblies/ Groupings | H53: Packs | I53: https://www.custompower.com/ | J53: 10910 Talbert Ave. | K53: Fountain Valley | L53: CA | M53: US | N53: 92708 | O53: 800-896-5059 | P53: 33.701599 | Q53: -117.93829 | R53: 75 | U53: 2025 | W53: Custom Power | X53: https://www.custompower.com/ | Y53: Fountain Valley | Z53: CA | AA53: US | AB53: VP | AC53: 44774 | AD53: Thomasnet: Battery Packs / manufacturers; custompower.com | AE53: Custom battery packs for military and medical devices; Workforce range: 50-99 | AF53: Custom Power specializes in designing and manufacturing custom battery packs for Defense, Aerospace, Medical, and Industrial sectors, with a focus on lithium-ion and other chemistries. | AG53: https://www.custompower.com/, https://www.custompower.com/about-us/ | AH53: 25
A54: ICCT | E54: Dai Nippon Printing Co., Ltd. (DNP) | H54: Battery Component | K54: Harrodsburg | L54: KY | U54: 2026
A55: NaatBatt 2025 | B55: Under construction | C55: Downstream | D55: N | E55: Daimler | F55: Daimler Tuscaloosa Plant | G55: Cell Assemblies/ Groupings | H55: Packs | I55: https://www.daimlertruck.com/en | J55: 1 Mercedes Dr | K55: Vance | L55: AL | M55: US | N55: 35490 | P55: 33.184292 | Q55: -87.262439 | R55: 4400 (Planned) | W55: Daimler AG | X55: https://www.daimlertruck.com/en | Y55: Stuttgart | Z55: Baden-Württemberg | AA55: Germany | AB55: VP | AC55: 44774 | AD55: EV Battery Supply Chain Analysis; daimler.com | AE55: Will assemble battery packs for Mercedes | AF55: The Daimler Tuscaloosa Plant, operated by Mercedes-Benz, is focused on electric vehicle production, including EQS and EQE SUV models, supported by a new battery plant in Bibb County, Alabama. | AG55: https://www.daimlertruck.com/en, https://www.daimlertruck.com/en/company/our-purpose | AH55: 29
A56: NaatBatt 2025 | B56: Commercial | C56: Downstream | D56: N | E56: Daimler Truck North America | F56: Portland Truck Manufacturing Plant | G56: Assembly and Integration | H56: Integrated Battery Packs for Trucks and Energy Storage | I56: https://northamerica.daimlertruck.com/ | J56: 6936 North Fathom Street | K56: Portland | L56: OR | M56: US | N56: 97217 | P56: 45.574042 | Q56: -122.7138 | R56: 2800 | U56: 2025 | W56: Daimler Truck North America | X56: https://northamerica.daimlertruck.com/ | Y56: Portland | Z56: OR | AA56: US | AB56: AP | AC56: 45529 | AD56: https://northamerica.daimlertruck.com/eMobility/ | AE56: DAIMLER TRUCK develops ELECTRIC COMMERCIAL VEHICLES with lithium ion batteries. Daimler Truck team up with Accelera by Cummins and PACCAR and select Mississippi for battery cell production in the United States. | AF56: Daimler Truck North America manufactures, sells, and services several renowned commercial vehicle brands including Freightliner Trucks, Western Star Trucks, Thomas Built Buses, with an emphasis on electrification with LIBs | AG56: https://northamerica.daimlertruck.com/PressDetail/accelera-by-cummins-daimler-truck-and-2024-01-18/ | AH56: 29
A57: NaatBatt 2025 | B57: Commercial | C57: Downstream | D57: N | E57: Dantona Industries, Inc. | F57: Dantona Industries, Inc. | G57: Cell Assemblies/ Groupings | H57: Packs | I57: https://dantona.com/ | J57: 3051 Burns Ave | K57: Wantagh | L57: NY | M57: US | N57: 11793 | O57: 800-326-8662 | P57: 40.672924 | Q57: -73.517659 | R57: 30 | U57: 2025 | W57: Dantona Industries, Inc. | X57: https://dantona.com/ | Y57: Wantagh | Z57: NY | AA57: US | AB57: VP | AC57: 44774 | AD57: Thomasnet: Battery Packs / manufacturers; | AE57: Custom battery packs; Workforce Range: 10-49 | AF57: Dantona Industries is a supplier of industrial and consumer batteries, chargers, and battery packs. | AG57: https://dantona.com/ | AH57: 14
A58: NaatBatt 2025 | E58: Dragonfly Energy Holdings Corp | L58: NV | S58: 0.15 | T58: GWh/yr | U58: 2025
A59: NaatBatt 2024 | E59: Duckyang | H59: Modules | L59: CA | S59: 0.11 | T59: GWh/yr | U59: 2028
A60: NaatBatt 2025 | B60: Planned | C60: Downstream | D60: N | E60: Durapower | F60: Durapower | G60: Battery Development | H60: Lithium-ion cells | I60: https://durapowergroup.com/ | J60: TBD | K60: TBD | L60: TBD | M60: US | W60: Durapower | X60: https://durapowergroup.com/ | Y60: The Egis | AA60: Singapore | AB60: BM | AC60: 45922 | AD60: https://durapowergroup.com/ | AE60: Planning to build a battery pack plant in North America, location TBD. | AF60: Durapower is a Singaporean lithium‑ion battery cell developer and manufacturer offering end‑to‑end energy storage solutions for electric mobility, marine, and stationary applications across over 25 countries with a flawless safety record. | AH60: 31
A61: NaatBatt 2025 | B61: Planned | C61: Midstream | D61: No | E61: Durapower Tech Private Limited | F61: Durapower Tech Private Limited | G61: Cell | H61: Packs | K61: TBD | L61: TBD | M61: US | V61: Durapower Group | W61: https://durapowergroup.com/ | X61: Singapore | Z61: Singapore | AA61: MK | AB61: 45867 | AC61: https://durapowergroup.com/durapower-plans-for-u-s-manufacturing-presence-as-part-of-global-expansion/, https://chargedevs.com/newswire/singapores-durapower-plans-us-battery-manufacturing-as-part-of-global-expansion/ | AD61: Durapower is actively seeking joint venture partners for a U.S. manufacturing facility. The company's current North American presence is a sales office in Morgan Hill, CA | AE61: Durapower is a leading global provider of high-performance, end-to-end energy storage solutions, specializing in lithium-ion battery technology for automotive, marine, and stationary applications. | AG61: 23
A62: NaatBatt 2025 | B62: Planned | C62: Midstream | D62: N | E62: Durapower Tech Private Limited | F62: Durapower Tech Private Limited | G62: Battery Development | H62: Packs | I62: https://durapowergroup.com/ | J62: TBD | K62: TBD | L62: TBD | M62: US | W62: Durapower Group | X62: https://durapowergroup.com/ | Y62: Singapore | AA62: Singapore | AB62: MK | AC62: 45867 | AD62: https://durapowergroup.com/durapower-plans-for-u-s-manufacturing-presence-as-part-of-global-expansion/, https://chargedevs.com/newswire/singapores-durapower-plans-us-battery-manufacturing-as-part-of-global-expansion/ | AE62: Durapower is actively seeking joint venture partners for a U.S. manufacturing facility. The company's current North American presence is a sales office in Morgan Hill, CA | AF62: Durapower is a leading global provider of high-performance, end-to-end energy storage solutions, specializing in lithium-ion battery technology for automotive, marine, and stationary applications. | AH62: 23
A63: NaatBatt 2025 | B63: Commercial | C63: Downstream | D63: N | E63: EaglePicher Technologies, LLC | F63: Medical Power Production | G63: Cell Assemblies/ Groupings | H63: Packs | I63: https://www.eaglepicher.com/ | J63: 13136 82A Avenue | K63: Surrey | L63: BC | M63: Canada | N63: V3W 9Y6 | O63: 604-543-4350 | P63: 49.151971 | Q63: -122.85927 | U63: 2025 | W63: Eaglepicher Technologies, LLC | X63: https://www.eaglepicher.com/ | Y63: St. Louis | Z63: MO | AA63: US | AB63: VP | AC63: 44415 | AD63: eaglepicher.com | AE63: Also does R&D and makes a charger/analyzer; This facility focuses on batteries for medical devices; facility is 61,000 sq ft; > 900 employees across all locations | AF63: EaglePicher Technologies specializes in designing and manufacturing advanced lithium-ion batteries for various applications, including defense, aerospace, and medical devices, ensuring high-performance and reliability. | AG63: https://www.eaglepicher.com/ | AH63: 23
A64: NaatBatt 2025 | B64: Commercial | C64: Downstream | D64: N | E64: EaglePicher Technologies, LLC | F64: Aerospace Business Unit an Lithium Ion Center of Excellence | G64: Cell Assemblies/ Groupings | H64: Packs | I64: https://www.eaglepicher.com/ | J64: 8230 E. 23rd St | K64: Joplin | L64: MO | M64: US | N64: 64804 | O64: 417-624-3167 | P64: 37.063541 | Q64: -94.402179 | T64: 0.2 | U64: 2025 | W64: Eaglepicher Technologies, LLC | X64: https://www.eaglepicher.com/ | Y64: St. Louis | Z64: MO | AA64: US | AB64: VP | AC64: 44415 | AD64: eaglepicher.com | AE64: Also does R&D and makes a charger/analyzer; This facility focuses on batteries for aerospace devices; facility is 100,000 sq ft; > 900 employees across all locations | AF64: EaglePicher Technologies specializes in designing and manufacturing advanced lithium-ion batteries for various applications, including defense, aerospace, and medical devices, ensuring high-performance and reliability. | AG64: https://www.eaglepicher.com/ | AH64: 23
A65: NaatBatt 2025 | B65: Commercial | C65: Downstream | D65: N | E65: EaglePicher Technologies, LLC | F65: Defense Strategic Business Unit | G65: Cell Assemblies/ Groupings | H65: Packs | I65: https://www.eaglepicher.com/ | J65: C & Porter Streets | K65: Joplin | L65: MO | M65: US | N65: 64801 | O65: 417-623-8000 | P65: 37.094713 | Q65: -94.52806 | U65: 2025 | W65: Eaglepicher Technologies, LLC | X65: https://www.eaglepicher.com/ | Y65: St. Louis | Z65: MO | AA65: US | AB65: VP | AC65: 44415 | AD65: eaglepicher.com | AE65: Also does R&D and makes a charger/analyzer; This facility focuses on batteries for military applications; > 900 employees across all locations | AF65: EaglePicher Technologies specializes in designing and manufacturing advanced lithium-ion batteries for various applications, including defense, aerospace, and medical devices, ensuring high-performance and reliability. | AG65: https://www.eaglepicher.com/ | AH65: 23
A66: NaatBatt 2025 | B66: Commercial | C66: Downstream | D66: N | E66: Eaton | F66: Eaton | G66: Cell Assemblies/ Groupings | H66: Packs | I66: https://www.eaton.com/country.html | J66: 3301 Spring Forest Rd, | K66: Raleigh | L66: NC | M66: US | N66: 27616 | P66: 36.477545 | Q66: -78.403396 | R66: 650 | U66: 2025 | W66: Eaton | X66: https://www.eaton.com/country.html | Y66: Dublin | Z66: Leinster | AA66: Ireland | AD66: eaton.com | AE66: USP battery packs | AF66: Eaton provides electric vehicle charging solutions and lithium-ion battery and energy storage systems to support the transition to low-carbon transportation. It also collaborates on electric drives for commercial vehicles. | AG66: https://www.eaton.com/us/en-us.html, https://www.eaton.com/us/en-us/company/about-us.html | AH66: 29
A67: EDF | E67: EC Power | H67: Cells | K67: Ellabell, Bryan County | L67: Georgia | S67: 0.001 | T67: GWh/yr | U67: 2028
A68: NaatBatt 2025 | B68: Pre-commercial/ startup | C68: Downstream | D68: Y | E68: Electric Power Systems | F68: Electric Power Systems | G68: Cell Assemblies/ Groupings | H68: Modules/ Arrays | I68: https://epsenergy.com/ | J68: 520 W 2850 N | K68: North Logan | L68: UT | M68: US | N68: 84341 | O68: 435-535-6978 | P68: 41.783297 | Q68: -111.81006 | R68: 135 | W68: Electric Power Systems | X68: https://epsenergy.com/ | Y68: North Logan | Z68: UT | AA68: US | AB68: VP | AC68: 44777 | AD68: ep-sys.net; https://www.sltrib.com/news/2022/06/13/flying-cars-see-how-this/#:~:text=%E2%80%9CWe%20call%20them%20electric%20vertical,others%2C%20Millecam%20said%20EPS%20said. | AE68: batteries for spacecraft, helicopters, airplanes | AF68: Electric Power Systems (EPS) develops advanced lithium-ion energy storage solutions, including high-power, scalable powertrains certifiable for electrified aviation, and a broad range of applications, from fixed-wing aircraft to eVTOLs. | AG68: https://epsenergy.com/, https://epsenergy.com/about-electric-power-systems/our-mission/ | AH68: 29
A69: NaatBatt 2025 | B69: Commercial | C69: Downstream | D69: N | E69: Electrochem Solutions, Inc. | F69: Electrochem Solutions | G69: Cell Assemblies/ Groupings | H69: Packs | I69: https://www.electrochemsolutions.com/ | J69: 670 Paramount Dr. | K69: Raynham | L69: MA | M69: US | N69: 02767 | O69: 781-830-5800 | P69: 41.904315 | Q69: -71.024553 | R69: 120 | U69: 2025 | W69: Integer Holdings Company | X69: https://www.integer.net/home/default.aspx | Y69: Plano | Z69: TX | AA69: US | AB69: VP MK | AC69: 8/1/2022 8/14/2025 | AD69: electrochemsolutions.com; integer.net; https://www.buzzfile.com/business/Electrochem-Solutions,-Inc.-781-575-0800 | AE69: Makes custom cells and packs for Li-ion; also does consulting and design/development; Most manufacturing is lithium primary cells | AF69: Electrochem is the premium provider of custom power solutions for critical applications where energy demands are high, operating conditions are extreme, and the cost of failure is significant. | AG69: https://www.integer.net/home/default.aspx, https://electrochemsolutions.com/about/default.aspx | AH69: 28
A70: NaatBatt 2025 | B70: Commercial | C70: Downstream | D70: N | E70: Electrovaya | F70: Electrovaya | G70: Battery Development | H70: Lithium-ion batteries | I70: https://electrovaya.com/press/electrovaya-announces-start-of-battery-system-manufacturing-in-jamestown-ny/ | J70: 1 Precision Way | K70: Jamestown | L70: NY | M70: US | N70: 14701 | O70: 905-855-4610 | P70: 42.095554 | Q70: -79.238609 | R70: 200 | S70: 0.5 | T70: GWh/yr | U70: 2025 | W70: Electrovaya | X70: https://electrovaya.com/ | Y70: Mississauga | Z70: Ontario | AA70: Canada | AB70: BM | AC70: 45922 | AD70: https://electrovaya.com/press/electrovaya-announces-start-of-battery-system-manufacturing-in-jamestown-ny/; https://electrovaya.com/about-us/ | AF70: Electrovaya Inc. is a Canadian‑headquartered lithium‑ion battery developer and manufacturer specializing in high‑safety, long‑life Infinity battery systems and advanced solid‑state solutions for heavy‑duty vehicles and energy storage. | AH70: 27
A71: NaatBatt 2025 | E71: Electrovaya | L71: ON | S71: 0.5 | T71: GWh/yr | U71: 2025
A72: ICCT | E72: Electrovaya | H72: Battery | K72: Cartersville, Bartow County | L72: Georgia | S72: 1 | T72: GWh/yr | U72: 2025
A73: EDF | E73: ElringKlinger Group | H73: Battery Component | K73: Toledo | L73: OH | T73: GWh/yr | U73: 2025
A74: NaatBatt 2025 | B74: Pre-commercial/ startup | C74: Downstream | D74: N | E74: EMBS Battery Systems | F74: EMBS North America | G74: Cell Assemblies/ Groupings | H74: Battery Systems | I74: https://embatterysystems.com/ | J74: 1721-A White Horse Rd. | K74: Greenville | L74: SC | M74: US | N74: 29605 | O74: 864-220-1010 | P74: 34.795623 | Q74: -82.421449 | R74: 10 | S74: 0.16 | T74: GWh/yr | U74: 2025 | V74: Naatbatt showed 1,000 MT/yr converted to GWh is (1000 MT / .5 MT *80 kWh) | W74: Prettl Group | X74: https://www.prettl.com/en/home | Y74: Pfullingen | Z74: BW | AA74: Germany | AB74: MK | AC74: 1/31/2025 8/4/2025 | AD74: Questionnaire | AF74: EMBS Battery Systems is a battery pack original design manufacturer and manufacturing services provider, specializing in low-voltage lithium-ion battery packs for robotics and other cordless applications. | AH74: 26 | AI74: Noemi Romero | AJ74: Noemi.Romero@prettl-electronics.com | AK74: 864-220-1010
A75: NaatBatt 2025 | B75: Commercial | C75: Downstream | D75: N | E75: Emerging Power | F75: Emerging Power | G75: Manufacturing | H75: Packs | I75: https://emergingpower.com/ | J75: 200 Holt Street | K75: Hackensack | L75: NJ | M75: US | N75: 7601 | O75: 201-441-3590 | P75: 40.871129 | Q75: -74.04498 | R75: 50 | U75: 2025 | W75: Emerging Power | X75: https://emergingpower.com/ | Y75: Hackensack | Z75: NJ | AA75: US | AB75: BM | AC75: 45922 | AD75: https://emergingpower.com/; https://emergingpower.com/about-us/ | AF75: Emerging Power is a New Jersey‑based small business since 2000, designing and manufacturing custom battery packs across chemistries for original equipment manufacturers, commercial, military, medical, internet of things, and unmanned aerial vehicle applications. | AH75: 32
A76: NaatBatt 2025 | B76: Commercial | C76: Downstream | D76: N | E76: Empower Greentech | F76: Empower Greentech | G76: Manufacturing | H76: Packs | I76: https://enpower-greentech.com/ | J76: 1500 E Walnut Ave | K76: Fullerton | L76: CA | M76: US | N76: 92831 | P76: 33.86815 | Q76: -117.90122 | U76: 2025 | W76: Empower Greentech | X76: https://enpower-greentech.com/ | Y76: Ann Arbor | Z76: MI | AA76: US | AB76: BM | AC76: 45923 | AD76: https://enpower-greentech.com/; https://www.globenewswire.com/news-release/2025/04/09/3058511/0/en/Mullen-and-Enpower-Greentech-Inc-Enter-Partnership-and-Supply-Agreement-to-Build-EGI-s-SWIFT-Series-of-Semi-Solid-State-Batteries.html | AE76: Mullen Automotive and Enpower Greentech are planning on building a battery pack plant in Fullerton, CA with a 202x SOP. | AF76: Enpower Greentech is a U.S.-based advanced battery cell manufacturer delivering semi‑solid‑state lithium‑ion, lithium‑metal, and silicon‑rich batteries which are designed and made in America for high-performance energy and mobility applications. | AH76: 29
A77: NaatBatt 2025 | B77: Planned | C77: Downstream | D77: N | E77: Endurance Motive | F77: Endurance Motive | G77: Battery Development | H77: Lithium-ion batteries | I77: https://endurancemotive.com/en/ | J77: TBD | K77: TBD | L77: TBD | M77: Mexico | W77: Endurance Motive | X77: https://endurancemotive.com/en/ | Y77: Canet d'en Berenguer | Z77: Valencia | AA77: Spain | AB77: BM | AC77: 45922 | AD77: https://endurancemotive.com/en/; https://endurancemotive.com/en/e-mobility/ | AE77: Building a plant in Puebla, Mexico | AF77: Endurance Motive, S.A. designs, manufactures, and sells lithium-ion batteries for industrial traction equipment, marine vessels, and urban electromobility, using integrated monitoring, GPS, and accelerometer systems. | AH77: 24
A78: NaatBatt 2025 | B78: Commercial | C78: Downstream | D78: N | E78: Energy Plug | F78: Energy Plug | G78: Battery Development | H78: Packs | I78: https://energyplug.com/ | J78: 1681 Chestnut Street, Ste 400 | K78: Vancouver | L78: British Columbia | M78: Canada | N78: V6J 4M6 | O78: 604-283-1262 | P78: 49.27108 | Q78: -123.1466 | R78: 50 | U78: 2025 | W78: Energy Plug | X78: https://energyplug.com/ | Y78: Vancouver | Z78: British Columbia | AA78: Canada | AB78: BM | AC78: 45922 | AD78: https://energyplug.com/; https://energyplug.com/#about | AF78: Energy Plug Technologies Corp. is a Vancouver‑based energy‑tech company providing secure, scalable battery energy storage systems, serving data centers, artificial intelligence, transportation, residential, and utility markets across Canada and into the U.S. | AH78: 32
A79: NaatBatt 2025 | E79: EnerSys | L79: CA | S79: 0 | T79: GWh/yr | U79: 2025 | X79: Closed
A80: NaatBatt 2025 | E80: EnerSys | L80: PA | S80: 0.07 | T80: GWh/yr | U80: 2025
A81: NaatBatt 2025 | B81: Commercial | C81: Downstream | D81: y- updated capacity | E81: EnerSys | F81: EnerSys | G81: Cell Assemblies/ Groupings | H81: Packs | I81: https://www.alpha.com/ | J81: 1075 Satellite Blvd NW #100 | K81: Suwanee | L81: GA | M81: US | N81: 30024 | O81: 800-322-5742 | P81: 34.019067 | Q81: -84.069399 | S81: 4 | T81: GWh/yr | U81: 2027 | W81: EnerSys | X81: https://www.enersys.com/en/ | Y81: Reading | Z81: PA | AA81: US | AB81: VP | AC81: 44429 | AD81: Questionnaire; enersys.com; alpha.com | AF81: EnerSys is a provider of energy storage systems for industrial applications, manufacturing and distributing a range of products including power batteries, battery chargers, power equipment for various industries​ | AG81: https://www.alpha.com/, https://www.alpha.com/company/overview/about-alpha-technologies | AH81: 28
A82: ICCT | E82: EnerVenue | H82: Battery | K82: Toledo | L82: KY | S82: 2.904 | T82: GWh/yr | U82: 2026 | V82: Metaly hydrogen batteries - https://enervenue.com/enervenue-opening-gigafactory-in-shelby-county-kentucky-to-scale-production-of-its-differentiated-energy-storage-solutions/#:~:text=March%2028%2C%202023-,EnerVenue%20Opening%20Gigafactory%20in%20Shelby%20County%2C%20Kentucky%20to%20Scale%20Production,manufacturing%20sites%20in%20subsequent%20phases.
A83: ICCT | E83: Enevate Corp | H83: Cells | K83: Walterboro | L83: South Carolina | S83: 0 | T83: GWh/yr | U83: 2028 | V83: Charging - https://www.enevate.com/
A84: NaatBatt 2025 | E84: Enovix | L84: CA | S84: 0.2 | T84: GWh/yr | U84: 2025
A85: NaatBatt 2025 | E85: Enovix | L85: CA | S85: 0.2 | T85: GWh/yr | U85: 2025
A86: EDF | E86: Enovix | H86: Cells | K86: Lansing | L86: Malaysia | S86: 0.495 | T86: GWh/yr | U86: 2024
A87: EDF | E87: EnPower | H87: Cells | K87: Warren | L87: OH | S87: 1 | T87: GWh/yr | U87: 2024 | V87: Hydrogen power modules
A88: NaatBatt 2025 | E88: Enpower Greentech | L88: MI | S88: 0.2 | T88: GWh/yr | U88: 2025 | X88: https://www.enpower-energy.com/en/news/usa-battery-development-manufacturing-updates?utm_source=chatgpt.com
A89: NaatBatt 2025 | E89: Enpower Greentech | L89: IN | S89: 0.8 | T89: GWh/yr | U89: 2025
A90: NaatBatt 2025 | B90: Commercial | C90: Downstream | D90: N | E90: Estes Energy | F90: Estes Energy | G90: Development | H90: Battery Systems(NMC, LFP, sodium) | I90: https://www.estes.energy/ | J90: 1235 Connecticut Street | K90: San Francisco | L90: CA | M90: US | N90: 94107 | P90: 37.75053 | Q90: -122.39635 | U90: 2025 | W90: Estes Energy | X90: https://www.estes.energy/ | Y90: San Francisco | Z90: CA | AA90: US | AB90: BM | AC90: 45922 | AD90: https://www.estes.energy/; https://www.estes.energy/company | AF90: Estes Energy Solutions is a San Francisco–based innovator developing high‑performance, chemistry‑agnostic battery systems for commercial electrification, backed by BMW i Ventures and Fortescue. | AH90: 21
A91: NaatBatt 2025 | B91: Under construction | C91: Downstream | D91: N | E91: e-STORAGE | F91: White Rock BESS | G91: Battery Development | H91: Battery Energy Storage | I91: https://www.csisolar.com/na/ | K91: White Rock | L91: Nova Scotia | M91: Canada | P91: 45.1051 | Q91: -64.4416 | S91: 0.705 | T91: GWh/yr | U91: 2026 | V91: https://investors.canadiansolar.com/news-releases/news-release-details/canadian-solars-e-storage-deliver-nova-scotias-first-grid-scale | W91: Canadian Solar | X91: https://www.csisolar.com/ | Y91: Guelph | Z91: ON | AA91: Canada | AB91: MK | AC91: 45872 | AD91: https://pv-magazine-usa.com/2024/07/08/battery-storage-deployment-in-canada-kicks-into-gear/, https://sustainablebiz.ca/e-storage-to-develop-150-mw-of-energy-storage-in-nova-scotia | AE91: This is one of three sites in a 150 MW / 705 MWh portfolio of projects for Nova Scotia Power. The first site is expected to be operational in 2025, with all three completed by the end of 2026 | AF91: Canadian Solar is a leading manufacturer of solar PV modules and a provider of solar energy and battery storage solutions, with a geographically diversified pipeline of utility-scale projects. | AH91: 28
A92: NaatBatt 2024 | B92: Under construction | C92: Downstream | D92: N | E92: e-STORAGE | F92: Bridgewater Grid-Scale Battery Facility | G92: Battery Development | H92: Battery Energy Storage | I92: https://www.csisolar.com/na/ | J92: King St | K92: Bridgewater | L92: Nova Scotia | M92: Canada | P92: 44.3756 | Q92: -64.5196 | S92: 0.705 | T92: GWh/yr | U92: 2026 | V92: https://investors.canadiansolar.com/news-releases/news-release-details/canadian-solars-e-storage-deliver-nova-scotias-first-grid-scale | W92: Canadian Solar | X92: https://www.csisolar.com/ | Y92: Guelph | Z92: ON | AA92: Canada | AB92: MK | AC92: 45872 | AD92: https://sustainablebiz.ca/e-storage-to-develop-150-mw-of-energy-storage-in-nova-scotia | AE92: This is one of three sites in a 150 MW / 705 MWh portfolio of projects for Nova Scotia Power. The first site is expected to be operational in 2025, with all three completed by the end of 2027 | AF92: Canadian Solar is a leading manufacturer of solar PV modules and a provider of solar energy and battery storage solutions, with a geographically diversified pipeline of utility-scale projects. | AH92: 28
A93: EDF | B93: Under construction | C93: Downstream | D93: N | E93: e-STORAGE | F93: Waverley Grid-Scale Battery Facility | G93: Battery Development | H93: Battery Energy Storage | I93: https://www.csisolar.com/na/ | J93: Waverley Rd | K93: Waverley | L93: Nova Scotia | M93: Canada | P93: 44.7573 | Q93: -63.5302 | S93: 0.705 | T93: GWh/yr | U93: 2026 | V93: https://investors.canadiansolar.com/news-releases/news-release-details/canadian-solars-e-storage-deliver-nova-scotias-first-grid-scale | W93: Canadian Solar | X93: https://www.csisolar.com/ | Y93: Guelph | Z93: ON | AA93: Canada | AB93: MK | AC93: 45872 | AD93: https://sustainablebiz.ca/e-storage-to-develop-150-mw-of-energy-storage-in-nova-scotia | AE93: This is one of three sites in a 150 MW / 705 MWh portfolio of projects for Nova Scotia Power. The first site is expected to be operational in 2025, with all three completed by the end of 2028 | AF93: Canadian Solar is a leading manufacturer of solar PV modules and a provider of solar energy and battery storage solutions, with a geographically diversified pipeline of utility-scale projects. | AH93: 28
A94: NaatBatt 2025 | E94: e-Storage | L94: KY | S94: 6 | T94: GWh/yr | U94: 2029
A95: NaatBatt 2025 | B95: Pre-commercial/ startup | C95: Downstream | D95: N | E95: Eviation Aircraft | F95: Arlington Production Site | G95: Assembly and Integration | H95: Battery Systems | I95: https://www.eviation.com/ | J95: 18204 59th Dr NE | K95: Arlington | L95: WA | M95: US | N95: 98223 | P95: 48.161 | Q95: -122.1481 | U95: 2025 | W95: Eviation Aircraft | X95: https://www.eviation.com/ | Y95: Arlington | Z95: WA | AA95: US | AB95: MK | AC95: 45876 | AD95: https://aviationweek.com/aerospace/advanced-air-mobility/eviation-ceo-expects-minor-refinements-production-alice, https://www.flyingmag.com/eviation-alice-electric-commuter/ | AF95: Eviation Aircraft develops and manufactures efficient electric aircraft to deliver a competitive solution for the regional mobility of people and goods. | AH95: 21
A96: EDF | E96: EVLO | H96: Battery Energy Storage | K96: Jeffersonville | L96: OH | S96: 3.05 | T96: GWh/yr | U96: 2025 | V96: Stationary storage production - not battery manufacturing
A97: NaatBatt 2025 | B97: Commercial | C97: Downstream | D97: N | E97: Exponential Power | F97: Exponential Power | G97: Cell Assemblies/ Groupings | H97: Packs | I97: https://www.exponentialpower.com/ | J97: 179 Easy St | K97: Carol Stream | L97: IL | M97: US | N97: 60188 | O97: 630-221-1730 | P97: 41.897035 | Q97: -88.116064 | R97: 100 | U97: 2025 | W97: Exponential Power | X97: https://www.exponentialpower.com/ | Y97: Milwaukee | Z97: WI | AA97: US | AB97: VP | AC97: 44766 | AD97: Thomasnet: Battery Packs / manufacturers; exponentialpower.com | AE97: Li.ON FORCE industrial battery; Total Company Workforce Range: 100-199; Updated Long/Lat | AF97: Exponential Power provides stored power products and services. | AG97: https://www.exponentialpower.com/, https://www.exponentialpower.com/about-us | AH97: 8
A98: NaatBatt 2025 | B98: Commercial | C98: Downstream | D98: N | E98: Exponential Power | F98: Exponential Power | G98: Cell Assemblies/ Groupings | H98: Packs | I98: https://www.exponentialpower.com/ | J98: 7603 Honeywell Dr. | K98: Fort Wayne | L98: IN | M98: US | N98: 46825 | O98: 260-420-5170 | P98: 41.149346 | Q98: -85.154135 | R98: 100 | U98: 2025 | W98: Exponential Power | X98: https://www.exponentialpower.com/ | Y98: Milwaukee | Z98: WI | AA98: US | AB98: EW | AC98: 44418 | AD98: Thomasnet: Battery Packs / manufacturers; exponentialpower.com | AE98: Li.ON FORCE industrial battery; Total Company Workforce Range: 100-199 | AF98: Exponential Power provides stored power products and services. | AG98: https://www.exponentialpower.com/, https://www.exponentialpower.com/about-us | AH98: 8
A99: NaatBatt 2025 | B99: Commercial | C99: Downstream | D99: N | E99: Exponential Power | F99: Exponential Power | G99: Cell Assemblies/ Groupings | H99: Packs | I99: https://www.exponentialpower.com/ | J99: 2670 Observation Trail | K99: Rockwell | L99: TX | M99: US | N99: 75032 | O99: 214-247-5150 | P99: 32.913413 | Q99: -96.422633 | R99: 100 | U99: 2025 | W99: Exponential Power | X99: https://www.exponentialpower.com/ | Y99: Milwaukee | Z99: WI | AA99: US | AB99: EW | AC99: 44418 | AD99: Thomasnet: Battery Packs / manufacturers; exponentialpower.com | AE99: Li.ON FORCE industrial battery; Total Company Workforce Range: 100-199 | AF99: Exponential Power provides stored power products and services. | AG99: https://www.exponentialpower.com/, https://www.exponentialpower.com/about-us | AH99: 8
A100: NaatBatt 2025 | B100: Commercial | C100: Downstream | D100: y- updated capacity | E100: Factorial Energy | F100: Factorial | G100: Cell Assemblies/ Groupings | H100: Packs | I100: https://factorialenergy.com/ | J100: 19 Presidential Way Suite 103 | K100: Woborn | L100: MA | M100: US | N100: 1801 | O100: 617-315-9733 | P100: 42.524667 | Q100: -71.139204 | R100: 100 | S100: =3/1000 -> 0.003 | T100: GWh/yr | U100: 2025 | W100: Factorial Energy | X100: https://factorialenergy.com/ | Y100: Woburn | Z100: MA | AA100: US | AB100: KK | AC100: 44774 | AF100: Factorial delivers high performing, safe solid-state batteries that power life to the fullest. | AG100: https://factorialenergy.com/, https://factorialenergy.com/purpose/ | AH100: 13
...

Sheet production capacity sum
A3: Sum of Production Capacity | B3: Midstream
A4: 2025 | B4: Downstream | C4: Midstream | D4: Grand Total
B5: 0 | D5: 0
A6: 2023 | B6: 90 | D6: 90
A7: 2024 | B7: 23 | C7: 50 | D7: 73
A8: 2025 | B8: 504.72304 | C8: 173.865 | D8: 678.58804
A9: 2026 | B9: 312.96603 | C9: 33 | D9: 345.96603
A10: 2027 | B10: 256.768 | C10: 379.7 | D10: 636.468
A11: 2028 | B11: 130 | C11: 15 | D11: 145
A12: 2029 | C12: 411 | D12: 411
A13: 2030 | B13: 32 | D13: 32
B14: 0 | D14: 0
A15: Grand Total | B15: 1349.4571 | C15: 1062.565 | D15: 2412.0221
B17: yearly
B18: Downstream | C18: Midstream | D18: Total
A19: 2023 | B19: 90 | D19: 90
A20: 2024 | B20: 23 | C20: 50 | D20: 73
A21: 2025 | B21: 504.72304 | C21: 174.065 | D21: 678.78804
A22: 2026 | B22: 312.96603 | C22: 33 | D22: 345.96603
A23: 2027 | B23: 256.768 | C23: 379.7 | D23: 636.468
A24: 2028 | B24: 130 | C24: 15 | D24: 145
A25: 2029 | C25: 411 | D25: 411
A26: 2030 | B26: 32 | D26: 32
B29: total
B30: Downstream | C30: Midstream | D30: Total | E30: % loss | F30: Midstream loss | G30: Downstream loss | H30: GWh midstream manufacturing loss | I30: GWh downstream manufacturing loss
A31: 2023 | B31: =B19*F42 -> 69.3 | C31: =C19 | D31: =SUM(B31:C31) -> 69.3 | E31: 0.0767 | F31: =E31*$F$40 -> 0.05 | G31: =E31-F31 -> 0.0267 | H31: =F31*C31 -> 0 | I31: =B31*G31 -> 1.85031
A32: 2024 | B32: =(B20*$F$42)+B31 -> 87.01 | C32: =(C20*$F$42)+C31 -> 38.5 | D32: =SUM(B32:C32) -> 125.51 | E32: =E31-((E$31-E$38)/7) -> 0.071942857 | F32: =E32*$F$40 -> 0.046898864 | G32: =E32-F32 -> 0.025043993 | H32: =F32*C32 -> 1.8056063 | I32: =B32*G32 -> 2.1790779
A33: 2025 | B33: =(B21*$F$42)+B32 -> 475.64674 | C33: =(C21*$F$42)+C32 -> 172.53005 | D33: =SUM(B33:C33) -> 648.17679 | E33: =E32-((E$31-E$38)/7) -> 0.067185714 | F33: =E33*$F$40 -> 0.043797728 | G33: =E33-F33 -> 0.023387987 | H33: =F33*C33 -> 7.5564241 | I33: =B33*G33 -> 11.12442
A34: 2026 | B34: =(B22*$F$42)+B33 -> 716.63058 | C34: =(C22*$F$42)+C33 -> 197.94005 | D34: =SUM(B34:C34) -> 914.57063 | E34: =E33-((E$31-E$38)/7) -> 0.062428571 | F34: =E34*$F$40 -> 0.040696592 | G34: =E34-F34 -> 0.02173198 | H34: =F34*C34 -> 8.0554854 | I34: =B34*G34 -> 15.573801
A35: 2027 | B35: =(B23*$F$42)+B34 -> 914.34194 | C35: =(C23*$F$42)+C34 -> 490.30905 | D35: =SUM(B35:C35) -> 1404.651 | E35: =E34-((E$31-E$38)/7) -> 0.057671429 | F35: =E35*$F$40 -> 0.037595455 | G35: =E35-F35 -> 0.020075973 | H35: =F35*C35 -> 18.433392 | I35: =B35*G35 -> 18.356304
A36: 2028 | B36: =(B24*$F$42)+B35 -> 1014.4419 | C36: =(C24*$F$42)+C35 -> 501.85905 | D36: =SUM(B36:C36) -> 1516.301 | E36: =E35-((E$31-E$38)/7) -> 0.052914286 | F36: =E36*$F$40 -> 0.034494319 | G36: =E36-F36 -> 0.018419966 | H36: =F36*C36 -> 17.311286 | I36: =B36*G36 -> 18.685987
A37: 2029 | B37: =(B25*$F$42)+B36 -> 1014.4419 | C37: =(C25*$F$42)+C36 -> 818.32905 | D37: =SUM(B37:C37) -> 1832.771 | E37: =E36-((E$31-E$38)/7) -> 0.048157143 | F37: =E37*$F$40 -> 0.031393183 | G37: =E37-F37 -> 0.01676396 | H37: =F37*C37 -> 25.689954 | I37: =B37*G37 -> 17.006064
A38: 2030 | B38: =(B26*$F$42)+B37 -> 1039.0819 | C38: =(C26*$F$42)+C37 -> 818.32905 | D38: =SUM(B38:C38) -> 1857.411 | E38: 0.0434 | F38: =E38*$F$40 -> 0.028292047 | G38: =E38-F38 -> 0.015107953 | H38: =F38*C38 -> 23.152204 | I38: =B38*G38 -> 15.698401
E40: cell loss as percent of total loss | F40: =0.05/E31 -> 0.65189048
E42: Operating capacity | F42: 0.77

Sheet Electrode & Cell Manufacturing
A1: ID | B1: Status | C1: Supply Chain Segment | D1: Company | E1: NAATBatt Member | F1: Facility Name | G1: Product/Facility Type | H1: Product | I1: Company Website | J1: Facility Address | K1: Facility City | L1: Facility State or Province | M1: Facility Country | N1: Facility Zip | O1: Facility Phone | P1: Latitude | Q1: Longitude | R1: Facility Workforce | S1: Production Capacity | T1: Production Units | U1: HQ Company | V1: HQ Company Website | W1: HQ City | X1: HQ State or Province | Y1: HQ Country | Z1: QC | AA1: QC Date | AB1: Sources | AC1: Notes | AD1: Brief Company Profile | AE1: Sources2 | AF1: Summary Word Count | AG1: Contact | AH1: Contact Email | AI1: Contact Phone | AJ1: Column1
A2: 4008 | B2: Commercial | C2: Midstream | D2: Altairnano | E2: No | F2: Altairnano | G2: Prismatic pouch cells | H2: Lithium titanium oxide | I2: https://altairnano.com/ | J2: 7311 Quality Circle | K2: Anderson | L2: IN | M2: US | N2: 46013 | O2: 317-333-7617 | P2: 40.040127 | Q2: -85.728122 | R2: 106 | U2: Altairnano | V2: https://altairnano.com/ | W2: Reno | X2: NV | Y2: US | Z2: VP | AA2: 8/4/2022 8/14/2025 | AB2: altairnano.com;https://www.sec.gov/Archives/edgar/data/1016546/000143774916042208/alti20160922_10k.htm;https://en.wikipedia.org/wiki/Altairnano | AC2: Closed its Reno manuf. Facility and moved it to China. Initial facility in Anderson is listed as permanently closed; BNEF does not list it; Unsure if it makes cells in US. Called and emailed. Used to be called Altair Nanotechnologies | AD2: Altairnano leverages nanoscale technologies for powerful lithium titanate solutions. Its unique nano cells bring advantages to electric grid, transportation, and industrial applications. | AE2: https://altairnano.com/ | AF2: =IF(LEN(TRIM(AD2))=0,0,LEN(TRIM(AD2))-LEN(SUBSTITUTE(AD2," ",""))+1) -> 22
A3: 4001 | B3: Commercial | C3: Midstream | D3: A123 Systems | E3: No | F3: A123 Advanced Engineering Center | G3: Other/ Unknown cells | H3: Lithium iron phosphate | I3: http://www.a123systems.com/ | J3: 27101 Cabaret Drive | K3: Novi | L3: MI | M3: US | N3: 48377 | O3: 248-412-9100 | P3: 42.490552 | Q3: -83.48706 | R3: 493 | S3: 0.969 | T3: GWh/yr | U3: Wanxiang A123 | V3: http://www.a123systems.com/ | W3: Hangzhou | X3: Zheijiang | Y3: China | Z3: VP | AA3: 44781 | AB3: Questionnaire; A123systems.com; BNEF Interactive Dataset; Cell manufacturing; https://www.buzzfile.com/business/A123-Systems-LLC-248-412-9249 | AD3: A123 Systems aims to make the air fresher. It leads in batteries and control systems, boasting global patents and a renowned customer base after 20 years of innovation. | AE3: http://www.a123systems.com/ | AF3: =IF(LEN(TRIM(AD3))=0,0,LEN(TRIM(AD3))-LEN(SUBSTITUTE(AD3," ",""))+1) -> 27
A4: 4002 | B4: Commercial | C4: Midstream | D4: ABSL Power Solutions, Inc. | E4: Yes | F4: ABSL Power Solutions, Inc. | G4: Other/ Unknown cells | H4: Other/ Unknown | I4: https://www.enersys.com/en/products/batteries/absl/absl-space/ | J4: 1751 S. Fordham St., Suite 100 | K4: Longmont | L4: CO | M4: US | N4: 80503 | P4: 40.138802 | Q4: -105.14105 | R4: 100 | U4: Enersys | V4: https://www.enersys.com/en/ | W4: Reading | X4: PA | Y4: US | Z4: VP | AA4: 45339 | AB4: Questionnaire | AD4: ABSL manufactures lithium-ion batteries for space applications. It conducts design, structural and thermal analysis to ensure their performance exceeds the most demanding requirements. | AF4: =IF(LEN(TRIM(AD4))=0,0,LEN(TRIM(AD4))-LEN(SUBSTITUTE(AD4," ",""))+1) -> 23 | AG4: Roger Carlone | AH4: roger.carlone@eas.enersys.com
A5: 4003 | B5: Commercial | C5: Midstream | D5: Advanced Battery Concepts | E5: Yes | F5: Advanced Battery Concepts | G5: Cell Manufacturing and Assembly | H5: Sealed Bipolar Lead Acid | I5: https://advancedbatteryconcepts.com/ | J5: 8 Consumers Energy Parkway | K5: Clare | L5: MI | M5: US | N5: 48617 | O5: 989-424-6645 | P5: 43.845834 | Q5: -84.758957 | R5: 50 | U5: Advanced Battery Concepts | V5: https://advancedbatteryconcepts.com/ | W5: Clare | X5: MI | Y5: US | Z5: SD | AA5: 45475 | AB5: https://advancedbatteryconcepts.com/ | AD5: Advanced Battery Concepts delivers economical, socially, and environmentally responsible energy storage solutions with its advanced bipolar battery technology, driving a cleaner, more sustainable future. | AE5: https://advancedbatteryconcepts.com/ | AF5: =IF(LEN(TRIM(AD5))=0,0,LEN(TRIM(AD5))-LEN(SUBSTITUTE(AD5," ",""))+1) -> 24
A6: 4101 | B6: Cancelled | C6: Downstream | D6: Advanced Cell Engineering | F6: Advanced Cell Engineering Inc. | G6: Cell Assemblies/ Groupings | H6: Packs | I6: https://www.advancedcellengineering.com/ | J6: 2634 SE Market Pl | K6: Stuart | L6: FL | M6: US | N6: 34997 | O6: 772-382-9019 | P6: 27.155753 | Q6: -80.217023 | R6: 50 | U6: Advanced Cell Engineering Inc. | V6: https://www.advancedcellengineering.com/ | W6: Stuart | X6: FL | Y6: US | Z6: SD MK | AA6: 2/14/2025 8/27/2025 | AB6: Ahmad's email on 2.13.25; https://www.inforuptcy.com/browse-filings/florida-southern-bankruptcy-court/9:25-bk-16317/bankruptcy-case-advanced-cell-engineering-inc | AC6: The company filed for chapter 7 bankruptcy on June 3, 2025, in the Southern District of Florida | AD6: Advanced Cell Engineering discovers advanced lithium-ion technologies and create better energy storage solutions. Their mission is to accelerate the pace of battery innovation and empower customers. | AF6: =IF(LEN(TRIM(AD6))=0,0,LEN(TRIM(AD6))-LEN(SUBSTITUTE(AD6," ",""))+1) -> 26
A7: 4004 | B7: Commercial | C7: Midstream | D7: AESC | E7: No | F7: US Plant | G7: Prismatic pouch cells | H7: Nickel manganese cobalt | I7: https://www.aesc-group.com/en/ | J7: 500 Battery Plant Road | K7: Smyrna | L7: TN | M7: US | N7: 37167 | O7: 615-768-3505 | P7: 35.960162 | Q7: -86.483048 | R7: 350 | S7: 3 | T7: GWh/yr | U7: AESC | V7: https://www.aesc-group.com/en/ | W7: Zama | X7: Kanagawa | Y7: Japan | Z7: VP MK | AA7: 11/25/2022 8/14/2025 | AB7: BNEF: Interactive Datasets/Storage/Cell manufacturers; envision-aesc.com; https://www.manta.com/c/mkxnxqy/envision-aesc-us-llc#:~:text=Envision%20Aesc%20Us%20Smyrna%20TN%2C%2037167%20%E2%80%93%20Manta.com&text=Categorized%20under%20Computers%20Manufacturers.,a%20staff%20of%20approximately%20350; https://www.automotivemanufacturingsolutions.com/emobility/lithium-ion-battery-gigafactory-database/41937.article;https://www.envision-aesc.com/en/network.html;https://www.apollo.io/companies/Envision-AESC/5e57c2c4f6d38f0001777aae?chart=count; https://source.benchmarkminerals.com/article/lg-chem-tennessee-cathode-plant-could-double-north-american-production?mc_cid=c72c66f531&mc_eid=6a6017029d; https://source.benchmarkminerals.com/article/lg-chem-tennessee-cathode-plant-could-double-north-american-production?mc_cid=c72c66f531&mc_eid=6a6017029d, https://www.bizjournals.com/nashville/news/2025/06/25/aesc-envision-smyrna-battery-factory.html | AC7: Graphite anodes; Facility used to be Nissan factory and was acquired in 2012; Shifting focus from EV to ESS. TBD if this changes chemistry and format. | AD7: AESC Group leads the decarbonization revolution with artificial intelligence converging with the internet of things -driven battery solutions, globally pioneering high-performance EV and energy storage, accelerating the shift to a sustainable future. | AE7: https://www.aesc-group.com/en/, https://www.aesc-group.com/en/aboutus.html | AF7: =IF(LEN(TRIM(AD7))=0,0,LEN(TRIM(AD7))-LEN(SUBSTITUTE(AD7," ",""))+1) -> 31
A8: 4005 | B8: Paused construction | C8: Midstream | D8: AESC | E8: No | F8: Florence County Electric Battery Gigafactory | G8: Other/ Unknown cells | H8: Other/ Unknown | I8: https://www.aesc-group.com/en/ | J8: Technology and Business Park | K8: Florence | L8: SC | M8: US | P8: 34.19519 | Q8: -79.762675 | R8: 1170 (Planned) | S8: 30 | T8: GWh/yr | U8: AESC | V8: https://www.aesc-group.com/en/ | W8: Zama | X8: Kanagawa | Y8: Japan | Z8: VP MK | AA8: 6/11/2023 8/14/2025 | AB8: BNEF Cell database; https://governor.sc.gov/news/2022-12/envision-aesc-establish-florence-county-electric-vehicle-battery-gigafactory; https://www.electrive.com/2023/06/08/aesc-kicks-off-construction-of-battery-plant-in-south-carolina/#:~:text=Battery%20cell%20manufacturer%20AESC%20(formerly,come%20on%20stream%20in%202026, https://scdailygazette.com/2025/06/05/electric-vehicle-battery-company-halts-construction-of-sc-manufacturing-plant/ | AC8: $810M investment to support BMW; Construction started in June 2023; Resume SOP 202x | AD8: AESC Group leads the decarbonization revolution with artificial intelligence converging with the internet of things -driven battery solutions, globally pioneering high-performance EV and energy storage, accelerating the shift to a sustainable future. | AE8: https://www.aesc-group.com/en/, https://www.aesc-group.com/en/aboutus.html | AF8: =IF(LEN(TRIM(AD8))=0,0,LEN(TRIM(AD8))-LEN(SUBSTITUTE(AD8," ",""))+1) -> 31
A9: 4006 | B9: Paused construction | C9: Midstream | D9: AESC | E9: No | F9: Bowling Green Plant | G9: Other/ Unknown cells | H9: Nickel manganese cobalt | I9: https://www.aesc-group.com/en/ | J9: Kentucky Transpark | K9: Bowling Green | L9: KY | M9: US | N9: 42101 | O9: 502-377-5675 | P9: 37.04 | Q9: -86.3 | R9: 2000 (Planned) | S9: 30 | T9: GWh/yr | U9: Envision | V9: https://spectrumnews1.com/ky/bowling-green/news/2022/04/26/envision-aesc-plans-to-establish--2-billion-gigafactory-in-kentucky, https://ced.ky.gov/Newsroom/NewsPage/20220830_EnvisionAESCGroundbreaking | W9: Zama | X9: Kanagawa | Y9: Japan | Z9: VP MK | AA9: 6/19/2023 8/14/2025 | AB9: https://spectrumnews1.com/ky/bowling-green/news/2022/04/26/envision-aesc-plans-to-establish--2-billion-gigafactory-in-kentucky; BNEF Interactive Dataset Cell Manufacturing; https://ced.ky.gov/Newsroom/NewsPage/20220830_EnvisionAESCGroundbreaking, https://www.wsj.com/business/autos/china-aesc-battery-2d61cc41 | AC9: Commissioning expected by EOY 2027; $2B investment; SOP 202x | AD9: AESC Group leads the decarbonization revolution with artificial intelligence converging with the internet of things -driven battery solutions, globally pioneering high-performance EV and energy storage, accelerating the shift to a sustainable future. | AE9: https://www.aesc-group.com/en/, https://www.aesc-group.com/en/aboutus.html | AF9: =IF(LEN(TRIM(AD9))=0,0,LEN(TRIM(AD9))-LEN(SUBSTITUTE(AD9," ",""))+1) -> 31
A10: 4007 | B10: Pre-commercial/ startup | C10: Midstream | D10: Æsir Technologies, Inc. | E10: No | F10: R&D Facility | G10: Battery Development | H10: Rechargeable aqueous hybrid battery | I10: https://www.aesirtec.com | J10: 960 Technology Blvd. Suite 1 | K10: Bozeman | L10: MT | M10: US | N10: 59718 | O10: 417-553-0237 | P10: 45.669674 | Q10: -111.06596 | R10: 50 | U10: Æsir Technologies, Inc. | V10: https://www.aesirtec.com | W10: Joplin | X10: MO | Y10: US | Z10: MK | AA10: 45584 | AB10: https://www.aesirtec.com/LithiumZinc | AC10: Plans to offer nano material additives to Li-ion market this year (6 tpy), alkaline market in 2023 (350 tpy), and rechargeable markets in 2025 (5000 tpy) | AD10: Æsir Technologies develops lithium-zinc batteries offering enhanced cycle life, energy density, and safety. Its rechargeable aqueous hybrid battery technology provides sustainable, recyclable, and non-toxic energy storage solutions. | AF10: =IF(LEN(TRIM(AD10))=0,0,LEN(TRIM(AD10))-LEN(SUBSTITUTE(AD10," ",""))+1) -> 27 | AH10: info@aesirtec.com | AI10: 417-553-0237
A11: 4009 | B11: Under construction | C11: Midstream | D11: American Battery Factory | E11: Yes | F11: American Battery Factory | G11: Prismatic metal can cells | H11: Lithium iron phosphate | I11: https://americanbatteryfactory.com/ | J11: Aerospace Research Campus - I10 and South Rita Road | K11: Tucson | L11: AZ | M11: US | N11: 84003 | O11: 385-269-2061 | P11: 32.089065 | Q11: -110.80434 | R11: 1000 (Planned) | S11: 4 | T11: GWh/yr | U11: American Battery Factory | V11: https://americanbatteryfactory.com/ | W11: American Fork | X11: UT | Y11: US | Z11: VP MK | AA11: 1/13/2024 8/14/2025 | AB11: Questionnaire; telecon 8/20/21; BNEF Interactive Dataset Cell Manufacturing; https://pv-magazine-usa.com/2022/03/08/plans-announced-for-a-us-lithium-ferro-phosphate-battery-gigafactory-network/; https://americanbatteryfactory.com/press/2023-10-26-american-battery-factory-breaks-ground; https://content.civicplus.com/api/assets/ae999a10-d4d7-473b-8b3b-772516ff2b30 | AC11: $1.2B capital investment; SOP 2027; Targeting 20 GWh eventually | AD11: American Battery Factory revolutionizes energy with U.S.-owned vertical manufacturing for LFP battery cells, integrating software, hardware, and technology to ensure renewable, independent, and affordable energy. | AE11: https://americanbatteryfactory.com/ | AF11: =IF(LEN(TRIM(AD11))=0,0,LEN(TRIM(AD11))-LEN(SUBSTITUTE(AD11," ",""))+1) -> 24
A12: 4010 | B12: Commercial | C12: Midstream | D12: American Lithium Energy | E12: No | F12: ALEC | G12: Other/ Unknown cells | H12: Other/ Unknown | I12: https://www.americanlithiumenergy.com/ | J12: 1395 Aspen Way | K12: Vista | L12: CA | M12: US | N12: 92008 | O12: 760-444-5244 | P12: 33.136255 | Q12: -117.24337 | R12: 30 | U12: American Lithium Energy | V12: https://www.americanlithiumenergy.com/ | W12: Carlsbad | X12: CA | Y12: US | Z12: VP MK | AA12: 45896 | AB12: americanlithiumenergy.com; Questionnaire; https://www.dnb.com/business-directory/company-profiles.american_lithium_energy_corp.eb6cbeb7e4a7cbf5bd0c71ced5c81852.html;https://lithiumamericas.com/usa/thacker-pass/; https://www.connectcre.com/stories/lithium-ion-battery-maker-nearly-quadruples-space-in-move-to-vista/ | AC12: Focuses on batteries and packs for military applications | AD12: American Lithium Energy leads with the world's highest energy density silicon-based lithium-ion batteries, setting industry safety benchmarks. Its patented technologies ensure powerful, long-lasting, and safe cells, eliminating trade-offs in energy density, life cycle, and safety. | AE12: https://www.americanlithiumenergy.com/, https://www.americanlithiumenergy.com/about | AF12: =IF(LEN(TRIM(AD12))=0,0,LEN(TRIM(AD12))-LEN(SUBSTITUTE(AD12," ",""))+1) -> 34
A13: 4099 | B13: Under construction | C13: Midstream | D13: Amplify Cell Technologies | E13: No | F13: Marshall County Battery Cell Manufacturing Plant | G13: Cell | H13: Lithium-iron-phosphate battery cells | I13: https://amplifycelltech.com/ | J13: Chickasaw Trail Industrial Park | K13: Byhalia | L13: MS | M13: US | P13: 34.870605 | Q13: -89.69072 | R13: 2000 | S13: 21 | T13: Gwh/yr | U13: Amplify Cell Technologies | V13: https://amplifycelltech.com/ | W13: Byhalia | X13: MS | Y13: US | Z13: MK | AA13: 2/5/2025 8/14/2025 | AB13: https://www.paccar.com/news/current-news/2024/amplify-cell-technologies-begins-construction-of-mississippi-battery-cell-factory/, https://www.daimlertruck.com/en/newsroom/pressrelease/amplify-cell-technologies-a-joint-venture-between-accelera-by-cummins-daimler-truck-and-paccar-begins-construction-of-mississippi-battery-cell-factory-52757135; https://www.linkedin.com/posts/jack-baldwin-1052b1188_aviation-construction-constructionjobs-activity-7343246539114332160-qCgy/ | AC13: 2027 SOP | AD13: Amplify Cell Technologies produces lithium-iron-phosphate battery cells for electric commercial vehicles. | AF13: =IF(LEN(TRIM(AD13))=0,0,LEN(TRIM(AD13))-LEN(SUBSTITUTE(AD13," ",""))+1) -> 11
A14: 4011 | B14: Commercial | C14: Midstream | D14: Amprius | E14: No | F14: Amprius Lab | G14: Pouch cells | H14: Silicon nanowire anode | I14: https://amprius.com/ | J14: 1180 Page Ave | K14: Fremont | L14: CA | M14: US | N14: 94538 | O14: 800-425-8803 | P14: 37.468236 | Q14: -121.92567 | S14: 0.002 | T14: GWh/yr | U14: Amprius Technologies | V14: https://amprius.com/ | W14: Fremont | X14: CA | Y14: US | Z14: VP MK | AA14: 6/19/2023 8/14/2025 | AB14: energy.gov/mesc/bipartisan-infrastructure-law-battery-materials-processing-and-battery-manufacturing-recycling; https://www.businesswire.com/news/home/20230602005357/en/Amprius-and-U.S.-Department-of-Energy-Mutually-Agree-to-End-Negotiations-for-Cost-Sharing-Grant, https://ir.amprius.com/news-events/press-releases/detail/138/amprius-technologies-announces-date-for-second-quarter-2025-results-and-business-updates | AC14: Recipient of DE-FOA-2678 to build a MWh-scale manufacturing line, but decided that they would do it with private funding instead. This facility is the company's headquarters and pilot production line. It is where they validate their manufacturing processes before scaling them. | AD14: Amprius pioneers the highest energy density lithium-ion batteries, enabling new applications and accelerating markets with indispensable storage capabilities using silicon nanowires. | AF14: =IF(LEN(TRIM(AD14))=0,0,LEN(TRIM(AD14))-LEN(SUBSTITUTE(AD14," ",""))+1) -> 21
A15: 4012 | B15: Cancelled | C15: Midstream | D15: Amprius | E15: No | F15: Amprius Fab | G15: Pouch cells | H15: Lithium-ion batteries, Silicon nanowire anode | I15: https://amprius.com/ | J15: 18875 E. Bromley Lane | K15: Brighton | L15: CO | M15: US | N15: 80601 | P15: 39.976901 | Q15: -104.76452 | R15: 330 (Planned) | S15: 5 | T15: GWh/yr | U15: Amprius Technologies | V15: https://amprius.com/ | W15: Fremont | X15: CA | Y15: US | Z15: VP MK | AA15: 6/19/2023 8/14/2025 | AB15: amprius.com; Questionnaire; Pitchbook.com; https://d1io3yog0oux5.cloudfront.net/_4a2b0e55ef4b9aff108f8757f9b1dbdc/amprius/db/2227/20814/pdf/Amprius+Technologies+Investor+Presentation+November+2022.pdf; https://amprius.com/amprius-technologies-selects-colorado-for-gigawatt-hour-scale-factory-site/; https://www.businesswire.com/news/home/20230602005357/en/Amprius-and-U.S.-Department-of-Energy-Mutually-Agree-to-End-Negotiations-for-Cost-Sharing-Grant, https://coloradosun.com/2025/06/25/colorado-clean-energy-project-cancellations/ | AC15: Recipient of DE-FOA-2678 to build a MWh-scale manufacturing line, but decided that they would do it with private funding instead. Initial plant will be 500 kWh by 2025 and then scaled up to 5 GWh. | AD15: Amprius pioneers the highest energy density lithium-ion batteries, enabling new applications and accelerating markets with indispensable storage capabilities using silicon nanowires. | AE15: https://amprius.com/, https://amprius.com/about/ | AF15: =IF(LEN(TRIM(AD15))=0,0,LEN(TRIM(AD15))-LEN(SUBSTITUTE(AD15," ",""))+1) -> 20
A16: 4013 | B16: Commercial | C16: Midstream | D16: Ateios Systems | E16: No | F16: Ateios Systems | G16: LIB Manufacturing | H16: Electrode | I16: https://ateios.com/ | J16: 7979 S Energy Dr | K16: Newberry | L16: IN | M16: US | N16: 47449 | O16: 330-310-1323 | P16: 38.904714 | Q16: -86.918956 | R16: 12 | S16: 1+ | T16: GWh/yr | U16: Ateios Systems | V16: https://ateios.com/ | W16: Newberry | X16: IN | Y16: US | Z16: MK | AA16: 45689 | AB16: https://www.militaryaerospace.com/power/article/55241290/lithium-ion-batteries-reduced-fire-risk, https://www.wric.com/business/press-releases/ein-presswire/770751457/ateios-systems-partners-with-multiple-battery-assemblers-to-achieve-gwh-capacity-of-batteries-with-raicore-inside/ | AC16: Awarded one-year sole-source contract from US Army Contracting Command in Adelphi, Md. To produce 3Ah Li-ion batteries with the ability for reduced fire risk from battlefield damage. | AD16: Ateios Systems, under a U.S. Army contract, will produce 3Ah Li-ion batteries with reduced fire risk, featuring Ateios electrolyte, graphene-based anode, and semi-solid-state, nickel-manganese-cobalt cathode for military use. | AF16: =IF(LEN(TRIM(AD16))=0,0,LEN(TRIM(AD16))-LEN(SUBSTITUTE(AD16," ",""))+1) -> 28
A17: 4100 | B17: Pre-commercial/ startup | C17: Midstream | D17: Blue Current | E17: No | F17: Blue Current Pilot Manufacturing Facility | G17: Cell | H17: Silicon-based solid-state batteries | I17: https://bluecurrent.com/ | J17: 25821 Industrial Blvd | K17: Hayward | L17: CA | M17: US | N17: 94545 | P17: 37.634162 | Q17: -122.11475 | R17: 50 | U17: Blue Current | V17: https://bluecurrent.com/ | W17: Hayward | X17: CA | Y17: US | Z17: MK | AA17: 45698 | AB17: https://bluecurrent.com/about/, https://bluecurrent.com/news/2023-momentum-release/ | AD17: Blue Current is developing silicon-based solid-state batteries for safer, high-energy-density energy storage solutions. | AF17: =IF(LEN(TRIM(AD17))=0,0,LEN(TRIM(AD17))-LEN(SUBSTITUTE(AD17," ",""))+1) -> 13
A18: 4014 | B18: Commercial | C18: Midstream | D18: Blue Solutions Canada Inc. | E18: Yes | F18: Blue Solutions Canada Inc. | G18: Prismatic metal can cells | H18: Solid-state lithium-metal polymer (LMP®) | I18: https://www.blue-solutions.ca/ | J18: 1601 Rue de Coulomb | K18: Boucherville | L18: QC | M18: Canada | N18: J4B 8J7 | O18: 450-655-6622 | P18: 45.556091 | Q18: -73.425186 | R18: 450 | S18: 0.2 | T18: GWh/yr | U18: Blue Solutions Canada Inc. | V18: https://www.blue-solutions.ca/ | W18: Boucherville | X18: QC | Y18: Canada | Z18: VP MK | AA18: 8/4/2022 8/14/2025 | AB18: Questionnaire;https://www.blue-solutions.com/app/assets-bluesolutions/uploads/2021/04/0414_bsol_2102265_brochure_16_pages_gb.pdf; BNEF Interactive Dataset Cell manufacturing; https://www.reuters.com/business/autos-transportation/battery-maker-blue-solutions-plans-2-billion-euro-gigafactory-france-2024-05-28/ | AC18: Blue Solutions develops and produces batteries based on its own unique solid-state Lithium Metal Polymer (LMP®) technology. The company controls every step of the design and mass production of these groundbreaking solid-state batteries | AD18: Blue Solutions propels battery tech, elevating energy density, power, and safety. Its solid-state 100% tech, highly recyclable, secures an endurable future. | AE18: https://www.blue-solutions.ca/en | AF18: =IF(LEN(TRIM(AD18))=0,0,LEN(TRIM(AD18))-LEN(SUBSTITUTE(AD18," ",""))+1) -> 20
A19: 4015 | B19: Under construction | C19: Midstream | D19: BlueOvalSK (JV of Ford and SK On) | E19: No | F19: BlueOvalSK Tennessee Plant | G19: Prismatic pouch cells | H19: Nickel manganese cobalt | I19: https://blueovalsk.com/ | J19: 2025 BlueOval City Dr | K19: Stanton | L19: TN | M19: US | N19: 38069 | P19: 35.402916 | Q19: -89.417312 | R19: 5800 (Planned) | S19: 43 | T19: GWh/Yr | U19: S K Innovation | V19: https://www.skinnovation.com/ | W19: Jongno-gu | X19: Seoul | Y19: S Korea | Z19: VP MK | AA19: 11/25/2022 8/14/2025 | AB19: https://www.kentucky.com/news/state/kentucky/article254556442.html; https://www.commercialappeal.com/story/money/business/2022/07/14/ford-sk-on-ev-battery-plant-west-tennessee-blue-oval-city/10038277002/; BNEF Interactive Dataset\Cell Manufacturing; https://source.benchmarkminerals.com/article/lg-chem-tennessee-cathode-plant-could-double-north-american-production?mc_cid=c72c66f531&mc_eid=6a6017029d, https://ttc.tml1.org/2025/03/28/employees-report-first-day-blue-oval-sk-facility-stanton | AC19: Planned 2025 SOP | AD19: BlueOval SK shapes America's mobility future, pivotal in EV adoption. Its high-efficiency lithium-ion batteries offer convenient transport—charging faster and traveling farther, driving an endurable tomorrow. | AE19: https://www.blueovalsk.com/ | AF19: =IF(LEN(TRIM(AD19))=0,0,LEN(TRIM(AD19))-LEN(SUBSTITUTE(AD19," ",""))+1) -> 24
A20: 4016 | B20: Under construction | C20: Midstream | D20: BlueOvalSK (JV of Ford and SK On) | E20: No | F20: BlueOvalSK Glendale Plant | G20: Other/ unknown cells | H20: Other/ Unknown | I20: https://blueovalsk.com/ | J20: 2022 Battery Park Dr | K20: Glendale | L20: KY | M20: US | N20: 42740 | P20: 37.6 | Q20: -85.9 | R20: 5000 (Planned) | S20: 20 | T20: GWh/yr | U20: S K Innovation | V20: https://www.skinnovation.com/ | W20: Jongno-gu | X20: Seoul | Y20: S Korea | Z20: VP MK | AA20: 6/19/2023 8/14/2025 | AB20: https://www.kentucky.com/news/state/kentucky/article254556442.html; BNEF Interactive Data Set Cell Manufacturing; https://www.charged-the-book.com/na-ev-supply-chain-map; https://www.wdrb.com/in-depth/inside-blueoval-sk-a-1st-look-at-kentucky-s-ev-battery-powerhouse/article_6345687f-0700-48c7-8036-b08769e43539.html | AC20: Commissioning expected in by EOY 2025; Construction started in 2022; Phase 1 will be 20 GWh, Phase 2 an additional 66 GWh by 203x. | AD20: BlueOvalSK shapes America's mobility future, pivotal in EV adoption. Its high-efficiency lithium-ion batteries offer convenient transport—charging faster and traveling farther, driving an endurable tomorrow. | AE20: https://www.blueovalsk.com/ | AF20: =IF(LEN(TRIM(AD20))=0,0,LEN(TRIM(AD20))-LEN(SUBSTITUTE(AD20," ",""))+1) -> 23
A21: 4017 | B21: Cancelled | C21: Midstream | D21: Britishvolt | E21: No | F21: Britishvolt | G21: Other/ Unknown cells | H21: Other/ Unknown | I21: https://www.britishvolt.com/ | J21: 3900 Montréal | K21: Quebec | L21: QC | M21: Canada | N21: H3B 4M7 | O21: 781-610-860 | P21: 45.62 | Q21: -73.5 | S21: 60 | T21: GWh/Yr | U21: Britishvolt | V21: https://www.britishvolt.com/ | W21: Blyth | X21: Northumberland | Y21: UK | Z21: KK MK | AA21: 8/4/2022 8/14/2025 | AB21: https://www.spglobal.com/commodityinsights/en/market-insights/latest-news/energy-transition/100821-britishvolt-plans-60-gwh-canadian-gigafactory-in-quebec; BNEF Interactive Dataset Cell Manufacturing; https://www.theguardian.com/business/2022/nov/27/britishvolt-scraps-plan-for-second-factory-in-canada | AD21: Britishvolt specializes in developing and manufacturing lithium-ion batteries for electric vehicles, focusing on innovation and large-scale production. | AE21: https://www.britishvolt.com/, https://www.rechargeindustries.com/ | AF21: =IF(LEN(TRIM(AD21))=0,0,LEN(TRIM(AD21))-LEN(SUBSTITUTE(AD21," ",""))+1) -> 17
A22: 4018 | B22: Under construction | C22: Midstream | D22: Camel Group | E22: No | F22: Camel Energy Manufacturing (Michigan) | G22: Cell Manufacturing | H22: Flooded and AGM Batteries | I22: https://www.camelbatt.com/ | J22: 4600 W. Dickman Rd | K22: Battle Creek | L22: MI | M22: US | N22: 49037 | O22: 734-929-4396 | P22: 42.335762 | Q22: -85.269506 | R22: 35 | S22: 0.1 | T22: GWh/yr | U22: Camel Group Co., Ltd. | V22: camelbatt.com | W22: Wuhan | X22: Hubei | Y22: China | Z22: VP MK | AA22: 6/11/2023 8/14/2025 | AB22: BNEF Cell Database; https://www.camelbatt.com/news/details/58.html; camelenergyus.com; https://www.batteriesinternational.com/2023/07/27/camel-launches-pilot-production-at-michigan-plant/ | AD22: The Camel Group's main focus includes automobile low-voltage batteries and energy storage. | AE22: https://www.camelbatt.com/, https://www.camelbatt.com/about.html | AF22: =IF(LEN(TRIM(AD22))=0,0,LEN(TRIM(AD22))-LEN(SUBSTITUTE(AD22," ",""))+1) -> 11
A23: 4019 | B23: Commercial | C23: Midstream | D23: Clarios | E23: Yes | F23: Clarios Meadowbrook Battery Manufacturing Plant | G23: Prismatic metal can cells | H23: Lithium nickel cobalt aluminum oxide | I23: https://clairos.com/ | J23: 70 W 48th St | K23: Holland | L23: MI | M23: US | N23: 49423 | O23: 616-494-4420 | P23: 42.752875 | Q23: -86.108588 | R23: 85 | S23: 1646 | T23: MWh/yr | U23: Clarios, Inc. | V23: https://clairos.com/ | W23: Milwaukee | X23: WI | Y23: US | Z23: VP | AA23: 45088 | AB23: BNEF Cell Database https://betterbuildingssolutioncenter.energy.gov/iso-50001/showcase-projects/clarios-meadowbrook-lithium-ion%E2%80%9450001-ready-facility; https://business.westcoastchamber.org/member-directory/Details/clarios-884387;https://wwmt.com/news/local/battery-clairos-manufacturing-plant-holland-michigan-meadowbrook-recycling-environmental-efforts-electric-cars; BNEF Interactive Dataset cell manufacturing | AC23: Purchased by Clarios | AD23: Clarios develops advanced batteries for evolving transportation needs. It transforms insightful ideas into impactful realities, anticipating and delivering solutions with agility and flexibility. | AE23: https://www.clarios.com/, https://www.clarios.com/company/company-overview, https://www.clarios.com/company/mission-values | AF23: =IF(LEN(TRIM(AD23))=0,0,LEN(TRIM(AD23))-LEN(SUBSTITUTE(AD23," ",""))+1) -> 23
A24: 4020 | B24: Cancelled | C24: Midstream | D24: Contemporary Amperex Technology (CATL) Co Ltd | E24: Yes | F24: CATL Chihuahua Ciudad Juarez Battery Manufacturing Plant | G24: Other/ unknown cells | H24: Other/ Unknown | I24: https://www.catlbttery.com | K24: Chihuahua | L24: Ciudad Juarez | M24: Mexico | P24: 31.694694 | Q24: -106.42904 | S24: 80 | T24: GWh/yr | U24: Contemporary Amperex Technology (CATL) | V24: https://www.catlbattery.com | W24: Ningde | X24: Fujian | Y24: China | Z24: VP MK | AA24: 6/10/2023 8/14/2025 | AB24: https://mexico-now.com/catl-seeks-to-install-battery-plant-in-mexico/; BNEF Cell Database; https://cnevpost.com/2024/03/29/catl-plans-plant-with-gm-north-america-tech-licensing-report/ | AC24: Could be located in Saltillo, Coahuila; $5 billion investment; expected in 2024 | AD24: CATL is a global leader of new energy innovative technologies, committed to providing premier solutions and services for new energy applications worldwide. | AE24: https://www.catlbattery.com, https://www.catl.com/en/about/profile/, https://www.catl.com/en/about/strategy/ | AF24: =IF(LEN(TRIM(AD24))=0,0,LEN(TRIM(AD24))-LEN(SUBSTITUTE(AD24," ",""))+1) -> 22
A25: 4107 | B25: Commercial | C25: Midstream | D25: Dragonfly Energy Holdings Corp | E25: No | F25: Dragonfly Energy Manufacturing Facility | G25: Cylindrical cells | H25: LFP | I25: https://dragonflyenergy.com/ | J25: 1190 Trademark Dr Ste 108 | K25: Reno | L25: NV | M25: US | N25: 89521 | O25: 775-622-3448 | P25: 39.4916 | Q25: 119.7212 | S25: 0.15 | T25: GWh/yr | U25: Dragonfly Energy Holdings Corp | V25: https://dragonflyenergy.com/ | W25: Reno | X25: NV | Y25: US | Z25: MK | AA25: 45900 | AB25: https://dragonflyenergy.com/company/battery-factory/; https://dragonflyenergy.com/dragonfly-energy-completes-u-s-lithium-battery-cell-pilot-line-begins-manufacturing-anode-at-scale-using-patented-dry-deposition-processes/; https://web.vegaschamber.com/directory/results/map.aspx?listingid=44077 | AD25: Dragonfly Energy, based in Reno, manufactures lithium-ion batteries using a patented dry electrode process, supporting U.S. supply chains with Battle Born Batteries® for RV, marine, and off-grid applications. | AF25: =IF(LEN(TRIM(AD25))=0,0,LEN(TRIM(AD25))-LEN(SUBSTITUTE(AD25," ",""))+1) -> 28
A26: 4103 | B26: Planned | C26: Midstream | D26: Durapower Tech Private Limited | E26: No | F26: Durapower Tech Private Limited | G26: Cell | H26: Packs | I26: https://durapowergroup.com/ | J26: TBD | K26: TBD | L26: TBD | M26: US | U26: Durapower Group | V26: https://durapowergroup.com/ | W26: Singapore | Y26: Singapore | Z26: MK | AA26: 45867 | AB26: https://durapowergroup.com/durapower-plans-for-u-s-manufacturing-presence-as-part-of-global-expansion/, https://chargedevs.com/newswire/singapores-durapower-plans-us-battery-manufacturing-as-part-of-global-expansion/ | AC26: Durapower is actively seeking joint venture partners for a U.S. manufacturing facility. The company's current North American presence is a sales office in Morgan Hill, CA | AD26: Durapower is a leading global provider of high-performance, end-to-end energy storage solutions, specializing in lithium-ion battery technology for automotive, marine, and stationary applications. | AF26: =IF(LEN(TRIM(AD26))=0,0,LEN(TRIM(AD26))-LEN(SUBSTITUTE(AD26," ",""))+1) -> 23
A27: 4116 | B27: Planned | C27: Midstream | D27: e-Storage | E27: No | F27: Shelbyville Battery Manufacturing Facility | G27: Battery Development | H27: LFP batteries for utility-scale energy storage | I27: https://csestorage.com | J27: Finchville Industrial Park | K27: Shelbyville | L27: KY | M27: US | N27: 40065 | P27: 38.1678 | Q27: 85.1856 | R27: 700 | S27: 6 | T27: GWh/Yr | U27: Canadian Solar | V27: https://www.canadiansolar.com | W27: Kitchener | X27: ON | Y27: Canada | Z27: MK | AA27: 45918 | AB27: https://www.kentuckyliving.com/energy/shelbyville-battery-manufacturing-to-produce-utility-scale-batteries; https://www.courier-journal.com/story/money/companies/2024/11/15/canadian-solar-700-million-battery-plant-shelbyville-ky-jobs/76133727007/ | AD27: e-Storage, a subsidiary of Canadian Solar, is building a utility-scale battery facility in Kentucky through its local entity, Shelbyville Battery Manufacturing, focusing on integrated LFP battery production and R&D. | AF27: =IF(LEN(TRIM(AD27))=0,0,LEN(TRIM(AD27))-LEN(SUBSTITUTE(AD27," ",""))+1) -> 29
A28: 4021 | B28: Commercial | C28: Midstream | D28: EaglePicher Technologies, LLC | E28: Yes | F28: Aerospace Business Unit an Lithium Ion Center of Excellence | G28: Cylindrical and Prismatic Can cells | H28: Nickel manganese cobalt | I28: https://www.eaglepicher.com/ | J28: 8230 E. 23rd St | K28: Joplin | L28: MO | M28: US | N28: 64804 | O28: 417-624-3167 | P28: 37.064363 | Q28: -94.40086 | R28: 750 | U28: Eaglepicher Technologies | V28: https://www.eaglepicher.com/ | W28: St. Louis | X28: MO | Y28: US | Z28: VP | AA28: 44415 | AB28: eaglepicher.com | AC28: Also does R&D and makes a charger/analyzer; Makes several types of batteries, including Li-ion for specialized mission-critical applications: aerospace, military and medical. This facility focuses on batteries for aerospace devices; facility is 100,000 sq ft; >9 00 employees across all locations | AD28: EaglePicher Technologies specializes in designing and manufacturing advanced lithium-ion batteries for various applications, including defense, aerospace, and medical devices, ensuring high-performance and reliability. | AE28: https://www.eaglepicher.com/ | AF28: =IF(LEN(TRIM(AD28))=0,0,LEN(TRIM(AD28))-LEN(SUBSTITUTE(AD28," ",""))+1) -> 23
A29: 4022 | B29: Commercial | C29: Midstream | D29: EaglePicher Technologies, LLC | E29: Yes | F29: Defense Strategic Business Unit | G29: Cylindrical and Prismatic Can cells | H29: Nickel cobalt aluminum oxide | I29: https://www.eaglepicher.com/ | J29: C & Porter Streets | K29: Joplin | L29: MO | M29: US | N29: 64801 | O29: 417-623-8000 | P29: 37.094787 | Q29: -94.528397 | S29: 0.2 | T29: GWh/yr | U29: Eaglepicher Technologies | V29: https://www.eaglepicher.com/ | W29: St. Louis | X29: MO | Y29: US | Z29: VP MK | AA29: 8/7/2021 8/14/2025 | AB29: eaglepicher.com; https://ded.mo.gov/press-room/eaglepicher-technologies-expand-joplin-investing-209-million-and-creating-100-new-jobs | AC29: Also does R&D and makes a charger/analyzer; Makes several types of batteries, including Li-ion for specialized mission-critical applications: aerospace, military and medical. This facility focuses on batteries for aerospace devices; > 900 employees across all locations | AD29: EaglePicher Technologies specializes in designing and manufacturing advanced lithium-ion batteries for various applications, including defense, aerospace, and medical devices, ensuring high-performance and reliability. | AE29: https://www.eaglepicher.com/ | AF29: =IF(LEN(TRIM(AD29))=0,0,LEN(TRIM(AD29))-LEN(SUBSTITUTE(AD29," ",""))+1) -> 23
A30: 4023 | B30: Commercial | C30: Midstream | D30: EaglePicher Technologies, LLC | E30: Yes | F30: Medical Power Production | G30: Pouch and cylindrical Can cells | H30: Lithium cobalt oxide | I30: https://www.eaglepicher.com/ | J30: 13136 82A Avenue | K30: Surrey | L30: BC | M30: Canada | N30: V3W 9Y6 | O30: 604-543-4350 | P30: 49.151971 | Q30: -122.85931 | U30: Eaglepicher Technologies | V30: https://www.eaglepicher.com/ | W30: St. Louis | X30: MO | Y30: US | Z30: VP | AA30: 44415 | AB30: eaglepicher.com;https://growjo.com/company/EaglePicher_Technologies | AC30: Also does R&D and makes a charger/analyzer; Makes several types of batteries, including Li-ion for specialized mission-critical applications: aerospace, military and medical. This facility focuses on batteries for medical devices; facility is 61,000 sq ft; > 900 employees across all locations | AD30: EaglePicher Technologies specializes in designing and manufacturing advanced lithium-ion batteries for various applications, including defense, aerospace, and medical devices, ensuring high-performance and reliability. | AE30: https://www.eaglepicher.com/ | AF30: =IF(LEN(TRIM(AD30))=0,0,LEN(TRIM(AD30))-LEN(SUBSTITUTE(AD30," ",""))+1) -> 23
A31: 4024 | B31: Cancelled | C31: Midstream | D31: EC Power | E31: No | F31: EC Power | G31: Pouch and Prismatic Can cells | H31: Nickel manganese cobalt | I31: https://ecpowergroup.com/ | J31: 341 Science Park Rd | K31: State College | L31: PA | M31: US | N31: 16803 | O31: 814-861-6233 | P31: 40.778986 | Q31: -77.895136 | R31: 12 | S31: 0.001 | T31: GWh/yr | U31: EC Power | V31: https://ecpowergroup.com/ | W31: State College | X31: PA | Y31: US | Z31: VP MK | AA31: 11/23/2022 8/14/2025 | AB31: ecpowergroup.com; Questionnairep; https://www.centredaily.com/news/local/community/philipsburg/article288998659.html | AC31: Develops new solid-state batteries, especially those applicable to different environments; has a heat from within technology for their cells, TMCT ™ , which allows faster charging. Also prototypes cells for clients with new technologies; Workforce range 8-15 | AD31: EC Power innovates with 30x technology and rapid thermal control. Focused on cooperation, science, and fairness, it unites to deliver faster, reliable lithium-ion batteries globally. | AE31: https://www.ecpowergroup.com/, https://www.ecpowergroup.com/story | AF31: =IF(LEN(TRIM(AD31))=0,0,LEN(TRIM(AD31))-LEN(SUBSTITUTE(AD31," ",""))+1) -> 24
A32: 4025 | B32: Commercial | C32: Midstream | D32: Electrovaya | E32: No | F32: Mississauga | G32: Prismatic metal can cells | H32: Nickel manganese cobalt | I32: https://electrovaya.com/ | J32: 6688 Kitimat Rd | K32: Mississauga | L32: ON | M32: Canada | N32: L5N 1P8 | O32: 905-855-4610 | P32: 43.603811 | Q32: -79.737918 | R32: 65 | S32: 0.5 | T32: GWh/yr | U32: Electrovaya | V32: https://electrovaya.com/ | W32: Mississauga | X32: ON | Y32: Canada | Z32: VP MK | AA32: 8/4/2022 8/14/2025 | AB32: electrovaya.com; Propulsion Quebec; https://growjo.com/company/Electrovaya; https://www.zoominfo.com/c/electrovaya-inc/39932216; https://electrovaya.com/press/electrovaya-plans-transformational-acquisition/ | AC32: Focuses primarily on mission critical applications like forklifts. Uses ceramic separators; Employee range: 50-80 | AD32: Pioneering the energy transformation with safe, durable lithium-ion batteries, Electrovaya's mission is to accelerate the energy transition with advanced technology for safer and better batteries. | AE32: https://electrovaya.com/, https://electrovaya.com/company/#About-Us | AF32: =IF(LEN(TRIM(AD32))=0,0,LEN(TRIM(AD32))-LEN(SUBSTITUTE(AD32," ",""))+1) -> 25
A33: 4026 | B33: Commercial | C33: Midstream | D33: Electrovaya | E33: No | F33: Jamestown | G33: Prismatic metal can cells | H33: Nickel cobalt aluminum oxide | I33: https://electrovaya.com/ | K33: Jamestown | L33: NY | M33: US | P33: 42.101382 | Q33: -79.241098 | R33: 250 (Planned) | S33: 0.5 | T33: GWh/yr | U33: Electrovaya | V33: https://electrovaya.com/ | W33: Mississauga | X33: ON | Y33: Canada | Z33: VP MK | AA33: 6/11/2023 8/14/2025 | AB33: BNEF Cell database; https://electrovaya.com/press/electrovaya-to-establish-lithium-ion-gigafactory-in-new-york-state/; https://chargedevs.com/newswire/electrovaya-starts-battery-system-manufacturing-in-new-york/ | AC33: Exact location not known. Center of Jamestown used. Plans to reach 1 GWh. | AD33: Pioneering the energy transformation with safe, durable lithium-ion batteries, Electrovaya's mission is to accelerate the energy transition with advanced technology for safer and better batteries. | AE33: https://electrovaya.com/, https://electrovaya.com/company/#About-Us | AF33: =IF(LEN(TRIM(AD33))=0,0,LEN(TRIM(AD33))-LEN(SUBSTITUTE(AD33," ",""))+1) -> 25
A34: 4108 | B34: Planned | C34: Midstream | D34: ElevenEs | E34: No | F34: ElevenEs Gigafactory III | G34: Prismatic cells | H34: LFP | I34: https://elevenes.com/ | J34: TBD | K34: TBD | L34: TBD | M34: US | S34: 20 | T34: GWh/yr | U34: ElevenEs | V34: https://elevenes.com/ | W34: Subotica | Y34: Serbia | Z34: MK | AA34: 45900 | AB34: https://elevenes.com/about-us/, https://en.whchem.com/cmscontent/837.html | AC34: Projected SOP of 2031 | AD34: ElevenEs is a Serbian company specializing in the development and manufacturing of lithium-iron-phosphate (LFP) batteries. The company has a focus on prismatic LFP cells and has established an R&D center and production facility in Subotica, Serbia. | AF34: =IF(LEN(TRIM(AD34))=0,0,LEN(TRIM(AD34))-LEN(SUBSTITUTE(AD34," ",""))+1) -> 36
A35: 4027 | B35: Commercial | C35: Midstream | D35: EnerSys | E35: Yes | F35: Quallion LLC | G35: Prismatic metal can cells | H35: Nickel manganese cobalt | I35: https://www.enersys.com/en/ | J35: 12744 San Fernando Rd | K35: Sylmar | L35: CA | M35: US | N35: 91342 | O35: 732-543-7900 | P35: 34.302284 | Q35: -118.46136 | U35: Enersys | V35: https://www.enersys.com/en/ | W35: Reading | X35: PA | Y35: US | Z35: VP MK | AA35: 8/21/2021 8/14/2025 | AB35: enersys.com; Questionnaire; https://powersourcesconference.com/PowerSources23/docs/18-5.pdf? | AC35: Pilot facility | AD35: EnerSys provides energy storage systems and technology for industrial applications, manufacturing and distributing reserve and motive power batteries, chargers, power equipment, and accessories for telecommunications, utilities, medical, aerospace, and defense. | AE35: https://www.enersys.com/en/ | AF35: =IF(LEN(TRIM(AD35))=0,0,LEN(TRIM(AD35))-LEN(SUBSTITUTE(AD35," ",""))+1) -> 30
A36: 4028 | B36: Planned | C36: Midstream | D36: EnerSys | E36: Yes | F36: EnerSys Advanced Systems | G36: Cylindrical and prismatic can cells | H36: Nickel cobalt manganese oxide | I36: https://www.enersys.com/en/ | K36: Greenville | L36: SC | M36: US | P36: 34.7025 | Q36: -82.4568 | U36: Enersys | V36: https://www.enersys.com/en/ | W36: Reading | X36: PA | Y36: US | Z36: BM AP (moved it to cell manufacturing) MK | AA36: 9/25/2024 9/25/2024 8/14/2025 | AB36: https://www.defenseandmunitions.com/news/ener-sys-selected-to-develop-lithium-ion-cell-gigafactory/ | AD36: EnerSys Advanced Systems will produce high-performance prismatic and cylindrical cells, offering cost-competitive domestic capabilities for industrial and defense markets crucial to U.S. economic growth. | AE36: https://www.energy.gov/mesc/bipartisan-infrastructure-law-battery-materials-processing-and-battery-manufacturing-recycling | AF36: =IF(LEN(TRIM(AD36))=0,0,LEN(TRIM(AD36))-LEN(SUBSTITUTE(AD36," ",""))+1) -> 24
A37: 4029 | B37: Commercial | C37: Midstream | D37: EnerSys | E37: Yes | F37: EnerSys Advanced Systems | G37: Cylindrical and prismatic can cells | H37: Nickel cobalt manganese oxide | I37: https://www.enersys.com/en/ | J37: 104 Rock Rd | K37: Horsham | L37: PA | M37: US | N37: 19044 | O37: 215-674-3800 | P37: 40.1873 | Q37: -75.1432 | S37: 0.07 | T37: GWh/yr | U37: Enersys | V37: https://www.enersys.com/en/ | W37: Reading | X37: PA | Y37: US | Z37: MK | AA37: 45883 | AB37: https://investor.enersys.com/news/news-details/2025/EnerSys-Announces-Workforce-Reduction-as-Part-of-Strategic-Organizational-Realignment-to-Support-Future-Growth/default.aspx | AD37: EnerSys provides energy storage systems and technology for industrial applications, manufacturing and distributing reserve and motive power batteries, chargers, power equipment, and accessories for telecommunications, utilities, medical, aerospace, and defense. | AF37: =IF(LEN(TRIM(AD37))=0,0,LEN(TRIM(AD37))-LEN(SUBSTITUTE(AD37," ",""))+1) -> 30
A38: 4030 | B38: Pre-commercial/ startup | C38: Midstream | D38: Enovix | E38: Yes | F38: Enovix Fremont | G38: Prismatic pouch cells | H38: Lithium cobalt oxide, Nickel manganese cobalt | I38: https://www.enovix.com/ | J38: 3501 W Warren Ave | K38: Fremont | L38: CA | M38: US | N38: 94538 | O38: 510-695-2350 | P38: 37.482105 | Q38: -121.94432 | R38: 215 | S38: 0.2 | T38: GWh/yr | U38: Enovix | V38: https://www.enovix.com/ | W38: Fremont | X38: CA | Y38: US | Z38: VP MK | AA38: 11/25/2022 8/27/2025 | AB38: enovix.com; https://ir.enovix.com/static-files/26fdf917-b25f-461f-862a-3e9349934d9d; https://www.zippia.com/enovix-careers-1404878/; Questionnaire; https://www.buzzfile.com/business/Enovix-Corporation-510-695-2399; Pitchbook.com; https://www.zoominfo.com/c/enovix-incorporated/346492803 | AC38: Develop batteries using silicon anodes, focusing on compact wearable, portable designs followed by 3D design for EV and stationary sources; Plan to commercialize by Q2 2022; Won contract to demo advanced LiBs for US Army; 50,000 sq ft/ 280 MWh battery pre-production facility; Jumping to 0.4 Gwh with expansion by 2030 | AD38: Enovix's breakthrough cell architecture is unlocking the full potential of next-gen devices with 100% active silicon anode. | AE38: https://www.enovix.com/, https://www.enovix.com/applications/, https://www.linkedin.com/company/enovix-corp-/ | AF38: =IF(LEN(TRIM(AD38))=0,0,LEN(TRIM(AD38))-LEN(SUBSTITUTE(AD38," ",""))+1) -> 17
A39: 4031 | B39: Commercial | C39: Midstream | D39: Enpower Greentech | E39: Yes | F39: Enpower Greentech | G39: Cell Manufacturing and Assembly | H39: Lithium iron phosphate | I39: https://www.enpower-greentech.com/#top | J39: 600 S Wagner Rd. | K39: Ann Arbor | L39: MI | M39: US | N39: 48103 | P39: 42.277438 | Q39: -83.800585 | R39: 127 | U39: Enpower Greentech | V39: https://www.enpower-greentech.com | W39: San Jose | X39: CA | Y39: US | Z39: AP MK | AA39: 8/25/2024 8/14/2025 | AB39: https://pitchbook.com/profiles/company/439547-50#:~:text=Enpower%20Greentech%20General%20Information&text=Developer%20of%20energy%20storage%20battery,energy%20and%20smart%20power%20applications; https://enpower-greentech.com/news/in-the-press-contrasting-semi-solid-lithium-ion-and-lithium-polymer-batteries-mrxfm | AC39: semi-solid-state lithium-ion pouch cells | AD39: Enpower Greentech is a developer of energy storage battery technologies and services designed for renewable energy and smart power applications with focus on cell manufacturing, such as LFP. | AF39: =IF(LEN(TRIM(AD39))=0,0,LEN(TRIM(AD39))-LEN(SUBSTITUTE(AD39," ",""))+1) -> 28
A40: 4032 | B40: Pre-commercial/ startup | C40: Midstream | D40: Enpower Greentech | E40: No | F40: EnPower, Inc. | G40: Prismatic pouch and canned cells | H40: Nickel manganese cobalt | I40: https://www.enpowerinc.com/ | J40: 8740 Hague Rd, Building 7 | K40: Indianapolis | L40: IN | M40: US | N40: 46256 | O40: 317-703-1800 | P40: 39.916858 | Q40: -86.034603 | R40: 49 | S40: 0.8 | T40: GWh/yr | U40: EnPower | V40: https://www.enpowerinc.com/ | W40: Indianapolis | X40: IN | Y40: US | Z40: VP MK | AA40: 11/25/2022 8/14/2025 8/27/2025 | AB40: BNEF: Interactive Datasets/Storage/Cell manufacturers; ;https://www.enpowerinc.com/us-lithium-ion-battery-manufacturing-facility/; https://www.zoominfo.com/pic/enerdel-inc/34770801; https://www.insideindianabusiness.com/articles/lithium-ion-battery-maker-relocating-to-indianapolis; https://www.enpowerinc.com/us-lithium-ion-battery-manufacturing-facility/; https://www.ibj.com/articles/battery-maker-relocating-to-indianapolis-planning-more-than-100-jobs; https://www.enpowerinc.com/enpower-opens-americas-newest-gigawatt-factory/; https://www.youarecurrent.com/2022/10/25/enpower-opens-gigawatt-facility/; https://my.pitchbook.com/profile/118857-34/company/profile#general-info | AC40: Acquired EnerDel's manufacturing facility and dedicated the 800 MWh facility on 10/5/2022; It hopes to start production in 2023 and increase the production capacity to > 1 GWh | AD40: EnPower is a lithium-ion battery company engaged in advanced battery manufacturing using its patented multilayer electrodes, which address the trade-off between energy and power, enabling fast charging, | AE40: https://www.enpowerinc.com/ | AF40: =IF(LEN(TRIM(AD40))=0,0,LEN(TRIM(AD40))-LEN(SUBSTITUTE(AD40," ",""))+1) -> 26 | AG40: Andrew Rossier | AH40: andrew.rossier@enpowerinc.com | AI40: 1 586-524-8892
A41: 4109 | B41: Planned | C41: Midstream | D41: Factorial Energy | E41: No | F41: Factorial Energy | G41: Battery Development | H41: Solid-state battery | I41: https://factorialenergy.com/ | K41: Methuen | L41: MA | M41: US | O41: 617-315-9733 | P41: 42.7293 | Q41: 71.1856 | R41: 150 | S41: 200 | T41: MWh/yr | U41: Factorial Energy | V41: https://factorialenergy.com/ | W41: Billerica | X41: MA | Y41: US | Z41: MK | AA41: 45902 | AB41: https://www.businesswire.com/news/home/20231023929129/en/Factorial-Energy-Opens-New-Manufacturing-Facility-to-House-Largest-Solid-State-Battery-Line-in-the-US; https://cleantechnica.com/2023/10/24/factorial-energy-opens-largest-solid-state-battery-factory-in-america/; https://factorialenergy.com/contact-us/ | AC41: Projected SOP of 2026 | AD41: Factorial Energy is a U.S.-based company developing and manufacturing solid-state battery technology for electric vehicles. The company is focused on its proprietary FEST® (Factorial Electrolyte System Technology) platform. | AF41: =IF(LEN(TRIM(AD41))=0,0,LEN(TRIM(AD41))-LEN(SUBSTITUTE(AD41," ",""))+1) -> 28
A42: 4033 | B42: Planned | C42: Midstream | D42: Five Stone Energy | E42: No | F42: Five Stone Energy | G42: Prismatic, pouch and cylindrical cells | H42: Nickel manganese cobalt, Lithium iron phosphate | I42: https://www.fivestonegreen.com/ | J42: 11220 Waples Mill Road | K42: Fairfax | L42: VA | M42: US | N42: 22030 | O42: 917-528-3159 | P42: 38.856534 | Q42: -77.336159 | U42: Five Stone Energy | V42: https://www.fivestonegreen.com/ | W42: Fairfax | X42: VA | Y42: US | Z42: SD | AA42: 45412 | AB42: Questionnaire | AD42: Five Stone Energy produces lithium iron phosphate and nickel manganese cobalt battery cells for energy storage systems and electric vehicles without toxic chemicals. It plans to build a battery manufacturing facility. | AF42: =IF(LEN(TRIM(AD42))=0,0,LEN(TRIM(AD42))-LEN(SUBSTITUTE(AD42," ",""))+1) -> 31 | AG42: Jian Ham | AH42: jham@fivestonegreen.com | AI42: 917-528-3159
A43: 4034 | B43: Planned | C43: Midstream | D43: Ford Motor Company | E43: Yes | F43: BlueOval Battery Park Michigan | G43: Prismatic cells | H43: Lithium iron phosphate | I43: https://corporate.ford.com/ | K43: Marshall | L43: MI | M43: US | P43: 42.280462 | Q43: -84.959888 | R43: 1700 (Planned) | S43: 20 | T43: GWh/yr | U43: Ford Motor Company | V43: https://corporate.ford.com/ | W43: Detroit | X43: MI | Y43: US | Z43: VP MK | AA43: 12/29/2023 8/26/2025 | AB43: charged-the-book.com; https://media.ford.com/content/fordmedia/fna/us/en/news/2023/02/13/ford-taps-michigan-for-new-lfp-battery-plant--new-battery-chemis.html; https://www.freep.com/story/money/cars/ford/2023/11/21/ford-marshall-electric-vehicle-battery-plant-reduce-plans-jobs/71664207007/; https://www.reuters.com/business/autos-transportation/ford-says-michigan-ev-battery-plant-on-track-production-tax-credits-2025-07-08/ | AC43: $3.5B investment; production expected in 2026; Ford revised its investment in late 2023 by >$1 B and reducing 800 jobs and reducing capacity by 40% | AD43: Ford's BlueOval Battery Park in Michigan focuses on producing electric vehicle batteries, enhancing EV manufacturing capabilities, and advancing lithium-ion and solid-state battery technologies for transportation solutions. | AE43: https://corporate.ford.com/, https://corporate.ford.com/about/purpose.html, https://corporate.ford.com/social-impact/sustainability.html | AF43: =IF(LEN(TRIM(AD43))=0,0,LEN(TRIM(AD43))-LEN(SUBSTITUTE(AD43," ",""))+1) -> 20
A44: 4035 | B44: Commercial | C44: Midstream | D44: Forge Nano | E44: Yes | F44: Forge Nano | G44: Cylindrical cells | H44: Nickel manganese cobalt with ALD | I44: https://www.forgenano.com/ | J44: 12300 Grant St., #110 | K44: Thornton | L44: CO | M44: US | N44: 80241 | O44: 720-259-8579 | P44: 39.920425 | Q44: -104.98312 | R44: 50 | U44: Forge Nano, Inc. | V44: https://www.forgenano.com/ | W44: Thornton | X44: CO | Y44: US | Z44: VP | AA44: 44780 | AB44: Questionnaire; forgenano.com;https://www.forgenano.com/press-release-atomic-layer-deposition-enabled-battery-materials-methods-products-ip-roll/;https://www.zoominfo.com/pic/forge-nano-inc/398065114 | AD44: Forge Nano, a materials science leader, accelerates manufacturing innovation and transforms product performance with its nanocoating technology, Atomic Armor. | AF44: =IF(LEN(TRIM(AD44))=0,0,LEN(TRIM(AD44))-LEN(SUBSTITUTE(AD44," ",""))+1) -> 19
A45: 4036 | B45: Under construction | C45: Midstream | D45: Forge Nano - Forge Battery | E45: Yes | F45: North Carolina Gigafactory | G45: Cylindrical and Pouch cells | H45: Nickel manganese cobalt with ALD | I45: https://www.forgenano.com/ | K45: Morrisville | L45: NC | M45: US | N45: 27560 | P45: 35.826784 | Q45: -78.830691 | R45: 204 (Planned) | S45: 1 | T45: GWh/yr | U45: Forge Nano, Inc. | V45: https://www.forgenano.com/ | W45: Thornton | X45: CO | Y45: US | Z45: VP MK | AA45: 12/29/2023 8/27/2025 | AB45: https://rhomotion.com/forge-nano-plans-to-open-battery-cell-factory-in-north-carolina-usa#:~:text=Material%20science%20company%2C%20Forge%20Nano,capacity%20of%20one%20gigawatt%20hour; https://forgebattery.com/#data; https://forgebattery.com/2025/01/forge-battery-completes-contract-negotiation-to-secure-100m-from-u-s-department-of-energy-for-north-carolina-lithium-ion-battery-gigafactory/ | AC45: 21700 cylindrical cells; 2027 Projected SOP | AD45: Forge Nano, a materials science leader, accelerates manufacturing innovation and transforms product performance with its nanocoating technology, Atomic Armor. | AF45: =IF(LEN(TRIM(AD45))=0,0,LEN(TRIM(AD45))-LEN(SUBSTITUTE(AD45," ",""))+1) -> 19
A46: 4110 | B46: Commercial | C46: Midstream | D46: Form Energy | E46: No | F46: Form Energy | G46: Battery Development | H46: Iron-air batteries | I46: https://formenergy.com/ | J46: 1725 Main St | K46: Weirton | L46: WV | M46: US | N46: 26062 | P46: 40.4223 | Q46: 80.5895 | R46: 750 | S46: 500 | T46: MWh/yr | U46: Form Energy | V46: https://formenergy.com/ | W46: Somerville | X46: MA | Y46: US | Z46: MK | AA46: 45902 | AB46: https://formenergy.com/form-factory-1/, https://www.stantec.com/en/projects/united-states-projects/f/form-factory-1-iron-air-battery-production-facility, https://frontier-companies.com/form-energy-form-factory-1/ | AD46: Form Energy is a U.S. company developing and manufacturing large-scale, iron-air batteries. Its technology is designed for multi-day energy storage to ensure a reliable electric grid. | AF46: =IF(LEN(TRIM(AD46))=0,0,LEN(TRIM(AD46))-LEN(SUBSTITUTE(AD46," ",""))+1) -> 26
A47: 4037 | B47: Cancelled | C47: Midstream | D47: FREYR | E47: No | F47: FREYR Giga America | G47: Pouch and Cylindrical cells | H47: Nickel cobalt manganese oxide; Lithium iron phosphate | I47: https://www.freyrbattery.com/extra-pages/facilities/giga-factory-usa | J47: Bridgeport Industrial Park | L47: GA | M47: US | P47: 34.267393 | Q47: -79.760065 | R47: 720 (Planned) | S47: 34 | T47: GWh/yr | U47: FREYR | V47: https://www.freyrbattery.com/ | W47: Luxembourg | X47: Luxembourg | Y47: Belgium | Z47: VP MK | AA47: 6/11/2023 8/27/2025 | AB47: BNEF Cell database:; https://www.businesswire.com/news/home/20221111005115/en/FREYR-Battery-Announces-Plans-for-U.S.-Gigafactory-in-Georgia; https://www.freyrbattery.com/extra-pages/facilities/giga-factory-usa | AC47: $1.7B investment; could expand to $2.9B; will be focused on ESS | AD47: FREYR is building a Giga America clean battery manufacturing facility based on the next-generation SemiSolid™ Lithium-Ion Battery Technology platform developed by 24M Technologies Inc. | AE47: https://www.freyrbattery.com/about; https://www.wsbtv.com/news/local/coweta-county/norwegian-company-abandons-plans-25-billion-battery-plant-700-jobs-metro-atlanta/USFZQ6YMNRH2NHRYB5R7GTBWCU/ | AF47: =IF(LEN(TRIM(AD47))=0,0,LEN(TRIM(AD47))-LEN(SUBSTITUTE(AD47," ",""))+1) -> 23
A48: 4038 | B48: Planned | C48: Midstream | D48: General Motors (GM) - Samsung SDI JV | E48: No | F48: GM-Samsung SDI JV Indiana Battery Plant | G48: Prismatic pouch cells, cylindrical cells | H48: Other/ Unknown | I48: https://gmauthority.com/blog/gm/gm-facilities/ultium-cells-battery-plants-global/ultium-cells-usa-battery-plants/gm-new-carlisle-indiana-battery-plant/ | K48: near New Carlisle | L48: IN | M48: US | P48: 41.706711 | Q48: -86.498275 | R48: 1700 (Planned) | S48: 36 | T48: GWh/yr | U48: General Motors Samsung SDI | V48: https://www.gm.com/ | W48: Detroit Yongin | X48: MI Gyeonggi-do | Y48: US, South Korea | Z48: VP MK | AA48: 6/19/2023 8/27/2025 | AB48: Charged-the-book.com; https://techcrunch.com/2023/06/13/gm-and-partner-samsung-sdi-pick-indiana-for-3b-battery-factory/; https://techcrunch.com/2023/04/25/hyundai-gm-partner-with-korean-battery-makers-to-build-us-plants/; https://electrek.co/2023/06/13/gm-fourth-ev-battery-plant-new-partner/; https://www.inkfreenews.com/2025/06/06/new-carlisle-gm-battery-plant-ahead-of-schedule/ | AC48: $3B investment; NCA Chemistry | AD48: GM's Indiana battery facility in New Carlisle, in partnership with Samsung, will mass-produce lithium ion cells for its electric vehicle lineup, representing its fourth U.S. battery plant, currently under construction. | AE48: https://gmauthority.com/blog/gm/gm-facilities/ultium-cells-battery-plants-global/ultium-cells-usa-battery-plants/gm-new-carlisle-indiana-battery-plant/ | AF48: =IF(LEN(TRIM(AD48))=0,0,LEN(TRIM(AD48))-LEN(SUBSTITUTE(AD48," ",""))+1) -> 30
A49: 4039 | B49: Planned | C49: Midstream | D49: Gotion | E49: No | F49: Gotion Manteno Plant | G49: Cylindrical and Pouch cells | H49: Nickel cobalt manganese oxide | I49: https://www.gotion.com/ | J49: 333 S Spruce St. | K49: Manteno | L49: IL | M49: US | P49: 41.245031 | Q49: -87.866013 | R49: 2600 (Planned) | S49: 40 | T49: GWh/yr | U49: Gotion High-Tech | V49: https://www.en.gotion.com.cn/ | W49: Heifei | Y49: China | Z49: VP MK | AA49: 12/29/2023 8/27/2025 | AB49: Battery Atlas; https://abc7chicago.com/electric-vehicles-gotion-manteno-battery-plant/13755678/; https://www.illinois.gov/news/press-release.26993.html#:~:text=Once%20completed%2C%20the%20facility%20in,will%20cover%20approximately%20150%20acres. https://chicagoyimby.com/2023/09/new-ev-gigafactory-announced-near-kankakee.html#:~:text=Located%20at%20333%20S%20Spruce,battery%20maker%20Gotion%20Hight%2DTech; https://restofworld.org/2025/gotion-ev-battery-us-expansion-backlash-michigan/ | AC49: $2B investment; Projected SOP 202x; LFP Chemistry | AD49: Gotion is a rapidly expanding company focused on innovative energy solutions and next-gen battery technology such as advanced lithium-ion batteries for electric vehicles and stationary applications. | AE49: https://lgeshonda.com/ | AF49: =IF(LEN(TRIM(AD49))=0,0,LEN(TRIM(AD49))-LEN(SUBSTITUTE(AD49," ",""))+1) -> 26
A50: 4040 | B50: Planned | C50: Midstream | D50: Gotion | E50: No | F50: Gotion Mecosta County Plant | G50: Cylindrical and Pouch cells | H50: Lithium iron phosphate | I50: https://www.gotion.com/ | K50: Big Rapids | L50: MI | M50: US | P50: 43.776528 | Q50: -85.503626 | R50: 2350 (Planned) | U50: Gotion High-Tech | V50: https://www.en.gotion.com.cn/ | W50: Heifei | Y50: China | Z50: VP MK | AA50: 12/29/2023 8/27/2025 | AB50: https://www.wzzm13.com/article/news/local/gotion-battery-plant-approved-near-big-rapids/69-3dbe01e7-2544-4ed7-b013-bbb1d74155ce; Battery Atlas; https://battery-news.de/en/2025/04/08/legal-dispute-stops-construction-of-gotion-battery-plant-in-michigan/ | AC50: $2.36B investment; Projected SOP 203x as community opposition has caused delays | AD50: Gotion is a rapidly expanding company focused on innovative energy solutions and next-gen battery technology such as advanced lithium-ion batteries for electric vehicles and stationary applications. | AE50: https://www.hyundainews.com/en-us/releases/3920 | AF50: =IF(LEN(TRIM(AD50))=0,0,LEN(TRIM(AD50))-LEN(SUBSTITUTE(AD50," ",""))+1) -> 26
A51: 4041 | B51: Under construction | C51: Midstream | D51: Honda - LGES Partnership | E51: Yes | F51: Honda LGES Fayette Battery Manufacturing Plant | G51: Prismatic pouch cells | H51: Other/ Unknown | I51: https://lgeshonda.com/ | J51: Milledgeville-Jeffersonville Road | K51: Jeffersonville | L51: OH | M51: US | N51: 43128 | P51: 39.630107 | Q51: -83.565148 | R51: 2200 (Planned) | S51: 40 | T51: GWh/yr | U51: Honda LGES | V51: https://lgeshonda.com/ | W51: Tokyo Seoul | X51: Gyeonggi | Y51: Japan, South Korea | Z51: VP MK | AA51: 6/11/2023 8/27/2025 | AB51: https://insideevs.com/news/591209/rumor-honda-lges-battery-plant-ohio/; https://www.bloomberg.com/news/articles/2022-06-08/honda-lg-energy-eyeing-ohio-for-new-electric-car-battery-plant; BNEF Interactive Dataset Cell Manufacturing; lgesolhonda.com; https://www.prnewswire.com/news-releases/lg-energy-solution-and-honda-break-ground-for-new-joint-venture-ev-battery-plant-in-ohio-301758629.html | AC51: Will supply US Honda facilities; NMC Chemistry; Projected 2025 SOP | AD51: The newly announced battery plant, a joint venture between LG Energy Solution and Honda, is coming to Fayette County, Ohio. | AE51: https://lgeshonda.com/ | AF51: =IF(LEN(TRIM(AD51))=0,0,LEN(TRIM(AD51))-LEN(SUBSTITUTE(AD51," ",""))+1) -> 20
A52: 4111 | B52: Planned | C52: Midstream | D52: Honda - LGES Partnership | E52: Yes | F52: Honda Canada Inc | G52: Battery Development | H52: Cell | I52: https://www.honda.ca/ | J52: 4700 Industrial Pkwy | K52: Alliston | L52: ON | M52: Canada | N52: L9R 1N2 | P52: 44.1165 | Q52: 79.8459 | R52: 1000 | S52: 36 | T52: GWh/yr | U52: Honda | V52: https://www.honda.com/ | W52: Tokyo | Y52: Japan | Z52: MK | AA52: 45902 | AB52: https://www.electrive.com/2025/05/14/honda-puts-ev-and-battery-production-plans-for-canada-on-ice/; https://www.automotivedive.com/news/honda-postpones-ontario-canada-investment-ev-batteries-11-billion-tariffs/748149/ | AC52: Plans have been postponed and will be reevaluated in 2 years | AD52: Honda is establishing a comprehensive electric vehicle value chain in Canada. This includes a new EV assembly plant and a standalone battery manufacturing facility at its Alliston, Ontario, location. | AF52: =IF(LEN(TRIM(AD52))=0,0,LEN(TRIM(AD52))-LEN(SUBSTITUTE(AD52," ",""))+1) -> 29
A53: 4042 | B53: Under construction | C53: Midstream | D53: Hyundai-LGES JV | E53: No | F53: Hyundai LGES Bryan County Battery Plant | G53: Other/ Unknown cells | H53: Other/ Unknown | I53: https://www.hyundainews.com/en-us/releases/3920 | J53: near Hyundai Metaplant in Bryan County | K53: Savannah | L53: GA | M53: US | P53: 32.170063 | Q53: -81.455761 | R53: 400 (Planned) | S53: 30 | T53: GWh/yr | U53: Hyundai Motor Group LGES | V53: https://www.hyundaimotorgroup.com/main/mainRecommend | W53: Seoul | X53: Gyeonggi | Y53: South Korea | Z53: VP MK | AA53: 6/11/2023 8/27/2025 | AB53: charged-the-book.com; https://www.hyundaimotorgroup.com/news/CONT0000000000093783; https://apnews.com/article/georgia-cartersville-solar-electric-vehicle-battery-congress-e48856feda02a4c1462dc783c5f6a126 | AC53: Will supply batteries to 300,000 EVs per year; construction underway with SOP 2025; located adjacent to Hyundai Motor Group Metaplant America; plant will make batteries for Hyundai, Kia and GEnesis EVs made in GA. Used Metaplant location for GPS; NMC Chemistry | AD53: Hyundai Motor Group, a global enterprise with a diverse value chain, spans mobility, steel, construction, logistics, finance, IT, and service. | AE53: https://www.hyundainews.com/en-us/releases/3920 | AF53: =IF(LEN(TRIM(AD53))=0,0,LEN(TRIM(AD53))-LEN(SUBSTITUTE(AD53," ",""))+1) -> 19
A54: 4043 | B54: Under construction | C54: Midstream | D54: Hyundai-SK On | E54: No | F54: Bartow Battery Manufacturing Plant | G54: Prismatic pouch cells | H54: Other/ Unknown | I54: https://www.hyundai.com/worldwide/en/company/newsroom/detail/hyundai-motor-group-and-sk-on-to-establish-ev-battery-cell-production-joint-venture-in-us-0000000237 | J54: Bartow Centre, Highway 411 | K54: Bartow County | L54: GA | M54: US | N54: 35960 | P54: 34.266466 | Q54: -84.815594 | R54: 3500 (Planned) | S54: 35 | T54: GWh/yr | U54: Hyundai Motor Group SK On | V54: https://www.hyundaimotorgroup.com/main/mainRecommend | W54: Seoul Icheon | X54: Gyeonggi Gyeonggi | Y54: South Korea | Z54: VP MK | AA54: 6/11/2023 8/27/2025 | AB54: BNEF Cell database; https://www.utilitydive.com/news/Hyundai-SK-On-plan-5B-Georgia-EV-battery-joint-venture/648667/; https://www.prnewswire.com/news-releases/hyundai-motor-group-and-sk-on-to-build-ev-battery-facility-in-bartow-county-301698015.html; https://electrek.co/2023/04/25/hyundai-and-sk-on-finalize-5b-us-battery-factory-update/ | AC54: $5B investment; should produce enough batteries for 300,000 vehicles by the second half of 2025; NMC Chemistry | AD54: Hyundai Motor Group is a global enterprise that has created a value chain based on mobility, steel, and construction, as well as logistics, finance, IT, and service. | AE54: https://www.hyundainews.com/en-us/releases/3920 | AF54: =IF(LEN(TRIM(AD54))=0,0,LEN(TRIM(AD54))-LEN(SUBSTITUTE(AD54," ",""))+1) -> 27
A55: 4044 | B55: Cancelled | C55: Midstream | D55: IM3NY | E55: No | F55: Imperium3 Huron Battery Manufacturing Plant I | G55: Other/ Unknown cells | H55: Other/ Unknown | I55: https://im3ny.com/ | J55: Huron Campus - 1701 North St | K55: Endicott | L55: NY | M55: US | N55: 13760 | O55: 607-444-1545 | P55: 42.104972 | Q55: -76.044494 | R55: 100 | S55: 1 | T55: GWh/yr | U55: Imperium3 | V55: im3.com.au | W55: Sydney | X55: NSW | Y55: Australia | Z55: VP MK | AA55: 6/11/2023 8/27/2025 | AB55: BNEF: Interactive Datasets/Storage/Cell manufacturers; https://www.pressconnects.com/story/money/2021/04/21/endicott-ny-lithium-ion-battery-plant-begin-production-2022/7318704002/; https://www.automotivemanufacturingsolutions.com/emobility/lithium-ion-bat; https://www.pressconnects.com/story/news/local/2025/01/28/endicott-new-york-im3ny-files-for-bankruptcy/77996357007/#:~:text='Best%20and%20only%20path%20forward,hub%22%20designation%20for%20battery%20innovation | AC55: Filed for bankruptcy | AD55: iM3NY, a U.S.-based independent lithium-ion cell manufacturer, commercializes American-developed cell chemistry with a primarily North American supply chain. Production started in 2022, targeting 38 GWh/yr in the near future. | AE55: https://im3ny.com/, https://im3ny.com/about/ | AF55: =IF(LEN(TRIM(AD55))=0,0,LEN(TRIM(AD55))-LEN(SUBSTITUTE(AD55," ",""))+1) -> 28
A56: 4045 | B56: Cancelled | C56: Midstream | D56: IM3NY | E56: No | F56: Imperium3 Huron Battery Manufacturing Plant II | G56: Other/ Unknown cells | H56: Other/ Unknown | I56: https://im3ny.com/ | J56: Huron Campus - 1701 North St | K56: Endicott | L56: NY | M56: US | N56: 13760 | O56: 607-444-1545 | P56: 42.104972 | Q56: -76.044494 | R56: 1600 (Planned) | S56: 29 | T56: GWh/yr | U56: Imperium3 | V56: im3.com.au | W56: Sydney | X56: NSW | Y56: Australia | Z56: VP MK | AA56: 6/11/2023 8/27/2025 | AB56: BNEF: Interactive Datasets/Storage/Cell manufacturers; https://www.pressconnects.com/story/money/2021/04/21/endicott-ny-lithium-ion-battery-plant-begin-production-2022/7318704002/; https://www.automotivemanufacturingsolutions.com/emobility/lithium-ion-battery-gigafactory-database/41937.article; https://www.pressconnects.com/story/news/local/2025/01/28/endicott-new-york-im3ny-files-for-bankruptcy/77996357007/#:~:text='Best%20and%20only%20path%20forward,hub%22%20designation%20for%20battery%20innovation | AC56: Workers were ratioed by output. Automotive Manufacturing Solutions reported 3 GWh rising to 15 GWh; C4V and Magnis Resources, Boston Energy and Innovation involved as well; Filed for bankruptcy | AD56: iM3NY, a U.S.-based independent lithium-ion cell manufacturer, commercializes American-developed cell chemistry with a primarily North American supply chain. Production started in 2022, targeting 38 GWh/yr in the near future. | AE56: https://im3ny.com/, https://im3ny.com/about/ | AF56: =IF(LEN(TRIM(AD56))=0,0,LEN(TRIM(AD56))-LEN(SUBSTITUTE(AD56," ",""))+1) -> 28
A57: 4046 | B57: Cancelled | C57: Midstream | D57: IM3NY | E57: No | F57: Imperium3 Huron Battery Manufacturing Plant II | G57: Other/ Unknown cells | H57: Other/ Unknown | I57: https://im3ny.com/ | J57: Huron Campus - 1701 North St | K57: Endicott | L57: NY | M57: US | N57: 13760 | O57: 607-444-1545 | P57: 42.104972 | Q57: -76.044494 | R57: 800 (Planned) | S57: 8 | T57: GWh/yr | U57: Imperium3 | V57: im3.com.au | W57: Sydney | X57: NSW | Y57: Australia | Z57: VP MK | AA57: 6/11/2023 8/27/2025 | AB57: BNEF: Interactive Datasets/Storage/Cell manufacturers; https://www.pressconnects.com/story/money/2021/04/21/endicott-ny-lithium-ion-battery-plant-begin-production-2022/7318704002/; https://www.automotivemanufacturingsolutions.com/emobility/lithium-ion-battery-gigafactory-database/41937.article; https://im3ny.com/gigafactory/; https://www.pressconnects.com/story/news/local/2025/01/28/endicott-new-york-im3ny-files-for-bankruptcy/77996357007/#:~:text='Best%20and%20only%20path%20forward,hub%22%20designation%20for%20battery%20innovation | AC57: Workers were ratioed by output. Automotive Manufacturing Solutions reported 3 GWh rising to 15 GWh; C4V and Magnis Resources, Boston Energy and Innovation involved as well; Filed for bankruptcy | AD57: iM3NY, a U.S.-based independent lithium-ion cell manufacturer, commercializes American-developed cell chemistry with a primarily North American supply chain. Production started in 2022, targeting 38 GWh/yr in the near future. | AE57: https://im3ny.com/, https://im3ny.com/about/ | AF57: =IF(LEN(TRIM(AD57))=0,0,LEN(TRIM(AD57))-LEN(SUBSTITUTE(AD57," ",""))+1) -> 28
A58: 4047 | B58: Commercial | C58: Midstream | D58: Ingevity | E58: Yes | F58: Ingevity | G58: Electrode Materials | H58: Silicon-based anode materials | I58: https://www.ingevity.com/about/our-story/ | J58: 4920 O'Hear Avenue Suite 400 | K58: North Charleston | L58: SC | M58: US | N58: 29405 | P58: 32.88432 | Q58: 79.975138 | R58: 5000 | U58: Ingevity | V58: https://www.ingevity.com/about/our-story/ | W58: North Charleston | X58: SC | Y58: US | Z58: SD AP | AA58: 7/31/2024 8/25/2024 | AB58: https://www.ingevity.com/news/press-releases/ingevity-enters-battery-electric-vehicle-market-invests-60-million-in-lithium-ion-anode-materials-producer-nexeon-and-secures-future-activated-carbon-supply-relationship/ | AC58: Ingevity enters battery electric vehicle market, invests $60 million in lithium-ion anode materials producer, Nexeon, and secures future activated carbon supply relationship | AD58: Ingevity delivers solutions that purify, protect, and enhance, using innovative technologies to solve complex problems and promote sustainability. | AF58: =IF(LEN(TRIM(AD58))=0,0,LEN(TRIM(AD58))-LEN(SUBSTITUTE(AD58," ",""))+1) -> 18
A59: 4048 | B59: Pre-commercial/ startup | C59: Midstream | D59: Ion Storage Systems | E59: No | F59: Ion Storage Systems | G59: Prismatic pouch cells | H59: Prismatic (pouch) cells | I59: https://ionstoragesystems.com/ | J59: 12500 Baltimore Avenue Suite D | K59: Beltsville | L59: MD | M59: US | N59: 20705 | O59: 240-384-6020 | P59: 39.062138 | Q59: -76.887317 | R59: 70 | S59: 10 | T59: MWh/yr | U59: Ion Storage Systems | V59: https://ionstoragesystems.com/ | W59: Beltsville, MD | X59: MD | Y59: US | Z59: VP MK | AA59: 6/11/2023 8/27/2025 | AB59: ionstoragesystems.com; https://energy.umd.edu/news/story/energy-start-up-places-3rd-in-battery-competition; https://www.businesswire.com/news/home/20201110005395/en/Ion-Storage-Announces-New-State-of-the-Art-HQ-Manufacturing-Facility; Pitchbook.com; BNEF Cell Database; https://ionstoragesystems.com/ion-storage-systems-commissions-one-of-the-countrys-largest-solid-state-battery-manufacturing-facilities/ | AC59: Contract with DLA to commercialize a conformal wearable battery for soldiers. Are scaling up to do this. Battery is non-flammable; can work with any cathode; Plan to reach 500 Mwh by 2028 | AD59: ION offers a uniquely adaptable solid-state battery solution for a variety of applications including defense and aerospace, consumer electronics, electric vehicles, and grid storage. | AE59: https://ionstoragesystems.com/, https://ionstoragesystems.com/#about | AF59: =IF(LEN(TRIM(AD59))=0,0,LEN(TRIM(AD59))-LEN(SUBSTITUTE(AD59," ",""))+1) -> 24 | AG59: Ryan Naehr | AH59: naehr@ionstoragesystems.com | AI59: 6109312084
A60: 4049 | B60: Pre-commercial/ startup | C60: Midstream | D60: Ionblox | E60: No | F60: Ionblox | G60: Prismatic pouch cells | H60: Nickel manganese cobalt | I60: https://www.ionblox.com/ | J60: 3390 Gateway Blvd. | K60: Fremont | L60: CA | M60: US | N60: 94538 | O60: 510-962-3682 | P60: 37.473522 | Q60: -121.93736 | R60: 18 | U60: Ionblox | V60: https://www.ionblox.com/ | W60: Fremont | X60: CA | Y60: US | Z60: VP | AA60: 44890 | AB60: zenlabsinc.com; Questionnaire; Pitchbook.com; ionblox.com | AC60: Formerly Zenlabs Energy; the proprietary silicon-based anodes help make a battery with high energy density and a long cycle life | AD60: Ionblox transforms lithium-ion batteries using high-capacity silicon monoxide anodes. Its nano-engineered SEI layer and advanced cell architecture ensure high conductivity and extended cycle life, even with extreme fast charging. | AE60: https://www.ionblox.com/ | AF60: =IF(LEN(TRIM(AD60))=0,0,LEN(TRIM(AD60))-LEN(SUBSTITUTE(AD60," ",""))+1) -> 29
A61: 4050 | B61: Cancelled | C61: Midstream | D61: Kore Power | E61: Yes | F61: Kore Power | G61: Other/ Unknown cells | H61: Nickel manganese cobalt | I61: https://korepower.com/ | J61: SEC 85 & Baseline Rd | K61: Buckeye | L61: AZ | M61: US | N61: 85326 | O61: 208-904-1642 | P61: 33.37525 | Q61: -112.62219 | R61: 3000 (Planned) | S61: 12 | T61: GWh/yr | U61: Kore Power | V61: https://korepower.com/ | W61: Coeur d’Alene | X61: ID | Y61: US | Z61: VP MK | AA61: 8/7/2022 8/27/2025 | AB61: korepower.com; https://www.businesswire.com/news/home/20210511006073/en/KORE-Power-Names-Three-Potential-Sites-for-U.S.-Lithium-Ion-Battery-Manufacturing-Facility; https://www.automotivemanufacturingsolutions.com/emobility/lithium-ion-battery-gigafactory-database/41937.article; https://assets.website-files.com/602d520c7a0a3866755c38ae/602d520c7a0a3850e25c3b03_KORE-Power-GTM-Whitepaper.pdf;https://korepower.com/cell#:~:text=KORE%20Power%20has%202%20GWh,capacity%20based%20on%20market%20requirements; https://www.thecentersquare.com/arizona/kore-power-to-grow-in-maricopa-county-bringing-thousands-of-jobs/article_1b3ced78-f56e-11eb-a16c-ff48349baabb.html; https://korepower.com/media/kore-power-closes-on-purchase-of-koreplex-gigafactory-site-in-buckeye-arizona | AD61: Kore Power designs and manufactures high-density lithium-ion batteries and energy storage systems, primarily for utility, industrial, and mission-critical markets globally, with a focus on innovation. | AE61: https://korepower.com/, https://korepower.com/about; https://www.canarymedia.com/articles/energy-storage/kore-power-has-a-new-plan-after-canceling-1-2b-battery-plant-in-arizona | AF61: =IF(LEN(TRIM(AD61))=0,0,LEN(TRIM(AD61))-LEN(SUBSTITUTE(AD61," ",""))+1) -> 25
A62: 4090 | B62: Under construction | C62: Midstream | D62: LG Energy Solution | E62: No | F62: Lansing Battery Manufacturing Plant | G62: Prismatic pouch cells | H62: Nickel manganese cobalt | I62: https://lgenergymi.com/ | J62: Lansing | K62: Lansing | L62: MI | M62: US | N62: 48864 | O62: 517-267-044 | P62: 42.727766 | Q62: -84.55 | R62: 1700 (Planned) | S62: 50 | T62: GWh/yr | U62: LG Energy Solution | V62: https://lgenergymi.com/ | W62: Seoul | Y62: South Korea | Z62: VP MK | AA62: 6/19/2023 8/31/2025 | AB62: https://www.ultiumcell.com/our-locations/lansing-mi; https://insideevs.com/news/590979/ultium-cells-steel-building-structure-tennessee/#:~:text=The%20upcoming%20plant%20in%20Spring,very%20soon%20%2D%20in%20August%202022; BNEF Interactive Dataset Cell manufacturing; https://www.ultiumcell.com/our-locations/lansing-mi; https://www.google.com/search?q=has+construction+started+on+the+Ultium+cells+landsing+plant&rlz=1C1GCEB_enUS866US866&oq=has+construction+started+on+the+Ultium+cells+landsing+plant&aqs=chrome..69i57j0i546l5.52389221j1j15&sourceid=chrome&ie=UTF-8; https://www.greencarcongress.com/2025/05/20250509-lg.html | AC62: Scheduled to start construction in summer 2022 and opening in 202x. Will supply to GM facilities Factory ZERO, Orion Assembly as well as others; Structure was completed in March 2023 | AD62: LG Energy Solution is producing batteries for the future of transportation with cutting-edge battery cells crafted by innovation. Its committed to utilizing state-of-the-art industry methods for superior cell production. | AE62: https://www.ultiumcell.com/ | AF62: =IF(LEN(TRIM(AD62))=0,0,LEN(TRIM(AD62))-LEN(SUBSTITUTE(AD62," ",""))+1) -> 28
A63: 4051 | B63: Planned | C63: Midstream | D63: LG Energy Solution Ltd | E63: No | F63: Arizona ESS plant | G63: Prismatic pouch cells | H63: Lithium iron phosphate | I63: https://news.lgensol.com/company-news/press-releases/1613/ | J63: 22358 S. Ellsworth Road | K63: Queens Creek | L63: AZ | M63: US | N63: 85142 | O63: 480-358-3000 | P63: 33.25 | Q63: -111.63 | R63: 2000 (Planned) | S63: 17 | T63: GWh/yr | U63: LG Chem | V63: https://www.lgensol.com/en/index | W63: Seoul | X63: Gyeonggi | Y63: Republic of Korea | Z63: VP MK | AA63: 6/11/2023 8/27/2025 | AB63: https://www.azfamily.com/2022/04/12/300-acres-queen-creek-could-be-new-site-an-lg-battery-plant/; BNEF Interactive Dataset Cell manufacturers; https://www.just-auto.com/news/lges-reconsiders-ev-battery-plant-in-arizona/; https://www.azcommerce.com/news-events/news/2023/3/lg-energy-solution-to-invest-55-billion-to-build-battery-manufacturing-complex-in-queen-creek/ | AC63: Focus on ESS; Invest $2.3B; Construction halted in July 2024, though there are plans to resume | AD63: LG Energy Solution, subsidiary of the LG Chem, is a key player in the EV battery market, manufacturing and designing lithium-ion batteries for electric vehicles and energy storage systems. | AE63: https://news.lgensol.com/company-news/press-releases/1613/, https://news.lgensol.com/company-overview/fast-facts/ | AF63: =IF(LEN(TRIM(AD63))=0,0,LEN(TRIM(AD63))-LEN(SUBSTITUTE(AD63," ",""))+1) -> 29
A64: 4052 | B64: Under construction | C64: Midstream | D64: LG Energy Solution Ltd | E64: No | F64: Arizona EV plant | G64: Cylindrical cells | H64: Nickel manganese cobalt | I64: https://news.lgensol.com/company-news/press-releases/1613/ | J64: 22358 S. Ellsworth Road | K64: Queens Creek | L64: AZ | M64: US | N64: 85142 | O64: 480-358-3000 | P64: 33.25 | Q64: -111.63 | R64: 2000 (Planned) | S64: 36 | T64: GWh/yr | U64: LG Chem | V64: https://www.lgensol.com/en/index | W64: Seoul | X64: Gyeonggi | Y64: Republic of Korea | Z64: VP MK | AA64: 6/11/2023 8/27/2025 | AB64: https://www.azfamily.com/2022/04/12/300-acres-queen-creek-could-be-new-site-an-lg-battery-plant/; BNEF Interactive Dataset Cell manufacturers; https://www.just-auto.com/news/lges-reconsiders-ev-battery-plant-in-arizona/; https://www.azcommerce.com/news-events/news/2023/3/lg-energy-solution-to-invest-55-billion-to-build-battery-manufacturing-complex-in-queen-creek/ | AC64: Focus on Evs; Invest $3.2B; Projected SOP of 2026 | AD64: LG Energy Solution, subsidiary of the LG Chem, is a key player in the EV battery market, manufacturing and designing lithium-ion batteries for electric vehicles and energy storage systems. | AE64: https://news.lgensol.com/company-news/press-releases/1613/, https://news.lgensol.com/company-overview/fast-facts/ | AF64: =IF(LEN(TRIM(AD64))=0,0,LEN(TRIM(AD64))-LEN(SUBSTITUTE(AD64," ",""))+1) -> 29
A65: 4053 | B65: Commercial | C65: Midstream | D65: LG Energy Solution Ltd | E65: No | F65: LG Energy Solution Michigan Holland Battery Manufacturing Plant | G65: Prismatic pouch cells | H65: Nickel manganese cobalt | I65: https://lgenergymi.com/ | J65: 1 LG Way | K65: Holland | L65: MI | M65: US | N65: 49423 | O65: 616-494-7100 | P65: 42.755715 | Q65: -86.069522 | R65: 1495 | S65: 16.5 | T65: GWh/yr | U65: LG Energy Solution | V65: https://www.lgensol.com/kr/index | W65: Seoul | X65: Gyeonggi | Y65: Republic of Korea | Z65: VP MK | AA65: 6/11/2023 8/27/2025 | AB65: BNEF: Interactive Datasets/Storage/Cell manufacturers; https://www.forbes.com/sites/samabuelsamid/2021/03/11/lg-chem-commits-45b-to-expand-ev-battery-production-capacity-in-us-by-70-gwh/?sh=47842698a026; Questionnaire; https://www.automotivemanufacturingsolutions.com/emobility/lithium-ion-battery-gigafactory-database/41937.article; Questionnaire; https://www.michiganbusiness.org/news/2022/03/lg-energy-solution-and-michigan-leading-the-battery-evolution/; https://www.spglobal.com/commodityinsights/en/market-insights/latest-news/energy-transition/042722-lg-energy-aims-to-more-than-double-battery-capacity-to-520-gwhyear-by-2025; https://www.michigan.gov/whitmer/news/press-releases/2022/03/22/whitmer-announces-1200-new-jobs-from-lg-energy-solutions-investment#:~:text=LG%20Energy%20Solution%2C%20formerly%20known,has%201%2C495%20employees%20in%20Michigan; https://www.electrive.com/2022/03/24/lg-energy-solution-to-expand-michigan-plant/; https://insideevs.com/news/575359/lges-plant-expansion-michigan/ | AD65: LG Energy Solution, subsidiary of the LG Chem, is a key player in the EV battery market, manufacturing and designing lithium-ion batteries for electric vehicles and energy storage systems. | AE65: https://news.lgensol.com/company-news/press-releases/1613/, https://news.lgensol.com/company-overview/fast-facts/ | AF65: =IF(LEN(TRIM(AD65))=0,0,LEN(TRIM(AD65))-LEN(SUBSTITUTE(AD65," ",""))+1) -> 29
A66: 4054 | B66: Under construction | C66: Midstream | D66: LG Energy Solution Ltd | E66: No | F66: LG Energy Solution Michigan Holland Battery Manufacturing Plant | G66: Prismatic pouch cells | H66: Nickel manganese cobalt | I66: https://lgenergymi.com/ | J66: 1 LG Way | K66: Holland | L66: MI | M66: US | N66: 49423 | O66: 616-494-7100 | P66: 42.755715 | Q66: -86.069522 | R66: 1200 (Planned) | S66: 5 | T66: GWh/yr | U66: LG Energy Solution | V66: https://www.lgensol.com/kr/index | W66: Seoul | X66: Gyeonggi | Y66: Republic of Korea | Z66: VP MK | AA66: 6/11/2023 8/27/2025 | AB66: BNEF: Interactive Datasets/Storage/Cell manufacturers; https://www.forbes.com/sites/samabuelsamid/2021/03/11/lg-chem-commits-45b-to-expand-ev-battery-production-capacity-in-us-by-70-gwh/?sh=47842698a026; Questionnaire; https://www.automotivemanufacturingsolutions.com/emobility/lithium-ion-battery-gigafactory-database/41937.article; Questionnaire; https://www.michiganbusiness.org/news/2022/03/lg-energy-solution-and-michigan-leading-the-battery-evolution/; https://www.spglobal.com/commodityinsights/en/market-insights/latest-news/energy-transition/042722-lg-energy-aims-to-more-than-double-battery-capacity-to-520-gwhyear-by-2025; https://www.michigan.gov/whitmer/news/press-releases/2022/03/22/whitmer-announces-1200-new-jobs-from-lg-energy-solutions-investment#:~:text=LG%20Energy%20Solution%2C%20formerly%20known,has%201%2C495%20employees%20in%20Michigan;https://www.electrive.com/2022/03/24/lg-energy-solution-to-expand-michigan-plant/ | AC66: Quintupling size of Holland plant by 2025 | AD66: LG Energy Solution, subsidiary of the LG Chem, is a key player in the EV battery market, manufacturing and designing lithium-ion batteries for electric vehicles and energy storage systems. | AE66: https://news.lgensol.com/company-news/press-releases/1613/, https://news.lgensol.com/company-overview/fast-facts/ | AF66: =IF(LEN(TRIM(AD66))=0,0,LEN(TRIM(AD66))-LEN(SUBSTITUTE(AD66," ",""))+1) -> 29
A67: 4055 | B67: Pre-commercial/ startup | C67: Midstream | D67: LI-CAP Technologies | E67: Yes | F67: LI-CAP Technologies | G67: Electrodes | H67: Other/ Unknown | I67: https://www.licaptech.com/ | J67: 9795 Business Park Dr Unit I | K67: Sacramento | L67: CA | M67: US | N67: 95827 | O67: 916-329-8099 | P67: 38.571685 | Q67: -121.33072 | R67: 26 | U67: LICAP Technologies | V67: https://www.licaptech.com/ | W67: Sacramento | X67: CA | Y67: US | Z67: VP MK | AA67: 8/28/2022 8/27/2025 | AB67: licaptech.com; https://www.zoominfo.com/c/licap-technologies-inc/458886699; https://rocketreach.co/licap-technologies-inc-profile_b4525d66fc89e31f | AC67: LI-CAP primarily manufactures li-ion capacitors, not batteries | AD67: LI-CAP Technologies' Activated Dry Electrode® technology enables cost-effective and environmentally friendly manufacturing of lithium-ion batteries, ultracapacitors, and lithium-ion capacitors with superior performance. | AE67: https://www.licaptech.com/, https://www.licaptech.com/about | AF67: =IF(LEN(TRIM(AD67))=0,0,LEN(TRIM(AD67))-LEN(SUBSTITUTE(AD67," ",""))+1) -> 22
A68: 4056 | B68: Pre-commercial/ startup | C68: Midstream | D68: Linova Energy | E68: Yes | F68: Linova Energy | G68: Anode raw materials | H68: Metal-free cathodes | I68: https://www.linovaenergy.com/ | J68: 602 E Huntington Drive | K68: Monrovia | L68: CA | M68: US | N68: 91016 | P68: 34.1404 | Q68: -117.9921 | R68: 10 | U68: Linova Energy | V68: https://www.linovaenergy.com/ | W68: Monrovia | X68: CA | Y68: US | Z68: SD AP | AA68: 8/11/2024 8/25/2024 | AB68: https://www.linovaenergy.com/ | AD68: Linova Energy is developing ultra-high-energy batteries with polymer cathodes for EV, aerospace, and energy storage, using metal-free cathodes without nickel or cobalt for a sustainable, cost-effective power solution. | AF68: 28
A69: 4057 | B69: Cancelled | C69: Midstream | D69: LION Electric | E69: No | F69: Lion Campus - Battery Plant and Innovation Center | G69: Other/ Unknown cells | H69: Lithium iron phosphate | I69: https://thelionelectric.com/en | J69: 9900 Rie Irénée Vachon | K69: Mirabel | L69: QC | M69: Canada | N69: J7N 3C5 | O69: 450-432-5466 | P69: 45.681474 | Q69: -74.081396 | R69: 135 (Planned) | S69: 5 | T69: GWh/Yr | U69: LION Electric | V69: https://thelionelectric.com/en | W69: Quebec | X69: QC | Y69: Canada | Z69: VP MK | AA69: 6/19/2023 8/27/2025 | AB69: thelionelectric.com/documents/en/PressRelease_Lion_BatteryManufacturingPlantOpening_ENG.pdf; https://s27.q4cdn.com/902820926/files/doc_presentations/2023/May-2023-IR-Presentation-V2.pdf; https://www.shawlocal.com/daily-journal/news/local/2025/05/13/lion-electrics-venture-in-joliet-is-over-plant-on-auction-block/ | AC69: Closed, assets up for auction | AD69: LION Electric manufactures innovative zero-emission vehicles, including all-electric school buses and urban trucks. A leading OEM in North American transportation electrification, it actively seeks new technologies for user-specific features. | AE69: https://thelionelectric.com/en | AF69: =IF(LEN(TRIM(AD69))=0,0,LEN(TRIM(AD69))-LEN(SUBSTITUTE(AD69," ",""))+1) -> 29
A70: 4058 | B70: Commercial | C70: Midstream | D70: Lithion Battery, Inc. | E70: Yes | F70: Engineered Power Limited Partnership | G70: Cylindrical cells | H70: Lithium iron phosphate | I70: https://www.lithionbattery.com/ | J70: 3103 14th Ave NE, #20 | K70: Calgary | L70: AB | M70: Canada | N70: T2A 7N6 | O70: 403-235-2584 | P70: 51.064814 | Q70: -113.98954 | R70: 70 | U70: Lithion Battery Inc. | V70: https://www.lithionbattery.com/ | W70: Henderson | X70: NV | Y70: US | Z70: VP | AA70: 44801 | AB70: lithionbattery.com | AD70: Lithion Batteries, a vertically integrated manufacturer of battery cells and packs, produces custom, high-quality power solutions globally, emphasizing reliability in critical applications. | AE70: https://www.lithionbattery.com/ | AF70: =IF(LEN(TRIM(AD70))=0,0,LEN(TRIM(AD70))-LEN(SUBSTITUTE(AD70," ",""))+1) -> 22
A71: 4059 | B71: Commercial | C71: Midstream | D71: Lithion Battery, Inc. | E71: Yes | F71: Lithion Battery, Inc. | G71: Cylindrical cells | H71: Lithium iron phosphate | I71: https://www.lithionbattery.com/ | J71: 1350 Wigwam Parkway | K71: Henderson | L71: NV | M71: US | N71: 89074 | O71: 702-478-3590 | P71: 36.034692 | Q71: -115.04319 | R71: 31 | S71: 0.2 | T71: GWh/yr | U71: Lithion Battery Inc. | V71: https://www.lithionbattery.com/ | W71: Henderson | X71: NV | Y71: US | Z71: VP MK | AA71: 8/28/2022 8/27/2025 | AB71: lithionbattery.com | AC71: LFP and NMC chemistries | AD71: Lithion Batteries, a vertically integrated manufacturer of battery cells and packs, produces custom, high-quality power solutions globally, emphasizing reliability in critical applications. | AE71: https://www.lithionbattery.com/ | AF71: =IF(LEN(TRIM(AD71))=0,0,LEN(TRIM(AD71))-LEN(SUBSTITUTE(AD71," ",""))+1) -> 22
A72: 4060 | B72: Cancelled | C72: Midstream | D72: Luna Lithium Battery | E72: No | F72: Luna Lithium Hermosillo Battery Manufacturing Plant | G72: Other/ unknown cells | H72: Other/ Unknown | I72: https://www.delunalithiumbattery.com/ | K72: Ciudad Sahagún | L72: Hidalgo | M72: Mexico | O72: 52-551-377-9167 | P72: 19.764893 | Q72: -98.580269 | R72: 900 (Planned) | S72: 1 | T72: GWh/yr | U72: Luna Lithium Battery | V72: delunalithiumbattery.com | W72: Mexico City | Y72: Mexico | Z72: VP MK | AA72: 6/10/2023 8/27/2025 | AB72: delunalthiumbattery.com; BNEF Cell Database; https://mexicobusiness.news/mining/news/new-lithium-battery-plant-start-operations-soon | AD72: Luna Lithium Battery improves lives with its lithium battery technology, powering everything with energy. | AE72: delunalithiumbattery.com | AF72: =IF(LEN(TRIM(AD72))=0,0,LEN(TRIM(AD72))-LEN(SUBSTITUTE(AD72," ",""))+1) -> 14
A73: 4105 | B73: Under construction | C73: Midstream | D73: Lyten, Inc | E73: Yes | F73: San Leandro Production Facility | G73: Cell | H73: Lithium-sulfur battery cells | I73: https://lyten.com/ | J73: Gate510 Industrial Park | K73: San Leandro | L73: CA | M73: US | N73: 94557 | P73: 37.7213 | Q73: -122.1529 | S73: 100 | T73: MWh/yr | U73: Lyten, Inc | V73: https://lyten.com/ | W73: San Jose | X73: CA | Y73: US | Z73: MK | AA73: 45872 | AB73: https://www.automate.org/case-studies/transforming-battery-module-assembly-with-the-repeating-layer-process-rlp-, https://lyten.com/2024/11/13/lyten-acquires-battery-manufacturing-assets-from-cuberg-to-accelerate-us-production-of-lithium-sulfur-batteries/ | AC73: The facility and equipment were acquired from a former lithium-metal battery maker (Cuberg, a Northvolt subsidiary) in November 2024; Projected SOP 2025 | AD73: Lyten is a super-material applications company that has developed Lyten 3D Graphene™, which it uses to produce high-performance, next-generation lithium-sulfur batteries. | AF73: =IF(LEN(TRIM(AD73))=0,0,LEN(TRIM(AD73))-LEN(SUBSTITUTE(AD73," ",""))+1) -> 21
A74: 4106 | B74: Planned | C74: Midstream | D74: Lyten, Inc | E74: Yes | F74: Lyten Gigafactory | G74: Cell | H74: Lithium-sulfur battery cells | I74: https://lyten.com/ | J74: Reno Airlogistics Park | K74: Reno | L74: NV | M74: US | P74: 39.6728 | Q74: 119.851 | R74: 1000 | S74: 10 | T74: GWh/yr | U74: Lyten, Inc | V74: https://lyten.com/ | W74: San Jose | X74: CA | Y74: US | Z74: MK | AA74: 45902 | AB74: https://lyten.com/2024/10/15/lyten-announces-plans-to-build-the-worlds-first-lithium-sulfur-battery-gigafactory-in-nevada/; https://www.greencarcongress.com/2024/10/20241017-lyten.html | AC74: Projected SOP 2027 | AD74: Lyten is a super-material applications company that has developed Lyten 3D Graphene™, which it uses to produce high-performance, next-generation lithium-sulfur batteries. | AF74: =IF(LEN(TRIM(AD74))=0,0,LEN(TRIM(AD74))-LEN(SUBSTITUTE(AD74," ",""))+1) -> 21
A75: 4112 | B75: Commercial | C75: Midstream | D75: Medtronic | E75: No | F75: Medtronic Energy and Component Center (MECC) | G75: Battery Development | H75: Specialized li-ion batteries for implantable medical devices | I75: https://www.medtronic.com/ | J75: 6700 Shingle Creek Pkwy | K75: Brooklyn Center | L75: MN | M75: US | N75: 55430 | O75: 763-514-4000 | P75: 45.0592 | Q75: 93.3138 | S75: 0.03 | T75: GWh/yr | U75: Medtronic | V75: https://www.medtronic.com/ | W75: Minneapolis | X75: MN | Y75: US | Z75: MK | AA75: 45902 | AB75: https://www.energystar.gov/sites/default/files/buildings/tools/Medtronic-MECC_Proflie.pdf; https://news.medtronic.com/mecc-batteries; https://www.startribune.com/inside-the-lab-thats-the-beating-heart-of-medtronics-product-pipeline/601214189 | AD75: Medtronic is a global medical technology company. It designs, tests, and manufactures its own specialized batteries for use in critical life-sustaining medical devices like pacemakers and neurostimulators. | AF75: =IF(LEN(TRIM(AD75))=0,0,LEN(TRIM(AD75))-LEN(SUBSTITUTE(AD75," ",""))+1) -> 27
A76: 4061 | B76: Paused construction | C76: Midstream | D76: Microvast | E76: No | F76: Microvast North American Manufacturing Facility | G76: Prismatic pouch cells | H76: Nickel manganese cobalt, Lithium iron phosphate, Lithium titanium oxide | I76: https://microvast.com/ | J76: 780 International Blvd | K76: Clarksville | L76: TN | M76: US | N76: 37040 | P76: 36.587271 | Q76: -87.260911 | R76: 287 (Planned) | S76: 2 | T76: GWh/yr | U76: Microvast | V76: https://microvast.com/ | W76: Stafford | X76: TX | Y76: US | Z76: VP MK | AA76: 6/19/2023 8/27/2025 | AB76: microvast.com; https://microvast.com/microvast-governor-lee-and-commissioner-rolfe-announce-company-to-establish-manufacturing-facility-in-clarksville-tennessee/; https://www.automotivemanufacturingsolutions.com/emobility/lithium-ion-battery-gigafactory-database/41937.article; https://www.sec.gov/Archives/edgar/data/1760689/000121390021043159/ea145917ex99-1_microvasthold.htm; BNEF Interactive Database cell manufacturing; https://source.benchmarkminerals.com/article/lg-chem-tennessee-cathode-plant-could-double-north-american-production?mc_cid=c72c66f531&mc_eid=6a6017029d; https://ir.microvast.com/events-presentations/presentations; https://www.bizjournals.com/nashville/news/2025/04/14/microvast-new-cfo-air-liquide-tennessee-plant.html | AC76: Will make cells, modules, packs and separators; chemistry is unknown, but Microvast makes LTO, Nickel Manganese Cobalt and Lithium iron phosphate chemistries; Benchmark states that the facility will make Nickel Manganese Cobalt pouch cells; US expansion plans on hold, layoffs and $150M needed to open plant; Projected SOP 203x if it moves forward | AD76: Microvast controls every aspect of battery development for industry-leading energy density, safety, ultra-fast charging, and long lifespans in commercial transportation and energy storage. | AE76: https://microvast.com/, https://microvast.com/company/ | AF76: =IF(LEN(TRIM(AD76))=0,0,LEN(TRIM(AD76))-LEN(SUBSTITUTE(AD76," ",""))+1) -> 23
A77: 4113 | B77: Planned | C77: Midstream | D77: Nanoramic Laboratories | E77: No | F77: Torr Works Facility | G77: LIB Manufacturing | H77: Electrode | I77: https://nanoramic.com/ | J77: 10 Henry St | K77: Bridgeport | L77: CT | M77: US | N77: 06604 | P77: 41.1715 | Q77: 73.1865 | R77: 300 | S77: 1 | T77: GWh/yr | U77: Nanoramic Laboratories | V77: https://nanoramic.com/ | W77: Boston | X77: MA | Y77: US | Z77: MK | AA77: 45902 | AB77: https://www.energy.gov/articles/biden-harris-administration-announces-actions-strengthen-clean-energy-supply-chains-and; https://www.ctinsider.com/business/article/ct-bridgeport-nanoramic-laboratories-battery-18526507.php; https://fundraiseinsider.com/blog/nanoramic-laboratories/ | AD77: Nanoramic Laboratories is a U.S. company that has developed Neocarbonix™, an advanced electrode technology designed to improve performance and lower the cost of lithium-ion battery manufacturing. | AF77: =IF(LEN(TRIM(AD77))=0,0,LEN(TRIM(AD77))-LEN(SUBSTITUTE(AD77," ",""))+1) -> 26
A78: 4062 | B78: Commercial | C78: Midstream | D78: Nanotech Energy | E78: Yes | F78: Nanotech Energy | G78: Cylindrical cells | H78: Cell | I78: https://nanotechenergy.com/ | J78: 12100 Wilshire Blvd., Suite 800 | K78: Los Angeles | L78: CA | M78: US | N78: 90025 | O78: 800-995-5491 | P78: 34.043757 | Q78: -118.46756 | R78: 23 | S78: 0.15 | T78: GWh/yr | U78: Nanotech Energy | V78: https://nanotechenergy.com/ | W78: Los Angeles | X78: CA | Y78: US | Z78: VP MK | AA78: 8/6/2022 8/27/2025 | AB78: nanotechenergy.com; BNEF: 2020 Battery Startups; Pitchbook.com | AC78: Developing a non-flammable advanced Li-ion battery for the electric and portable electronics markets based on graphene; Won CES Innovation award 2022; Cylindrical (18650 & 21700) cells | AD78: Nanotech Energy delivers safe and efficient super material-based solutions for cutting-edge products. | AE78: https://nanotechenergy.com/, https://nanotechenergy.com/about-us/ | AF78: =IF(LEN(TRIM(AD78))=0,0,LEN(TRIM(AD78))-LEN(SUBSTITUTE(AD78," ",""))+1) -> 12
A79: 4063 | B79: Commercial | C79: Midstream | D79: Navitas Systems, LLC | E79: Yes | F79: Navitas Systems Venture Drive | G79: Pouch cells | H79: Nickel manganese cobalt | I79: https://www.navitassys.com/ | J79: 4880 Venture Drive | K79: Ann Arbor | L79: MI | M79: US | N79: 48108 | O79: 734-205-1400 | P79: 42.288839 | Q79: -83.847446 | R79: 118 | S79: 0.1 | T79: GWh/yr | U79: Navitas Systems LLC | V79: https://www.navitassys.com/ | W79: Lisle | X79: IL | Y79: US | Z79: VP MK | AA79: 8/7/2022 8/27/2025 | AB79: navitassys.com; Questionnaire; https://www.zoominfo.com/c/navitas-systems-llc/356127778; https://www.areadevelopment.com/newsitems/2-11-2021/navitas-systems-pittsfield-scio-michigan.shtml | AD79: Navitas Systems specializes in comprehensive energy storage solutions, manufacturing lithium cells and products for commercial and U.S. government/military customers. Its capabilities include advanced chemistries, electronics, system integration, and more. | AE79: https://www.navitassys.com/, https://www.navitassys.com/about-us/ | AF79: =IF(LEN(TRIM(AD79))=0,0,LEN(TRIM(AD79))-LEN(SUBSTITUTE(AD79," ",""))+1) -> 29
A80: 4064 | B80: Under construction | C80: Midstream | D80: NextStar Energy (Stellantis - LG Energy Solution JV) | E80: No | F80: Windsor Gigafactory | G80: Cylindrical & Prismatic cells | H80: Other/ Unknown | I80: https://www.stellantis.com/en/news/press-releases/2022/march/stellantis-and-lg-energy-solution-to-invest-over-5-billion-cad-in-joint-venture-for-first-large-scale-lithium-Ion-battery-production-plant-in-canada | K80: Windsor | L80: ON | M80: Canada | N80: N8W 3Y3 | P80: 42.296902 | Q80: -82.98576 | R80: 2500 (Planned) | S80: 49.5 | T80: GWh/yr | U80: Stellantis - LG Energy Solution JV | V80: https://www.stellantis.com/en | W80: Hoofddorp Seoul | X80: North Holland Gyeonggi | Y80: Netherlands, Republic of Korea | Z80: VP MK | AA80: 6/19/2023 8/27/2025 | AB80: https://www.stellantis.com/en/news/press-releases/2022/march/stellantis-and-lg-energy-solution-to-invest-over-5-billion-cad-in-joint-venture-for-first-large-scale-lithium-Ion-battery-production-plant-in-canada; BNEF Interactive Dataset Cell manufacturing; https://moparinsiders.com/stellantis-close-to-an-agreement-to-resume-construction-of-windsor-gigafactory/; https://www.am800cklw.com/news/operations-at-nextstar-energy-back-to-normal-following-temporary-work-stoppage-wednesday.html | AC80: Construction scheduled to start at the end of 2022 with production in Q1 2024; Construction is on hold as of 6/19/2023 due to disagreement with government, but the 2 sides are close to a deal; Construction resumed and with projected SOP of 2025 | AD80: Stellantis and LG Energy Solution's joint venture, NextStar Energy, aims to establish Canada's first major EV battery facility in Windsor, Ontario, focusing on lithium-ion battery production for Stellantis vehicle requirements. | AE80: https://www.stellantis.com/en/news/press-releases/2022/may/stellantis-and-samsung-announce-battery-plant-in-kokomo | AF80: =IF(LEN(TRIM(AD80))=0,0,LEN(TRIM(AD80))-LEN(SUBSTITUTE(AD80," ",""))+1) -> 30
A81: 4065 | B81: Cancelled | C81: Midstream | D81: Northvolt | E81: No | F81: Northvolt Six | G81: Other/ Unknown cells | H81: Nickel manganese cobalt | I81: https://northvolt.com/manufacturing/six/ | J81: Saint-Basile-le-Grand and McMasterville, suburbs of Montreal | K81: Montreal | L81: QC | M81: Canada | P81: 45.533333 | Q81: -73.283333 | R81: 3000 (Planned) | S81: 60 | T81: GWh/yr | U81: Northvolt | V81: https://northvolt.com/ | W81: Stockholm | Y81: Sweden | Z81: VP AP MK | AA81: 12/31/2023 9/25/2024 8/27/2025 | AB81: https://northvolt.com/ https://www.reuters.com/business/autos-transportation/swedens-northvolt-build-52-bln-battery-factory-canada-2023-09-28/; Battery Atlas; https://northvolt.com/manufacturing/six/; https://lyten.com/2025/08/07/lyten-to-acquire-all-remaining-northvolt-assets-in-sweden-and-germany/ | AC81: Production in 2026, reaching full capacity in 2028; Will have a full circular plant - recycling batteries into new batteries; unclear when the recycling plant will be included. $5.2B investment; Northvolt went bankrupt; Lyten acquired assets in Sweden and Germany, Canada plans TBD. | AD81: Northvolt produces batteries with clean energy to deliver batteries with a 90% lower carbon footprint than those using coal. | AF81: =IF(LEN(TRIM(AD81))=0,0,LEN(TRIM(AD81))-LEN(SUBSTITUTE(AD81," ",""))+1) -> 19
A82: 4102 | B82: Commercial | C82: Midstream | D82: Nuvvon Inc | E82: No | F82: Nuvvon US Lab | G82: Cell | H82: Solid-state battery | I82: https://nuvvon.com/ | J82: 4 Century Drive, Suite 350, Floor 3 | K82: Parsippany | L82: NJ | M82: US | N82: 07054 | P82: 40.8667 | Q82: -74.4011 | R82: 9 | S82: 10 | T82: Ah | U82: Nuvvon Inc | V82: https://nuvvon.com/ | W82: Parsippany | X82: NJ | Y82: US | Z82: MK | AA82: 45867 | AB82: https://nuvvon.com/nuvvon-opens-new-u-s-lab-to-support-growth-and-insource-cell-building/, https://www.azom.com/news.aspx?newsID=64690, https://pitchbook.com/profiles/company/510508-09 | AD82: Nuvvon is a solid-state battery materials company developing next-generation energy storage solutions. | AF82: =IF(LEN(TRIM(AD82))=0,0,LEN(TRIM(AD82))-LEN(SUBSTITUTE(AD82," ",""))+1) -> 12
A83: 4066 | B83: Commercial | C83: Midstream | D83: Our Next Energy, Inc. | E83: No | F83: ONE Circle Gigafactory | G83: Prismatic Cells | H83: Lithium iron phosphate | I83: https://one.ai/ | J83: 42060 Ecorse Rd. | K83: Belleville | L83: MI | M83: US | N83: 48111 | O83: 248-677-1010 | P83: 42.245867 | Q83: -83.546254 | R83: 2100 (Planned) | S83: 0.01 | T83: GWh/yr | U83: Our Next Energy, Inc. | V83: https://one.ai/ | W83: Novi | X83: MI | Y83: US | Z83: VP MK | AA83: 6/11/2023 8/27/2025 | AB83: BNEF Cell Database; prnewswire.com/news-releases/battery-startup-our-next-energy-one-closes-series-a-led-by-breakthrough-energy-ventures-301400984.html; BNEF Cell Database; https://one.ai/our-next-energy-helps-gov-whitmer-unveil-make-it-in-michigan-plan | AC83: Developer of transformative battery technology intended to significantly improve range while lowering the cost of batteries and electric propulsion systems. The company uses machine learning and artificial intelligence to improve the life and safety of high-energy-density batteries and offers long-lasting power solutions enabling OEMs (Original Equipment Manufacturers) to reach the market range expectations. | AD83: Our Next Energy is doubling the EV range, prioritizing safety with innovative chemistries, and building a North American supply chain with abundant materials for cost-effective, resilient batteries. | AE83: https://one.ai/, https://one.ai/mission | AF83: =IF(LEN(TRIM(AD83))=0,0,LEN(TRIM(AD83))-LEN(SUBSTITUTE(AD83," ",""))+1) -> 27
A84: 4067 | B84: Under construction | C84: Midstream | D84: Panasonic | E84: Yes | F84: De Soto Facility | G84: Cylindrical cells | H84: Nickel manganese cobalt, NCA | I84: https://automotive.na.panasonic.com/ev-energy | J84: 10301 Astra Pkwy | K84: De Soto | L84: KS | M84: US | N84: 66018 | P84: 38.940931 | Q84: -95.00654 | R84: 4000 (Planned) | S84: 30 | T84: GWh/yr | U84: Panasonic | V84: https://na.panasonic.com/ | W84: Kadoma | X84: Osaka | Y84: Japan | Z84: VP AP MK | AA84: 6/11/2023 8/23/2024 8/27/2025 | AB84: https://rethinkresearch.biz/articles/panasonic-name-de-soto-kansas-for-next-us-battery-plant/; https://insideevs.com/news/598071/panasonic-new-us-battery-plant-kansas/; https://na.panasonic.com/us/news/panasonic-awards-turner-yates-contract-build-ev-battery-plant; https://lawrencekstimes.com/2025/07/14/panasonic-grand-opening/ | AC84: Plans to reach 32 Gwh once ramped up to full capacity | AD84: With a century of experience making batteries, Panasonic is now focused on batteries for EVs that boast high safety, high capacity, and high energy density and building a factory in Kansas. | AE84: https://na.panasonic.com/us/, https://na.panasonic.com/us/who-we-are | AF84: =IF(LEN(TRIM(AD84))=0,0,LEN(TRIM(AD84))-LEN(SUBSTITUTE(AD84," ",""))+1) -> 31
A85: 4068 | B85: Pre-commercial/ startup | C85: Midstream | D85: Piersica | E85: Yes | F85: Piersica | G85: Cell | H85: Solid-state battery | I85: https://piersica.com/ | J85: 10801 NW 42nd Ct | K85: Sunrise | L85: FL | M85: US | N85: 33351 | P85: 26.17838 | Q85: -80.292374 | R85: 9 | U85: Piersica | V85: https://piersica.com/ | W85: Sunrise | X85: FL | Y85: US | Z85: SD AP | AA85: 7/1/2024 and 8/8/2024 | AB85: www.piersica.com https://pitchbook.com/profiles/company/438418-63#timeline | AD85: Piersica is a developer of solid-state lithium batteries for safe electric propulsion and energy storage, using proprietary technology for high-rate li-metal anodes, solid separators, and high-voltage cathodes to enhance environmental sustainability. | AE85: https://piersica.com/ | AF85: =IF(LEN(TRIM(AD85))=0,0,LEN(TRIM(AD85))-LEN(SUBSTITUTE(AD85," ",""))+1) -> 31 | AG85: Claudiu Bucur | AH85: claudiu.b.bucur@outlook.com | AI85: (954) 682-9520
A86: 4069 | B86: Under construction | C86: Midstream | D86: Pomega Energy Storage Technologies | E86: Yes | F86: Colleton County Battery Plant | G86: Other/ Unknown cells | H86: LFP | I86: https://tr.pomega.com/en/pomega-energy-storage-technologies-breaks-ground-for-new-lithium-ion-battery-plant/ | K86: Walterboro | L86: SC | M86: US | N86: 29488 | P86: 32.905007 | Q86: -80.668965 | R86: 575 (Planned) | S86: 3 | T86: GWh/yr | U86: Kontrolmatik Technologies | V86: https://www.kontrolmatik.com/en/ | W86: Istanbul | Y86: Türkiye | Z86: VP MK | AA86: 6/19/2023 8/27/2025 | AB86: Charged-the-book.com; https://governor.sc.gov/news/2022-12/kontrolmatik-technologies-establishing-operations-colleton-county; https://rebusinessonline.com/pomega-energy-storage-breaks-ground-on-300m-lithium-battery-plant-near-charleston/; https://charlestonbusiness.com/news/manufacturing/83129/ | AC86: Production expected in 2024; Would like to expand to 6GWh; $300M investment; focused on ESS | AD86: Pomega Energy, a Kontrolmatik subsidiary, breaks ground on a U.S. lithium-ion battery plant in South Carolina. It will manufacture lithium iron phosphate cells and assemble turnkey energy storage systems. | AE86: https://tr.pomega.com/en/pomega-energy-storage-technologies-breaks-ground-for-new-lithium-ion-battery-plant/ | AF86: =IF(LEN(TRIM(AD86))=0,0,LEN(TRIM(AD86))-LEN(SUBSTITUTE(AD86," ",""))+1) -> 29
